package kawa.lib; import kawa.lang.SyntaxTemplate;

public class syntax extends gnu.expr.ModuleBody { private static void $runBody$() { ; gnu.lists.Consumer $result = getInstanceconsumer;
  }
  

  public static final kawa.lang.Macro defmacro;
  
  public static final kawa.lang.Macro define$Mnmacro;
  
  public static final kawa.lang.Macro define$Mnsyntax$Mncase;
  
  public static final kawa.lang.Macro begin$Mnfor$Mnsyntax;
  
  public static final kawa.lang.Macro define$Mnfor$Mnsyntax;
  
  public static final kawa.lang.Macro when;
  
  public static final kawa.lang.Macro unless;
  
  public static final kawa.lang.Macro try$Mnfinally;
  
  public static final kawa.lang.Macro jdField_synchronized;
  
  public static final kawa.lang.Macro let$Mnvalues;
  
  public static final kawa.lang.Macro let$St$Mnvalues;
  
  public static final kawa.lang.Macro case$Mnlambda;
  
  public static final kawa.lang.Macro define$Mnvalues;
  
  public static final kawa.lang.Macro define$Mnalias$Mnparameter;
  
  public static final kawa.lang.Macro $bracket$Mnlist$;
  
  public static final kawa.lang.Macro $string$;
  
  public static final kawa.lang.Macro $string$Mnwith$Mndefault$Mnformat$;
  
  public static final kawa.lang.Macro $format$;
  
  public static final kawa.lang.Macro $sprintf$;
  
  public static final kawa.lang.Macro $string$Mnwith$Mndelimiter$Mnmarks$;
  
  public static final kawa.lang.Macro define$Mnsimple$Mnconstructor;
  
  public static final gnu.kawa.reflect.StaticFieldLocation $Prvt$define$Mnsyntax;
  
  public static final gnu.kawa.reflect.StaticFieldLocation $Prvt$define;
  
  public static final gnu.kawa.reflect.StaticFieldLocation $Prvt$define$Mnconstant;
  
  public static final gnu.kawa.reflect.StaticFieldLocation $Prvt$if;
  
  public static final gnu.kawa.reflect.StaticFieldLocation $Prvt$try$Mncatch;
  
  public static final gnu.kawa.reflect.StaticFieldLocation $Prvt$let;
  
  public static final gnu.kawa.reflect.StaticFieldLocation $Prvt$_;
  
  public static final gnu.kawa.reflect.StaticFieldLocation $Prvt$set$Mncdr$Ex;
  
  public static final gnu.kawa.reflect.StaticFieldLocation $Prvt$car;
  
  public static final gnu.kawa.reflect.StaticFieldLocation $Prvt$cdr;
  
  public static final gnu.kawa.reflect.StaticFieldLocation $Prvt$cadr;
  
  public static final gnu.kawa.reflect.StaticFieldLocation $Prvt$cddr;
  
  public static final gnu.kawa.reflect.StaticFieldLocation $Prvt$begin;
  
  public static final gnu.kawa.reflect.StaticFieldLocation $Prvt$call$Mnwith$Mnvalues;
  
  public static final gnu.kawa.reflect.StaticFieldLocation $Prvt$lambda;
  
  public static final gnu.kawa.reflect.StaticFieldLocation $Prvt$list;
  
  public static final gnu.kawa.reflect.StaticFieldLocation $Prvt$not;
  
  public static final gnu.kawa.reflect.StaticFieldLocation $Prvt$quasiquote;
  
  public static final gnu.kawa.reflect.StaticFieldLocation $Prvt$quote;
  
  public static final gnu.kawa.reflect.StaticFieldLocation $Prvt$set$Ex;
  
  public static final gnu.kawa.reflect.StaticFieldLocation $Prvt$syntax$Mnrules;
  
  public static final kawa.lang.Macro $Prvt$$Pcsimple$Mnconstruct$Mnbuilder;
  
  static final kawa.lang.SyntaxPattern Lit0;
  
  static final kawa.lang.SyntaxPattern Lit1;
  
  static final SyntaxTemplate Lit2;
  
  static final kawa.lang.SyntaxPattern Lit3;
  
  static final SyntaxTemplate Lit4;
  
  static final SyntaxTemplate Lit5;
  
  static final kawa.lang.SyntaxPattern Lit6;
  
  static final SyntaxTemplate Lit7;
  
  static final kawa.lang.SyntaxPattern Lit8;
  
  static final SyntaxTemplate Lit9;
  
  static final SyntaxTemplate Lit10;
  
  static final kawa.lang.SyntaxPattern Lit11;
  
  static final kawa.lang.SyntaxPattern Lit12;
  
  static final SyntaxTemplate Lit13;
  static final kawa.lang.SyntaxPattern Lit14;
  static final SyntaxTemplate Lit15;
  static final SyntaxTemplate Lit16;
  static final SyntaxTemplate Lit17;
  static final kawa.lang.SyntaxPattern Lit18;
  static final SyntaxTemplate Lit19;
  static final kawa.lang.SyntaxPattern Lit20;
  static final kawa.lang.SyntaxPattern Lit21;
  static final SyntaxTemplate Lit22;
  static final kawa.lang.SyntaxPattern Lit23;
  static final SyntaxTemplate Lit24;
  static final SyntaxTemplate Lit25;
  static final kawa.lang.SyntaxPattern Lit26;
  static final SyntaxTemplate Lit27;
  static final SyntaxTemplate Lit28;
  static final kawa.lang.SyntaxPattern Lit29;
  static final SyntaxTemplate Lit30;
  static final kawa.lang.SyntaxPattern Lit31;
  static final kawa.lang.SyntaxPattern Lit32;
  static final SyntaxTemplate Lit33;
  static final kawa.lang.SyntaxPattern Lit34;
  static final SyntaxTemplate Lit35;
  static final SyntaxTemplate Lit36;
  static final kawa.lang.SyntaxPattern Lit37;
  static final SyntaxTemplate Lit38;
  static final SyntaxTemplate Lit39;
  public static syntax $instance;
  static final gnu.mapping.SimpleSymbol Lit40;
  static final kawa.lang.SyntaxRules Lit41;
  static final gnu.mapping.SimpleSymbol Lit42;
  static final kawa.lang.SyntaxRules Lit43;
  static final gnu.mapping.SimpleSymbol Lit44;
  static final kawa.lang.SyntaxRules Lit45;
  static final gnu.mapping.SimpleSymbol Lit46;
  static final kawa.lang.SyntaxRules Lit47;
  static final gnu.mapping.SimpleSymbol Lit48;
  static final kawa.lang.SyntaxRules Lit49;
  static final gnu.mapping.SimpleSymbol Lit50;
  static final kawa.lang.SyntaxPattern Lit51;
  static final SyntaxTemplate Lit52;
  static final SyntaxTemplate Lit53;
  static final gnu.mapping.SimpleSymbol Lit54;
  static final kawa.lang.SyntaxPattern Lit55;
  static final SyntaxTemplate Lit56;
  static final SyntaxTemplate Lit57;
  static final gnu.mapping.SimpleSymbol Lit58;
  static final kawa.lang.SyntaxPattern Lit59;
  static final gnu.mapping.SimpleSymbol Lit60;
  static final SyntaxTemplate Lit61;
  static final SyntaxTemplate Lit62;
  static final gnu.mapping.SimpleSymbol Lit63;
  static final kawa.lang.SyntaxRules Lit64;
  static final gnu.mapping.SimpleSymbol Lit65;
  static final kawa.lang.SyntaxPattern Lit66;
  static final SyntaxTemplate Lit67;
  static final kawa.lang.SyntaxPattern Lit68;
  static final SyntaxTemplate Lit69;
  static final kawa.lang.SyntaxPattern Lit70;
  static final SyntaxTemplate Lit71;
  static final kawa.lang.SyntaxPattern Lit72;
  static final SyntaxTemplate Lit73;
  static final kawa.lang.SyntaxPattern Lit74;
  static final SyntaxTemplate Lit75;
  static final kawa.lang.SyntaxPattern Lit76;
  static final SyntaxTemplate Lit77;
  static final SyntaxTemplate Lit78;
  static final SyntaxTemplate Lit79;
  static final SyntaxTemplate Lit80;
  static final SyntaxTemplate Lit81;
  static final SyntaxTemplate Lit82;
  static final SyntaxTemplate Lit83;
  static final SyntaxTemplate Lit84;
  static final SyntaxTemplate Lit85;
  static final SyntaxTemplate Lit86;
  static final SyntaxTemplate Lit87;
  static final kawa.lang.SyntaxPattern Lit88;
  static final SyntaxTemplate Lit89;
  static final SyntaxTemplate Lit90;
  static final SyntaxTemplate Lit91;
  static final SyntaxTemplate Lit92;
  static final SyntaxTemplate Lit93;
  static final SyntaxTemplate Lit94;
  static final SyntaxTemplate Lit95;
  static final SyntaxTemplate Lit96;
  static final SyntaxTemplate Lit97;
  static final SyntaxTemplate Lit98;
  static final SyntaxTemplate Lit99;
  static final SyntaxTemplate Lit100;
  static final SyntaxTemplate Lit101;
  static final gnu.mapping.SimpleSymbol Lit102;
  static final kawa.lang.SyntaxRules Lit103;
  static final gnu.mapping.SimpleSymbol Lit104;
  static final kawa.lang.SyntaxPattern Lit105;
  static final SyntaxTemplate Lit106;
  static final SyntaxTemplate Lit107;
  static final kawa.lang.SyntaxPattern Lit108;
  static final SyntaxTemplate Lit109;
  static final SyntaxTemplate Lit110;
  static final kawa.lang.SyntaxPattern Lit111;
  static final kawa.lang.SyntaxPattern Lit112;
  static final SyntaxTemplate Lit113;
  static final gnu.mapping.SimpleSymbol Lit114;
  static final kawa.lang.SyntaxRules Lit115;
  static final gnu.mapping.SimpleSymbol Lit116;
  static final kawa.lang.SyntaxRules Lit117;
  static final gnu.mapping.SimpleSymbol Lit118;
  static final kawa.lang.SyntaxPattern Lit119;
  static final SyntaxTemplate Lit120;
  static final SyntaxTemplate Lit121;
  static final SyntaxTemplate Lit122;
  static final SyntaxTemplate Lit123;
  static final SyntaxTemplate Lit124;
  static final SyntaxTemplate Lit125;
  static final SyntaxTemplate Lit126;
  static final gnu.mapping.SimpleSymbol Lit127;
  static final kawa.lang.SyntaxRules Lit128;
  static final gnu.mapping.SimpleSymbol Lit129;
  static final kawa.lang.SyntaxRules Lit130;
  static final gnu.mapping.SimpleSymbol Lit131;
  static final kawa.lang.SyntaxRules Lit132;
  static final gnu.mapping.SimpleSymbol Lit133;
  static final kawa.lang.SyntaxRules Lit134;
  static final gnu.mapping.SimpleSymbol Lit135;
  static final kawa.lang.SyntaxRules Lit136;
  static final gnu.mapping.SimpleSymbol Lit137;
  static final kawa.lang.SyntaxPattern Lit138;
  static final SyntaxTemplate Lit139;
  static final SyntaxTemplate Lit140;
  static final SyntaxTemplate Lit141;
  static final SyntaxTemplate Lit142;
  static final kawa.lang.SyntaxPattern Lit143;
  static final SyntaxTemplate Lit144;
  static final gnu.mapping.SimpleSymbol Lit145;
  static final kawa.lang.SyntaxRules Lit146;
  static final gnu.mapping.SimpleSymbol Lit147;
  static final Object[] Lit148;
  static final gnu.mapping.SimpleSymbol Lit149;
  static final Object[] Lit150;
  static final Object[] Lit151;
  static final gnu.mapping.SimpleSymbol Lit152;
  static final gnu.expr.Keyword Lit153;
  static final gnu.expr.Keyword Lit154;
  static final gnu.lists.PairWithPosition Lit155;
  static final gnu.math.IntNum Lit156;
  static final gnu.expr.Keyword Lit157;
  static final gnu.mapping.SimpleSymbol Lit158;
  static final gnu.mapping.SimpleSymbol Lit159;
  static final gnu.mapping.SimpleSymbol Lit160;
  static final gnu.lists.PairWithPosition Lit161;
  static final gnu.expr.Keyword Lit162;
  static final gnu.lists.PairWithPosition Lit163;
  static final gnu.math.IntNum Lit164;
  static final gnu.lists.PairWithPosition Lit165;
  static final gnu.expr.Keyword Lit166;
  static final Object[] Lit167;
  static final gnu.lists.PairWithPosition Lit168;
  static final Object[] Lit169;
  static final gnu.mapping.SimpleSymbol Lit170;
  static final gnu.math.IntNum Lit171;
  static final gnu.lists.PairWithPosition Lit172;
  static final gnu.mapping.SimpleSymbol Lit173;
  static final gnu.mapping.SimpleSymbol Lit174;
  static final gnu.mapping.SimpleSymbol Lit175;
  static final gnu.mapping.SimpleSymbol Lit176;
  static final gnu.lists.PairWithPosition Lit177;
  static final gnu.mapping.SimpleSymbol Lit178;
  static final gnu.lists.PairWithPosition Lit179;
  static final gnu.mapping.SimpleSymbol Lit180;
  static final gnu.mapping.SimpleSymbol Lit181;
  static final gnu.mapping.SimpleSymbol Lit182;
  static final gnu.mapping.SimpleSymbol Lit183;
  static final gnu.mapping.SimpleSymbol Lit184;
  static final gnu.mapping.SimpleSymbol Lit185;
  static final gnu.mapping.SimpleSymbol Lit186;
  static final gnu.lists.PairWithPosition Lit187;
  static final gnu.lists.PairWithPosition Lit188;
  static final gnu.mapping.SimpleSymbol Lit189;
  static final gnu.mapping.SimpleSymbol Lit190;
  static final gnu.mapping.SimpleSymbol Lit191;
  static final gnu.mapping.SimpleSymbol Lit192;
  static final Object[] Lit193;
  static final Object[] Lit194;
  static final Object[] Lit195;
  static final Object[] Lit196;
  static final gnu.mapping.SimpleSymbol Lit197;
  static final gnu.mapping.SimpleSymbol Lit198;
  static final gnu.mapping.SimpleSymbol Lit199;
  static final gnu.mapping.SimpleSymbol Lit200;
  static final Object[] Lit201;
  static final gnu.mapping.SimpleSymbol Lit202;
  static final Object[] Lit203;
  static final gnu.mapping.SimpleSymbol Lit204;
  static final gnu.lists.PairWithPosition Lit205;
  static final Object[] Lit206;
  public int match1(gnu.expr.ModuleMethod paramModuleMethod, Object paramObject, gnu.mapping.CallContext paramCallContext)
  {
    switch (selector) {case 7:  value1 = paramObject;proc = paramModuleMethod;pc = 1;return 0;
    case 6: 
      value1 = paramObject;proc = paramModuleMethod;pc = 1;return 0; case 5:  value1 = paramObject;proc = paramModuleMethod;pc = 1;return 0;
    case 4: 
      value1 = paramObject;proc = paramModuleMethod;pc = 1;return 0;
    case 3: 
      value1 = paramObject;proc = paramModuleMethod;pc = 1;return 0;
    case 2: 
      value1 = paramObject;proc = paramModuleMethod;pc = 1;return 0;
    case 1: 
      value1 = paramObject;proc = paramModuleMethod;pc = 1;return 0; } return super.match1(paramModuleMethod, paramObject, paramCallContext); }
  static Object lambda1(Object x) { Object localObject = x;Object[] arrayOfObject = kawa.lang.SyntaxPattern.allocVars(2, null);
    

    kawa.lang.TemplateScope localTemplateScope = kawa.lang.TemplateScope.make();
    localTemplateScope = kawa.lang.TemplateScope.make();return Lit51.match(x, arrayOfObject, 0) ? new gnu.expr.TryExp(kawa.lang.SyntaxForms.rewrite(Lit52.execute(arrayOfObject, localTemplateScope)), kawa.lang.SyntaxForms.rewrite(Lit53.execute(arrayOfObject, localTemplateScope))) : kawa.standard.syntax_case.error("syntax-case", x);
  }
  
  static Object lambda2(Object x) {
    Object localObject = x;Object[] arrayOfObject = kawa.lang.SyntaxPattern.allocVars(2, null);
    

    kawa.lang.TemplateScope localTemplateScope = kawa.lang.TemplateScope.make();
    localTemplateScope = kawa.lang.TemplateScope.make();return Lit55.match(x, arrayOfObject, 0) ? new gnu.expr.SynchronizedExp(kawa.lang.SyntaxForms.rewrite(Lit56.execute(arrayOfObject, localTemplateScope)), kawa.lang.SyntaxForms.rewriteBody(Lit57.execute(arrayOfObject, localTemplateScope))) : kawa.standard.syntax_case.error("syntax-case", x);
  }
  
  static Object lambda3(Object form)
  {
    Object localObject = form;Object[] arrayOfObject = kawa.lang.SyntaxPattern.allocVars(2, null); kawa.lang.TemplateScope localTemplateScope; if (Lit59.match(form, arrayOfObject, 0))
    {
      gnu.mapping.CallContext $ctx = kawa.lang.TemplateScope.make();int i = $ctx.startFromContext(); try { kawa.lib.scheme.eval.eval$X(std_syntax.syntaxObject$To$Datum(new gnu.lists.Pair(Lit60, Lit61.execute(arrayOfObject, $ctx))), $ctx = gnu.mapping.CallContext.getInstance()); } finally { $ctx.cleanupFromContext(i);throw finally; }
      localTemplateScope = kawa.lang.TemplateScope.make(); } return gnu.expr.KawaConvert.isTrue($ctx.getFromContext(i)) ? Lit62.execute(arrayOfObject, localTemplateScope) : kawa.standard.syntax_case.error("syntax-case", form);
  }
  










  static Object lambda4(Object form)
  {
    Object localObject1 = form;Object[] arrayOfObject = kawa.lang.SyntaxPattern.allocVars(8, null);
    


    kawa.lang.TemplateScope localTemplateScope1 = kawa.lang.TemplateScope.make();
    


    localTemplateScope1 = kawa.lang.TemplateScope.make();
    
    localTemplateScope1 = kawa.lang.TemplateScope.make();
    

    localTemplateScope1 = kawa.lang.TemplateScope.make();
    

    localTemplateScope1 = kawa.lang.TemplateScope.make();
    




    kawa.lang.TemplateScope localTemplateScope2 = kawa.lang.TemplateScope.make();localTemplateScope2 = kawa.lang.TemplateScope.make();Object xvar = std_syntax.datum$To$Syntax(Lit77.execute(arrayOfObject, localTemplateScope2), std_syntax.syntax$To$Datum(Lit78.execute(arrayOfObject, localTemplateScope2)));
    localTemplateScope2 = kawa.lang.TemplateScope.make();
    


    localTemplateScope2 = kawa.lang.TemplateScope.make();localTemplateScope2 = kawa.lang.TemplateScope.make();Object xvar = std_syntax.datum$To$Syntax(Lit89.execute(arrayOfObject, localTemplateScope2), std_syntax.syntax$To$Datum(Lit90.execute(arrayOfObject, localTemplateScope2)));
    localTemplateScope2 = kawa.lang.TemplateScope.make();return Lit88.match(form, arrayOfObject, 0) ? kawa.lang.Quote.append$V(new Object[] { Lit91.execute(arrayOfObject, localTemplateScope2), gnu.lists.Pair.make(kawa.lang.Quote.append$V(new Object[] { Lit92.execute(arrayOfObject, localTemplateScope2), gnu.lists.Pair.make(kawa.lang.Quote.append$V(new Object[] { Lit93.execute(arrayOfObject, localTemplateScope2), xvar }), gnu.lists.Pair.make(kawa.lang.Quote.append$V(new Object[] { Lit94.execute(arrayOfObject, localTemplateScope2), gnu.lists.Pair.make(kawa.lang.Quote.append$V(new Object[] { Lit95.execute(arrayOfObject, localTemplateScope2), gnu.lists.Pair.make(kawa.lang.Quote.append$V(new Object[] { Lit96.execute(arrayOfObject, localTemplateScope2), kawa.lang.Quote.consX$V(new Object[] { xvar, Lit97.execute(arrayOfObject, localTemplateScope2) }) }), Lit98.execute(arrayOfObject, localTemplateScope2)) }), Lit99.execute(arrayOfObject, localTemplateScope2)) }), Lit100.execute(arrayOfObject, localTemplateScope2))) }), Lit101.execute(arrayOfObject, localTemplateScope2)) }) : Lit76.match(form, arrayOfObject, 0) ? kawa.lang.Quote.append$V(new Object[] { Lit79.execute(arrayOfObject, localTemplateScope2), gnu.lists.Pair.make(kawa.lang.Quote.append$V(new Object[] { Lit80.execute(arrayOfObject, localTemplateScope2), kawa.lang.Quote.consX$V(new Object[] { xvar, Lit81.execute(arrayOfObject, localTemplateScope2) }) }), kawa.lang.Quote.append$V(new Object[] { Lit82.execute(arrayOfObject, localTemplateScope2), gnu.lists.Pair.make(kawa.lang.Quote.append$V(new Object[] { Lit83.execute(arrayOfObject, localTemplateScope2), gnu.lists.Pair.make(kawa.lang.Quote.append$V(new Object[] { Lit84.execute(arrayOfObject, localTemplateScope2), kawa.lang.Quote.consX$V(new Object[] { xvar, Lit85.execute(arrayOfObject, localTemplateScope2) }) }), Lit86.execute(arrayOfObject, localTemplateScope2)) }), Lit87.execute(arrayOfObject, localTemplateScope2)) })) }) : Lit74.match(form, arrayOfObject, 0) ? Lit75.execute(arrayOfObject, localTemplateScope1) : Lit72.match(form, arrayOfObject, 0) ? Lit73.execute(arrayOfObject, localTemplateScope1) : Lit70.match(form, arrayOfObject, 0) ? Lit71.execute(arrayOfObject, localTemplateScope1) : Lit68.match(form, arrayOfObject, 0) ? Lit69.execute(arrayOfObject, localTemplateScope1) : Lit66.match(form, arrayOfObject, 0) ? Lit67.execute(arrayOfObject, localTemplateScope1) : kawa.standard.syntax_case.error("syntax-case", form);
  }
  










  static Object lambda5(Object form)
  {
    frame $heapFrame = new frame();Object localObject = form;$unnamed$0 = kawa.lang.SyntaxPattern.allocVars(1, null);
    
    kawa.lang.TemplateScope localTemplateScope = kawa.lang.TemplateScope.make();
    return Lit105.match(form, $unnamed$0, 0) ? kawa.lang.Quote.append$V(new Object[] { Lit106.execute($unnamed$0, localTemplateScope), $heapFrame.lambda6loop(localTemplateScope, Lit107.execute($unnamed$0, localTemplateScope)) }) : kawa.standard.syntax_case.error("syntax-case", form);
  }
  


































































  static Object $PcStringFormatFormat(Object default$Mnformat, Object forms)
  {
    Object localObject = forms;Object[] arrayOfObject = kawa.lang.SyntaxPattern.allocVars(3, null);
    

    kawa.lang.TemplateScope localTemplateScope = kawa.lang.TemplateScope.make();
    
    localTemplateScope = kawa.lang.TemplateScope.make();localTemplateScope = kawa.lang.TemplateScope.make();
    
    localTemplateScope = kawa.lang.TemplateScope.make();
    
    localTemplateScope = kawa.lang.TemplateScope.make();
    
    localTemplateScope = kawa.lang.TemplateScope.make();return Lit8.match(forms, arrayOfObject, 0) ? lists.cons(Lit9.execute(arrayOfObject, localTemplateScope), $PcStringFormatFormat(default$Mnformat, Lit10.execute(arrayOfObject, localTemplateScope))) : Lit6.match(forms, arrayOfObject, 0) ? lists.cons(default$Mnformat, $PcStringFormatFormat(default$Mnformat, Lit7.execute(arrayOfObject, localTemplateScope))) : Lit3.match(forms, arrayOfObject, 0) ? lists.cons(Lit4.execute(arrayOfObject, localTemplateScope), $PcStringFormatFormat(default$Mnformat, Lit5.execute(arrayOfObject, localTemplateScope))) : Lit1.match(forms, arrayOfObject, 0) ? $PcStringFormatEnclosedFormat(default$Mnformat, Lit2.execute(arrayOfObject, localTemplateScope)) : Lit0.match(forms, arrayOfObject, 0) ? gnu.lists.LList.Empty : kawa.standard.syntax_case.error("syntax-case", forms);
  }
  
  static Object $PcStringFormatEnclosedFormat(Object default$Mnformat, Object forms)
  {
    Object localObject = forms;Object[] arrayOfObject = kawa.lang.SyntaxPattern.allocVars(2, null);
    

    kawa.lang.TemplateScope localTemplateScope = kawa.lang.TemplateScope.make();
    
    localTemplateScope = kawa.lang.TemplateScope.make();
    localTemplateScope = kawa.lang.TemplateScope.make();
    
    localTemplateScope = kawa.lang.TemplateScope.make();return Lit18.match(forms, arrayOfObject, 0) ? lists.cons(default$Mnformat, $PcStringFormatEnclosedFormat(default$Mnformat, Lit19.execute(arrayOfObject, localTemplateScope))) : Lit14.match(forms, arrayOfObject, 0) ? lists.cons(kawa.lang.Quote.append$V(new Object[] { Lit15.execute(arrayOfObject, localTemplateScope), kawa.lang.Quote.consX$V(new Object[] { default$Mnformat, Lit16.execute(arrayOfObject, localTemplateScope) }) }), $PcStringFormatEnclosedFormat(default$Mnformat, Lit17.execute(arrayOfObject, localTemplateScope))) : Lit12.match(forms, arrayOfObject, 0) ? $PcStringFormatFormat(default$Mnformat, Lit13.execute(arrayOfObject, localTemplateScope)) : Lit11.match(forms, arrayOfObject, 0) ? gnu.lists.LList.Empty : kawa.standard.syntax_case.error("syntax-case", forms);
  }
  
  static Object $PcStringFormatArgs(Object forms) {
    for (;;) { Object localObject = forms;Object[] arrayOfObject = kawa.lang.SyntaxPattern.allocVars(3, null);
      

      kawa.lang.TemplateScope localTemplateScope = kawa.lang.TemplateScope.make();
      
      localTemplateScope = kawa.lang.TemplateScope.make();
      
      localTemplateScope = kawa.lang.TemplateScope.make(); if (!Lit29.match(forms, arrayOfObject, 0))
        break;
      localTemplateScope = kawa.lang.TemplateScope.make();forms = Lit30.execute(arrayOfObject, localTemplateScope); } return Lit26.match(forms, arrayOfObject, 0) ? kawa.lang.Quote.append$V(new Object[] { Lit27.execute(arrayOfObject, localTemplateScope), $PcStringFormatArgs(Lit28.execute(arrayOfObject, localTemplateScope)) }) : Lit23.match(forms, arrayOfObject, 0) ? kawa.lang.Quote.append$V(new Object[] { Lit24.execute(arrayOfObject, localTemplateScope), $PcStringFormatArgs(Lit25.execute(arrayOfObject, localTemplateScope)) }) : Lit21.match(forms, arrayOfObject, 0) ? $PcStringFormatEnclosedArgs(Lit22.execute(arrayOfObject, localTemplateScope)) : Lit20.match(forms, arrayOfObject, 0) ? gnu.lists.LList.Empty : kawa.standard.syntax_case.error("syntax-case", forms);
  }
  
  static Object $PcStringFormatEnclosedArgs(Object forms) {
    Object localObject = forms;Object[] arrayOfObject = kawa.lang.SyntaxPattern.allocVars(2, null);
    

    kawa.lang.TemplateScope localTemplateScope = kawa.lang.TemplateScope.make();
    
    localTemplateScope = kawa.lang.TemplateScope.make();
    
    localTemplateScope = kawa.lang.TemplateScope.make();return Lit37.match(forms, arrayOfObject, 0) ? kawa.lang.Quote.append$V(new Object[] { Lit38.execute(arrayOfObject, localTemplateScope), $PcStringFormatEnclosedArgs(Lit39.execute(arrayOfObject, localTemplateScope)) }) : Lit34.match(forms, arrayOfObject, 0) ? kawa.lang.Quote.append$V(new Object[] { Lit35.execute(arrayOfObject, localTemplateScope), $PcStringFormatEnclosedArgs(Lit36.execute(arrayOfObject, localTemplateScope)) }) : Lit32.match(forms, arrayOfObject, 0) ? $PcStringFormatArgs(Lit33.execute(arrayOfObject, localTemplateScope)) : Lit31.match(forms, arrayOfObject, 0) ? gnu.lists.LList.Empty : kawa.standard.syntax_case.error("syntax-case", forms);
  }
  
  static Object lambda7(Object form) {
    Object localObject = form;Object[] arrayOfObject = kawa.lang.SyntaxPattern.allocVars(3, null);
    
    kawa.lang.TemplateScope localTemplateScope = kawa.lang.TemplateScope.make();
    




    return Lit119.match(form, arrayOfObject, 0) ? kawa.lang.Quote.append$V(new Object[] { Lit120.execute(arrayOfObject, localTemplateScope), gnu.lists.Pair.make(kawa.lang.Quote.append$V(new Object[] { Lit121.execute(arrayOfObject, localTemplateScope), gnu.lists.Pair.make(kawa.lang.Quote.append$V(new Object[] { Lit122.execute(arrayOfObject, localTemplateScope), $PcStringFormatFormat(Lit123.execute(arrayOfObject, localTemplateScope), Lit124.execute(arrayOfObject, localTemplateScope)) }), Lit125.execute(arrayOfObject, localTemplateScope)) }), $PcStringFormatArgs(Lit126.execute(arrayOfObject, localTemplateScope))) }) : kawa.standard.syntax_case.error("syntax-case", form);
  }
  
  static
  {
    gnu.mapping.SimpleSymbol tmp15_12 = gnu.mapping.Symbol.valueOf("$format$");Lit131 = tmp15_12;(syntax.Lit206 = new Object[1])[0] = tmp15_12;Lit205 = gnu.lists.PairWithPosition.make(syntax.Lit176 = gnu.mapping.Symbol.valueOf("quote"), gnu.lists.PairWithPosition.make(gnu.mapping.Symbol.valueOf("toString"), gnu.lists.LList.Empty, "/mnt/hgfs/trunk/kawaForAndroid/kawa-2.4/kawa/lib/syntax.scm", 1048612), "/mnt/hgfs/trunk/kawaForAndroid/kawa-2.4/kawa/lib/syntax.scm", 1048612);Lit204 = gnu.mapping.Symbol.valueOf("invoke");(syntax.Lit203 = new Object[1])[0] = gnu.mapping.Symbol.valueOf("$splice$");Lit202 = gnu.mapping.Symbol.valueOf("string-append"); Object[] tmp102_99 = (syntax.Lit201 = new Object[2]); gnu.mapping.SimpleSymbol tmp110_107 = gnu.mapping.Symbol.valueOf("%define-macro");Lit200 = tmp110_107;tmp102_99[0] = tmp110_107; gnu.mapping.SimpleSymbol tmp122_119 = gnu.mapping.Symbol.valueOf("lambda");Lit181 = tmp122_119;tmp102_99[1] = tmp122_119;Lit199 = gnu.mapping.Symbol.valueOf("form");Lit198 = gnu.mapping.Symbol.valueOf("define-syntax");Lit197 = gnu.mapping.Symbol.valueOf("if"); Object[] tmp161_158 = (syntax.Lit196 = new Object[2]); gnu.mapping.SimpleSymbol tmp169_166 = gnu.mapping.Symbol.valueOf("call-with-values");Lit183 = tmp169_166;tmp161_158[0] = tmp169_166;tmp161_158[1] = Lit181;(syntax.Lit195 = new Object[1])[0] = "bind";(syntax.Lit194 = new Object[1])[0] = gnu.mapping.Symbol.valueOf("x");(syntax.Lit193 = new Object[1])[0] = "mktmp";Lit192 = gnu.mapping.Symbol.valueOf("car");Lit191 = gnu.mapping.Symbol.valueOf("cddr");Lit190 = gnu.mapping.Symbol.valueOf("set-cdr!");Lit189 = gnu.mapping.Symbol.valueOf("cadr");Lit188 = gnu.lists.PairWithPosition.make(gnu.mapping.Symbol.valueOf("list"), gnu.lists.LList.Empty, "/mnt/hgfs/trunk/kawaForAndroid/kawa-2.4/kawa/lib/syntax.scm", 610316);Lit187 = gnu.lists.PairWithPosition.make(syntax.Lit185 = gnu.mapping.Symbol.valueOf("v"), gnu.lists.LList.Empty, "/mnt/hgfs/trunk/kawaForAndroid/kawa-2.4/kawa/lib/syntax.scm", 626700);Lit186 = gnu.mapping.Symbol.valueOf("set!");Lit184 = gnu.mapping.Symbol.valueOf("let");Lit182 = gnu.mapping.Symbol.valueOf("define");Lit180 = gnu.mapping.Symbol.valueOf("wt");Lit179 = gnu.lists.PairWithPosition.make(syntax.Lit156 = gnu.math.IntNum.valueOf(1), gnu.lists.LList.Empty, "/mnt/hgfs/trunk/kawaForAndroid/kawa-2.4/kawa/lib/syntax.scm", 1183809);Lit178 = gnu.mapping.Symbol.valueOf("as");Lit177 = gnu.lists.PairWithPosition.make(gnu.mapping.Symbol.valueOf("arg"), gnu.lists.LList.Empty, "/mnt/hgfs/trunk/kawaForAndroid/kawa-2.4/kawa/lib/syntax.scm", 753674);Lit175 = gnu.mapping.Symbol.valueOf("gnu.mapping.LocationProc");Lit174 = gnu.mapping.Symbol.valueOf("constant-fold");Lit173 = gnu.mapping.Symbol.valueOf("gnu.kawa.functions.Format");Lit172 = gnu.lists.PairWithPosition.make(gnu.math.IntNum.valueOf(-2), gnu.lists.LList.Empty, "/mnt/hgfs/trunk/kawaForAndroid/kawa-2.4/kawa/lib/syntax.scm", 1196075);Lit171 = gnu.math.IntNum.valueOf(0);Lit170 = gnu.mapping.Symbol.valueOf("gnu.lists.Range$IntRange"); gnu.expr.Keyword tmp469_466 = gnu.expr.Keyword.make(">");Lit157 = tmp469_466;(syntax.Lit169 = new Object[1])[0] = tmp469_466;Lit168 = gnu.lists.PairWithPosition.make(syntax.Lit158 = gnu.mapping.Symbol.valueOf("$lookup$"), gnu.lists.Pair.make(syntax.Lit159 = gnu.mapping.Symbol.valueOf("gnu.kawa.functions.RangeUtils"), gnu.lists.Pair.make(gnu.lists.Pair.make(syntax.Lit160 = gnu.mapping.Symbol.valueOf("quasiquote"), gnu.lists.Pair.make(gnu.mapping.Symbol.valueOf("valueOfUnbounded"), gnu.lists.LList.Empty)), gnu.lists.LList.Empty)), "/mnt/hgfs/trunk/kawaForAndroid/kawa-2.4/kawa/lib/syntax.scm", 1183760); gnu.expr.Keyword tmp555_552 = gnu.expr.Keyword.make("<");Lit153 = tmp555_552;(syntax.Lit167 = new Object[1])[0] = tmp555_552;Lit166 = gnu.expr.Keyword.make("by");Lit165 = gnu.lists.PairWithPosition.make(Boolean.TRUE, gnu.lists.LList.Empty, "/mnt/hgfs/trunk/kawaForAndroid/kawa-2.4/kawa/lib/syntax.scm", 1155132);Lit164 = gnu.math.IntNum.valueOf(-1);Lit163 = gnu.lists.PairWithPosition.make(Lit158, gnu.lists.Pair.make(Lit159, gnu.lists.Pair.make(gnu.lists.Pair.make(Lit160, gnu.lists.Pair.make(gnu.mapping.Symbol.valueOf("downto"), gnu.lists.LList.Empty)), gnu.lists.LList.Empty)), "/mnt/hgfs/trunk/kawaForAndroid/kawa-2.4/kawa/lib/syntax.scm", 1159186);Lit162 = gnu.expr.Keyword.make(">=");Lit161 = gnu.lists.PairWithPosition.make(Boolean.FALSE, gnu.lists.LList.Empty, "/mnt/hgfs/trunk/kawaForAndroid/kawa-2.4/kawa/lib/syntax.scm", 1151035);Lit155 = gnu.lists.PairWithPosition.make(Lit158, gnu.lists.Pair.make(Lit159, gnu.lists.Pair.make(gnu.lists.Pair.make(Lit160, gnu.lists.Pair.make(gnu.mapping.Symbol.valueOf("upto"), gnu.lists.LList.Empty)), gnu.lists.LList.Empty)), "/mnt/hgfs/trunk/kawaForAndroid/kawa-2.4/kawa/lib/syntax.scm", 1150994);Lit154 = gnu.expr.Keyword.make("<=");Lit152 = gnu.mapping.Symbol.valueOf("args");Lit151 = new Object[0]; gnu.mapping.SimpleSymbol tmp751_748 = gnu.mapping.Symbol.valueOf("$>>$");Lit149 = tmp751_748;(syntax.Lit150 = new Object[1])[0] = tmp751_748; gnu.mapping.SimpleSymbol tmp771_768 = gnu.mapping.Symbol.valueOf("$<<$");Lit147 = tmp771_768;(syntax.Lit148 = new Object[1])[0] = tmp771_768; Object[] tmp784_781 = new Object[2]; Object[] tmp785_784 = tmp784_781;tmp785_784[0] = Lit147;tmp785_784[1] = Lit149; kawa.lang.SyntaxRule[] tmp800_797 = new kawa.lang.SyntaxRule[5]; kawa.lang.SyntaxRule[] tmp801_800 = tmp800_797;tmp801_800[0] = new kawa.lang.SyntaxRule(new kawa.lang.SyntaxPattern("\f\030\f\007\f\017,\r\027\020\b\b\f\002\033", Lit148, 4, "syntax.scm:327"), "\001\001\003\000", "\t\003\b\t\013\021\025\023\021\030\004\032", Lit148, 1); kawa.lang.SyntaxRule[] tmp838_801 = tmp801_800;tmp838_801[1] = new kawa.lang.SyntaxRule(new kawa.lang.SyntaxPattern("\f\030\f\007\f\017,\r\027\020\b\b\f\002\b", Lit150, 3, "syntax.scm:329"), "\001\001\003", "\t\003\b\025\023", Lit151, 1); kawa.lang.SyntaxRule[] tmp875_838 = tmp838_801;tmp875_838[2] = new kawa.lang.SyntaxRule(new kawa.lang.SyntaxPattern("\f\030\f\007\f\017,\r\027\020\b\b\f\002\033", Lit150, 4, "syntax.scm:331"), "\001\001\003\000", "\t\003\021\025\023\b\t\013\032", Lit151, 1); kawa.lang.SyntaxRule[] tmp912_875 = tmp875_838; Object[] tmp945_942 = new Object[1]; gnu.mapping.SimpleSymbol tmp953_950 = gnu.mapping.Symbol.valueOf("%simple-construct-builder");Lit145 = tmp953_950;tmp945_942[0] = tmp953_950;tmp912_875[3] = new kawa.lang.SyntaxRule(new kawa.lang.SyntaxPattern("\f\030\f\007\f\017,\r\027\020\b\b\f\037#", Lit151, 5, "syntax.scm:333"), "\001\001\003\001\000", "\021\030\004\t\003\t\013)\021\025\023\b\033\"", tmp945_942, 1);tmp912_875[4] = new kawa.lang.SyntaxRule(new kawa.lang.SyntaxPattern("\f\030\f\007\f\017,\r\027\020\b\b\b", Lit151, 3, "syntax.scm:335"), "\001\001\003", "\t\003\b\t\013\b\025\023", Lit151, 1);Lit146 = new kawa.lang.SyntaxRules(tmp784_781, tmp800_797, 5, Lit145); Object[] tmp1023_1020 = new Object[2]; Object[] tmp1024_1023 = tmp1023_1020; gnu.mapping.SimpleSymbol tmp1032_1029 = gnu.mapping.Symbol.valueOf("define-simple-constructor");Lit137 = tmp1032_1029;tmp1024_1023[0] = tmp1032_1029; gnu.mapping.SimpleSymbol tmp1044_1041 = gnu.mapping.Symbol.valueOf("$string$");Lit127 = tmp1044_1041;tmp1024_1023[1] = gnu.lists.PairWithPosition.make(tmp1044_1041, gnu.lists.LList.Empty, "/mnt/hgfs/trunk/kawaForAndroid/kawa-2.4/kawa/lib/syntax.scm", 1323062);Lit144 = new SyntaxTemplate("\001\001", "\021\030\004\t\003\t\013\030\f", tmp1023_1020, 0);Lit143 = new kawa.lang.SyntaxPattern("\f\030\f\007\f\017\b", Lit151, 2, "syntax.scm:322"); Object[] tmp1102_1099 = new Object[4]; Object[] tmp1103_1102 = tmp1102_1099;tmp1103_1102[0] = gnu.mapping.Symbol.valueOf("syntax-rules"); Object[] tmp1112_1103 = tmp1103_1102;tmp1112_1103[1] = gnu.lists.PairWithPosition.make(gnu.mapping.Symbol.valueOf("_"), Lit152, "/mnt/hgfs/trunk/kawaForAndroid/kawa-2.4/kawa/lib/syntax.scm", 1310737); Object[] tmp1133_1112 = tmp1112_1103;tmp1133_1112[2] = Lit145;tmp1133_1112[3] = gnu.lists.PairWithPosition.make(gnu.lists.LList.Empty, Lit152, "/mnt/hgfs/trunk/kawaForAndroid/kawa-2.4/kawa/lib/syntax.scm", 1314887);Lit142 = new SyntaxTemplate("\001\001\001", "\b\021\030\004\t\020\b\021\030\f\b\021\030\024\t\013\t\023\030\034", tmp1102_1099, 0);Lit141 = new SyntaxTemplate("\001\001\001", "\030\004", new Object[] { gnu.lists.Pair.make(Lit198, gnu.lists.LList.Empty) }, 0);Lit140 = new SyntaxTemplate("\001\001\001", "\003", Lit151, 0);Lit139 = new SyntaxTemplate("\001\001\001", "\003", Lit151, 0);Lit138 = new kawa.lang.SyntaxPattern("\f\030\f\007\f\017\f\027\b", Lit151, 3, "syntax.scm:316"); Object[] tmp1264_1261 = new Object[4]; Object[] tmp1265_1264 = tmp1264_1261;tmp1265_1264[0] = Lit153; Object[] tmp1271_1265 = tmp1265_1264;tmp1271_1265[1] = Lit154; Object[] tmp1277_1271 = tmp1271_1265;tmp1277_1271[2] = Lit157;tmp1277_1271[3] = Lit162; kawa.lang.SyntaxRule[] tmp1293_1290 = new kawa.lang.SyntaxRule[14]; kawa.lang.SyntaxRule[] tmp1294_1293 = tmp1293_1290; Object[] tmp1327_1324 = new Object[3]; Object[] tmp1328_1327 = tmp1327_1324;tmp1328_1327[0] = Lit155; Object[] tmp1334_1328 = tmp1328_1327;tmp1334_1328[1] = Lit156;tmp1334_1328[2] = Lit161;tmp1294_1293[0] = new kawa.lang.SyntaxRule(new kawa.lang.SyntaxPattern("\f\030\f\007\f\002\f\017\b", Lit167, 2, "syntax.scm:281"), "\001\001", "\021\030\004\t\003\t\f\t\013\030\024", tmp1327_1324, 0); kawa.lang.SyntaxRule[] tmp1350_1294 = tmp1294_1293; Object[] tmp1390_1387 = new Object[3]; Object[] tmp1391_1390 = tmp1390_1387;tmp1391_1390[0] = Lit155; Object[] tmp1397_1391 = tmp1391_1390;tmp1397_1391[1] = Lit156;tmp1397_1391[2] = Lit165;tmp1350_1294[1] = new kawa.lang.SyntaxRule(new kawa.lang.SyntaxPattern("\f\030\f\007\f\002\f\017\b", new Object[] { Lit154 }, 2, "syntax.scm:282"), "\001\001", "\021\030\004\t\003\t\f\t\013\030\024", tmp1390_1387, 0); kawa.lang.SyntaxRule[] tmp1413_1350 = tmp1350_1294; Object[] tmp1446_1443 = new Object[3]; Object[] tmp1447_1446 = tmp1446_1443;tmp1447_1446[0] = Lit163; Object[] tmp1453_1447 = tmp1447_1446;tmp1453_1447[1] = Lit164;tmp1453_1447[2] = Lit161;tmp1413_1350[2] = new kawa.lang.SyntaxRule(new kawa.lang.SyntaxPattern("\f\030\f\007\f\002\f\017\b", Lit169, 2, "syntax.scm:283"), "\001\001", "\021\030\004\t\003\t\f\t\013\030\024", tmp1446_1443, 0); kawa.lang.SyntaxRule[] tmp1469_1413 = tmp1413_1350; Object[] tmp1509_1506 = new Object[3]; Object[] tmp1510_1509 = tmp1509_1506;tmp1510_1509[0] = Lit163; Object[] tmp1516_1510 = tmp1510_1509;tmp1516_1510[1] = Lit164;tmp1516_1510[2] = Lit165;tmp1469_1413[3] = new kawa.lang.SyntaxRule(new kawa.lang.SyntaxPattern("\f\030\f\007\f\002\f\017\b", new Object[] { Lit162 }, 2, "syntax.scm:284"), "\001\001", "\021\030\004\t\003\t\f\t\013\030\024", tmp1509_1506, 0); kawa.lang.SyntaxRule[] tmp1532_1469 = tmp1469_1413; Object[] tmp1549_1546 = new Object[2]; Object[] tmp1550_1549 = tmp1549_1546;tmp1550_1549[0] = Lit166;tmp1550_1549[1] = Lit153; Object[] tmp1578_1575 = new Object[2]; Object[] tmp1579_1578 = tmp1578_1575;tmp1579_1578[0] = Lit155;tmp1579_1578[1] = Lit161;tmp1532_1469[4] = new kawa.lang.SyntaxRule(new kawa.lang.SyntaxPattern("\f\030\f\007\f\002\f\017\f\n\f\027\b", tmp1549_1546, 3, "syntax.scm:285"), "\001\001\001", "\021\030\004\t\003\t\013\t\023\030\f", tmp1578_1575, 0); kawa.lang.SyntaxRule[] tmp1595_1532 = tmp1532_1469; Object[] tmp1612_1609 = new Object[2]; Object[] tmp1613_1612 = tmp1612_1609;tmp1613_1612[0] = Lit166;tmp1613_1612[1] = Lit154; Object[] tmp1641_1638 = new Object[2]; Object[] tmp1642_1641 = tmp1641_1638;tmp1642_1641[0] = Lit155;tmp1642_1641[1] = Lit165;tmp1595_1532[5] = new kawa.lang.SyntaxRule(new kawa.lang.SyntaxPattern("\f\030\f\007\f\002\f\017\f\n\f\027\b", tmp1612_1609, 3, "syntax.scm:286"), "\001\001\001", "\021\030\004\t\003\t\013\t\023\030\f", tmp1641_1638, 0); kawa.lang.SyntaxRule[] tmp1658_1595 = tmp1595_1532; Object[] tmp1676_1673 = new Object[2]; Object[] tmp1677_1676 = tmp1676_1673;tmp1677_1676[0] = Lit166;tmp1677_1676[1] = Lit157; Object[] tmp1705_1702 = new Object[2]; Object[] tmp1706_1705 = tmp1705_1702;tmp1706_1705[0] = Lit163;tmp1706_1705[1] = Lit161;tmp1658_1595[6] = new kawa.lang.SyntaxRule(new kawa.lang.SyntaxPattern("\f\030\f\007\f\002\f\017\f\n\f\027\b", tmp1676_1673, 3, "syntax.scm:287"), "\001\001\001", "\021\030\004\t\003\t\013\t\023\030\f", tmp1705_1702, 0); kawa.lang.SyntaxRule[] tmp1722_1658 = tmp1658_1595; Object[] tmp1740_1737 = new Object[2]; Object[] tmp1741_1740 = tmp1740_1737;tmp1741_1740[0] = Lit166;tmp1741_1740[1] = Lit162; Object[] tmp1769_1766 = new Object[2]; Object[] tmp1770_1769 = tmp1769_1766;tmp1770_1769[0] = Lit163;tmp1770_1769[1] = Lit165;tmp1722_1658[7] = new kawa.lang.SyntaxRule(new kawa.lang.SyntaxPattern("\f\030\f\007\f\002\f\017\f\n\f\027\b", tmp1740_1737, 3, "syntax.scm:288"), "\001\001\001", "\021\030\004\t\003\t\013\t\023\030\f", tmp1769_1766, 0); kawa.lang.SyntaxRule[] tmp1786_1722 = tmp1722_1658; Object[] tmp1820_1817 = new Object[2]; Object[] tmp1821_1820 = tmp1820_1817;tmp1821_1820[0] = Lit168;tmp1821_1820[1] = Lit179;tmp1786_1722[8] = new kawa.lang.SyntaxRule(new kawa.lang.SyntaxPattern("\f\030\f\007\f\002\b", Lit167, 1, "syntax.scm:289"), "\001", "\021\030\004\t\003\030\f", tmp1820_1817, 0); kawa.lang.SyntaxRule[] tmp1837_1786 = tmp1786_1722;tmp1837_1786[9] = new kawa.lang.SyntaxRule(new kawa.lang.SyntaxPattern("\f\030\f\007\f\002\f\017\b", new Object[] { Lit166 }, 2, "syntax.scm:290"), "\001\001", "\021\030\004\t\003\b\013", new Object[] { Lit168 }, 0); kawa.lang.SyntaxRule[] tmp1889_1837 = tmp1837_1786; Object[] tmp1907_1904 = new Object[2]; Object[] tmp1908_1907 = tmp1907_1904;tmp1908_1907[0] = Lit166;tmp1908_1907[1] = gnu.expr.Keyword.make("size");tmp1889_1837[10] = new kawa.lang.SyntaxRule(new kawa.lang.SyntaxPattern("\f\030\f\007\f\002\f\017\f\n\f\027\b", tmp1907_1904, 3, "syntax.scm:291"), "\001\001\001", "\021\030\004\t\003\t\013\b\023", new Object[] { gnu.lists.PairWithPosition.make(Lit158, gnu.lists.Pair.make(Lit159, gnu.lists.Pair.make(gnu.lists.Pair.make(Lit160, gnu.lists.Pair.make(gnu.mapping.Symbol.valueOf("bySize"), gnu.lists.LList.Empty)), gnu.lists.LList.Empty)), "/mnt/hgfs/trunk/kawaForAndroid/kawa-2.4/kawa/lib/syntax.scm", 1191967) }, 0); kawa.lang.SyntaxRule[] tmp1989_1889 = tmp1889_1837;tmp1989_1889[11] = new kawa.lang.SyntaxRule(new kawa.lang.SyntaxPattern("\f\030\f\002\b", Lit167, 0, "syntax.scm:292"), "", "\030\004", new Object[] { gnu.lists.Pair.make(Lit170, gnu.lists.PairWithPosition.make(Lit171, gnu.lists.PairWithPosition.make(Lit156, Lit172, "/mnt/hgfs/trunk/kawaForAndroid/kawa-2.4/kawa/lib/syntax.scm", 1196073), "/mnt/hgfs/trunk/kawaForAndroid/kawa-2.4/kawa/lib/syntax.scm", 1196071)) }, 0); kawa.lang.SyntaxRule[] tmp2064_1989 = tmp1989_1889;tmp2064_1989[12] = new kawa.lang.SyntaxRule(new kawa.lang.SyntaxPattern("\f\030\f\002\b", Lit169, 0, "syntax.scm:293"), "", "\030\004", new Object[] { gnu.lists.Pair.make(Lit170, gnu.lists.PairWithPosition.make(Lit171, gnu.lists.PairWithPosition.make(Lit164, Lit172, "/mnt/hgfs/trunk/kawaForAndroid/kawa-2.4/kawa/lib/syntax.scm", 1200169), "/mnt/hgfs/trunk/kawaForAndroid/kawa-2.4/kawa/lib/syntax.scm", 1200167)) }, 0);tmp2064_1989[13] = new kawa.lang.SyntaxRule(new kawa.lang.SyntaxPattern("\f\030\003", Lit151, 1, "syntax.scm:294"), "\000", "\021\030\004\002", new Object[] { gnu.mapping.Symbol.valueOf("constant-vector") }, 0);Lit136 = new kawa.lang.SyntaxRules(tmp1264_1261, tmp1293_1290, 3, syntax.Lit135 = gnu.mapping.Symbol.valueOf("$bracket-list$"));Lit134 = new kawa.lang.SyntaxRules(Lit151, new kawa.lang.SyntaxRule[] { new kawa.lang.SyntaxRule(new kawa.lang.SyntaxPattern("\f\030\f\007\013", Lit151, 2, "syntax.scm:276"), "\001\000", "\021\030\004\t\003\n", new Object[] { gnu.lists.PairWithPosition.make(Lit158, gnu.lists.Pair.make(Lit173, gnu.lists.Pair.make(gnu.lists.Pair.make(Lit160, gnu.lists.Pair.make(gnu.mapping.Symbol.valueOf("sprintfToString"), gnu.lists.LList.Empty)), gnu.lists.LList.Empty)), "/mnt/hgfs/trunk/kawaForAndroid/kawa-2.4/kawa/lib/syntax.scm", 1134599) }, 0) }, 2, syntax.Lit133 = gnu.mapping.Symbol.valueOf("$sprintf$")); kawa.lang.SyntaxRule[] tmp2325_2322 = new kawa.lang.SyntaxRule[1]; Object[] tmp2358_2355 = new Object[2]; Object[] tmp2359_2358 = tmp2358_2355;tmp2359_2358[0] = gnu.lists.PairWithPosition.make(Lit158, gnu.lists.Pair.make(Lit173, gnu.lists.Pair.make(gnu.lists.Pair.make(Lit160, gnu.lists.Pair.make(gnu.mapping.Symbol.valueOf("formatToString"), gnu.lists.LList.Empty)), gnu.lists.LList.Empty)), "/mnt/hgfs/trunk/kawaForAndroid/kawa-2.4/kawa/lib/syntax.scm", 1114119);tmp2359_2358[1] = Lit171;tmp2325_2322[0] = new kawa.lang.SyntaxRule(new kawa.lang.SyntaxPattern("\f\030\003", Lit151, 1, "syntax.scm:271"), "\000", "\021\030\004\t\f\002", tmp2358_2355, 0);Lit132 = new kawa.lang.SyntaxRules(Lit151, tmp2325_2322, 1, Lit131); kawa.lang.SyntaxRule[] tmp2435_2432 = new kawa.lang.SyntaxRule[1]; Object[] tmp2468_2465 = new Object[2]; Object[] tmp2469_2468 = tmp2468_2465; gnu.mapping.SimpleSymbol tmp2477_2474 = gnu.mapping.Symbol.valueOf("$string-with-default-format$");Lit118 = tmp2477_2474;tmp2469_2468[0] = tmp2477_2474;tmp2469_2468[1] = "~Q";tmp2435_2432[0] = new kawa.lang.SyntaxRule(new kawa.lang.SyntaxPattern("\f\030\003", Lit151, 1, "syntax.scm:266"), "\000", "\021\030\004\t\f\002", tmp2468_2465, 0);Lit130 = new kawa.lang.SyntaxRules(Lit151, tmp2435_2432, 1, syntax.Lit129 = gnu.mapping.Symbol.valueOf("$string-with-delimiter-marks$")); kawa.lang.SyntaxRule[] tmp2520_2517 = new kawa.lang.SyntaxRule[1]; Object[] tmp2553_2550 = new Object[2]; Object[] tmp2554_2553 = tmp2553_2550;tmp2554_2553[0] = Lit118;tmp2554_2553[1] = "~a";tmp2520_2517[0] = new kawa.lang.SyntaxRule(new kawa.lang.SyntaxPattern("\f\030\003", Lit151, 1, "syntax.scm:261"), "\000", "\021\030\004\t\f\002", tmp2553_2550, 0);Lit128 = new kawa.lang.SyntaxRules(Lit151, tmp2520_2517, 1, Lit127);Lit126 = new SyntaxTemplate("\001\001\000", "\022", Lit151, 0);Lit125 = new SyntaxTemplate("\001\001\000", "\030\004", new Object[] { gnu.lists.Pair.make(Lit205, gnu.lists.LList.Empty) }, 0);Lit124 = new SyntaxTemplate("\001\001\000", "\022", Lit151, 0);Lit123 = new SyntaxTemplate("\001\001\000", "\013", Lit151, 0);Lit122 = new SyntaxTemplate("\001\001\000", "\030\004", new Object[] { gnu.lists.Pair.make(Lit174, gnu.lists.PairWithPosition.make(Lit202, gnu.lists.LList.Empty, "/mnt/hgfs/trunk/kawaForAndroid/kawa-2.4/kawa/lib/syntax.scm", 1032242)) }, 0);Lit121 = new SyntaxTemplate("\001\001\000", "\030\004", new Object[] { gnu.lists.Pair.make(Lit174, gnu.lists.PairWithPosition.make(Lit204, gnu.lists.LList.Empty, "/mnt/hgfs/trunk/kawaForAndroid/kawa-2.4/kawa/lib/syntax.scm", 1028131)) }, 0);Lit120 = new SyntaxTemplate("\001\001\000", "\030\004", new Object[] { gnu.lists.Pair.make(Lit131, gnu.lists.LList.Empty) }, 0);Lit119 = new kawa.lang.SyntaxPattern("\f\007\f\017\023", Lit151, 3, "syntax.scm:250"); kawa.lang.SyntaxRule[] tmp2827_2824 = new kawa.lang.SyntaxRule[1]; Object[] tmp2861_2858 = new Object[22]; Object[] tmp2862_2861 = tmp2861_2858; gnu.mapping.SimpleSymbol tmp2870_2867 = gnu.mapping.Symbol.valueOf("begin");Lit60 = tmp2870_2867;tmp2862_2861[0] = tmp2870_2867; Object[] tmp2875_2862 = tmp2862_2861;tmp2875_2862[1] = gnu.mapping.Symbol.valueOf("define-constant"); Object[] tmp2884_2875 = tmp2875_2862;tmp2884_2875[2] = gnu.mapping.Symbol.valueOf("::"); Object[] tmp2893_2884 = tmp2884_2875;tmp2893_2884[3] = gnu.mapping.Symbol.valueOf("$bracket-apply$"); Object[] tmp2902_2893 = tmp2893_2884;tmp2902_2893[4] = Lit175; Object[] tmp2908_2902 = tmp2902_2893;tmp2908_2902[5] = gnu.lists.PairWithPosition.make(Lit158, gnu.lists.Pair.make(Lit175, gnu.lists.Pair.make(gnu.lists.Pair.make(Lit160, gnu.lists.Pair.make(gnu.mapping.Symbol.valueOf("makeNamed"), gnu.lists.LList.Empty)), gnu.lists.LList.Empty)), "/mnt/hgfs/trunk/kawaForAndroid/kawa-2.4/kawa/lib/syntax.scm", 741380); Object[] tmp2953_2908 = tmp2908_2902;tmp2953_2908[6] = Lit176; Object[] tmp2960_2953 = tmp2953_2908;tmp2960_2953[7] = gnu.lists.PairWithPosition.make(Lit158, gnu.lists.Pair.make(Lit175, gnu.lists.Pair.make(gnu.lists.Pair.make(Lit160, gnu.lists.Pair.make(gnu.mapping.Symbol.valueOf("pushConverter"), gnu.lists.LList.Empty)), gnu.lists.LList.Empty)), "/mnt/hgfs/trunk/kawaForAndroid/kawa-2.4/kawa/lib/syntax.scm", 745481); Object[] tmp3006_2960 = tmp2960_2953;tmp3006_2960[8] = Lit181; Object[] tmp3013_3006 = tmp3006_2960;tmp3013_3006[9] = Lit177; Object[] tmp3020_3013 = tmp3013_3006;tmp3020_3013[10] = gnu.mapping.Symbol.valueOf("try-catch"); Object[] tmp3030_3020 = tmp3020_3013;tmp3030_3020[11] = Lit178; Object[] tmp3037_3030 = tmp3030_3020;tmp3037_3030[12] = Lit177; Object[] tmp3044_3037 = tmp3037_3030;tmp3044_3037[13] = gnu.mapping.Symbol.valueOf("ex"); Object[] tmp3054_3044 = tmp3044_3037;tmp3054_3044[14] = gnu.mapping.Symbol.valueOf("<java.lang.ClassCastException>"); Object[] tmp3064_3054 = tmp3054_3044;tmp3064_3054[15] = Lit184; Object[] tmp3071_3064 = tmp3064_3054;tmp3071_3064[16] = Lit180; Object[] tmp3078_3071 = tmp3071_3064;tmp3078_3071[17] = gnu.lists.PairWithPosition.make(Lit158, gnu.lists.Pair.make(gnu.mapping.Symbol.valueOf("gnu.mapping.WrongType"), gnu.lists.Pair.make(gnu.lists.Pair.make(Lit160, gnu.lists.Pair.make(gnu.mapping.Symbol.valueOf("make"), gnu.lists.LList.Empty)), gnu.lists.LList.Empty)), "/mnt/hgfs/trunk/kawaForAndroid/kawa-2.4/kawa/lib/syntax.scm", 770068); Object[] tmp3127_3078 = tmp3078_3071;tmp3127_3078[18] = gnu.lists.PairWithPosition.make(gnu.lists.PairWithPosition.make(Lit178, gnu.lists.PairWithPosition.make(gnu.mapping.Symbol.valueOf("<int>"), Lit179, "/mnt/hgfs/trunk/kawaForAndroid/kawa-2.4/kawa/lib/syntax.scm", 774160), "/mnt/hgfs/trunk/kawaForAndroid/kawa-2.4/kawa/lib/syntax.scm", 774156), Lit177, "/mnt/hgfs/trunk/kawaForAndroid/kawa-2.4/kawa/lib/syntax.scm", 774156); Object[] tmp3173_3127 = tmp3127_3078;tmp3173_3127[19] = Lit186; Object[] tmp3180_3173 = tmp3173_3127;tmp3180_3173[20] = gnu.lists.PairWithPosition.make(gnu.mapping.Symbol.valueOf("field"), gnu.lists.PairWithPosition.make(Lit180, gnu.lists.PairWithPosition.make(gnu.lists.PairWithPosition.make(Lit176, gnu.lists.PairWithPosition.make(gnu.mapping.Symbol.valueOf("expectedType"), gnu.lists.LList.Empty, "/mnt/hgfs/trunk/kawaForAndroid/kawa-2.4/kawa/lib/syntax.scm", 778261), "/mnt/hgfs/trunk/kawaForAndroid/kawa-2.4/kawa/lib/syntax.scm", 778261), gnu.lists.LList.Empty, "/mnt/hgfs/trunk/kawaForAndroid/kawa-2.4/kawa/lib/syntax.scm", 778260), "/mnt/hgfs/trunk/kawaForAndroid/kawa-2.4/kawa/lib/syntax.scm", 778257), "/mnt/hgfs/trunk/kawaForAndroid/kawa-2.4/kawa/lib/syntax.scm", 778250);tmp3180_3173[21] = gnu.lists.PairWithPosition.make(gnu.lists.PairWithPosition.make(gnu.mapping.Symbol.valueOf("primitive-throw"), gnu.lists.PairWithPosition.make(Lit180, gnu.lists.LList.Empty, "/mnt/hgfs/trunk/kawaForAndroid/kawa-2.4/kawa/lib/syntax.scm", 782357), "/mnt/hgfs/trunk/kawaForAndroid/kawa-2.4/kawa/lib/syntax.scm", 782340), gnu.lists.LList.Empty, "/mnt/hgfs/trunk/kawaForAndroid/kawa-2.4/kawa/lib/syntax.scm", 782340);tmp2827_2824[0] = new kawa.lang.SyntaxRule(new kawa.lang.SyntaxPattern("\f\030\f\007\f\017\f\027\b", Lit151, 3, "syntax.scm:178"), "\001\001\001", "\021\030\004é\021\030\f\t\003\021\030\024A\021\030\034\021\030$\b\013\b\021\030,)\021\0304\b\003\b\023\b\021\030<\t\003\b\021\030D\021\030L\b\021\030T9\021\030\\\t\013\030d\b\021\030l\021\030t\b\021\030|y\b\021\030\b\021\030\021\030l\t\003\030A\021\030\021\030¤\b\013\030¬", tmp2861_2858, 0);Lit117 = new kawa.lang.SyntaxRules(Lit151, tmp2827_2824, 3, syntax.Lit116 = gnu.mapping.Symbol.valueOf("define-alias-parameter")); kawa.lang.SyntaxRule[] tmp3331_3328 = new kawa.lang.SyntaxRule[5]; kawa.lang.SyntaxRule[] tmp3332_3331 = tmp3331_3328; Object[] tmp3365_3362 = new Object[5]; Object[] tmp3366_3365 = tmp3365_3362;tmp3366_3365[0] = Lit182; Object[] tmp3372_3366 = tmp3366_3365;tmp3372_3366[1] = gnu.mapping.Symbol.valueOf("dummy"); Object[] tmp3381_3372 = tmp3372_3366;tmp3381_3372[2] = Lit183; Object[] tmp3387_3381 = tmp3381_3372;tmp3387_3381[3] = Lit181;tmp3387_3381[4] = gnu.lists.PairWithPosition.make(gnu.lists.PairWithPosition.make(Lit181, gnu.lists.PairWithPosition.make(Lit152, Lit161, "/mnt/hgfs/trunk/kawaForAndroid/kawa-2.4/kawa/lib/syntax.scm", 581650), "/mnt/hgfs/trunk/kawaForAndroid/kawa-2.4/kawa/lib/syntax.scm", 581642), gnu.lists.LList.Empty, "/mnt/hgfs/trunk/kawaForAndroid/kawa-2.4/kawa/lib/syntax.scm", 581642);tmp3332_3331[0] = new kawa.lang.SyntaxRule(new kawa.lang.SyntaxPattern("\f\030\f\b\f\007\b", Lit151, 1, "syntax.scm:139"), "\001", "\021\030\004\021\030\f\b\021\030\0249\021\030\034\t\020\b\003\030$", tmp3365_3362, 0); kawa.lang.SyntaxRule[] tmp3439_3332 = tmp3332_3331;tmp3439_3332[1] = new kawa.lang.SyntaxRule(new kawa.lang.SyntaxPattern("\f\030\034\f\007\b\f\017\b", Lit151, 2, "syntax.scm:143"), "\001\001", "\021\030\004\t\003\b\013", new Object[] { Lit182 }, 0); kawa.lang.SyntaxRule[] tmp3483_3439 = tmp3439_3332; Object[] tmp3517_3514 = new Object[14]; Object[] tmp3518_3517 = tmp3517_3514;tmp3518_3517[0] = Lit60; Object[] tmp3524_3518 = tmp3518_3517;tmp3524_3518[1] = Lit182; Object[] tmp3530_3524 = tmp3524_3518;tmp3530_3524[2] = Lit183; Object[] tmp3536_3530 = tmp3530_3524;tmp3536_3530[3] = Lit181; Object[] tmp3542_3536 = tmp3536_3530;tmp3542_3536[4] = Lit188; Object[] tmp3548_3542 = tmp3542_3536;tmp3548_3542[5] = Lit184; Object[] tmp3554_3548 = tmp3548_3542;tmp3554_3548[6] = Lit185; Object[] tmp3561_3554 = tmp3554_3548;tmp3561_3554[7] = Lit189; Object[] tmp3568_3561 = tmp3561_3554;tmp3568_3561[8] = Lit190; Object[] tmp3575_3568 = tmp3568_3561;tmp3575_3568[9] = Lit191; Object[] tmp3582_3575 = tmp3575_3568;tmp3582_3575[10] = Lit187; Object[] tmp3589_3582 = tmp3582_3575;tmp3589_3582[11] = Lit186; Object[] tmp3596_3589 = tmp3589_3582;tmp3596_3589[12] = Lit192;tmp3596_3589[13] = Lit187;tmp3483_3439[2] = new kawa.lang.SyntaxRule(new kawa.lang.SyntaxPattern("\f\030T\f\007\r\017\b\b\026\f\027\b\f\037\b", Lit151, 4, "syntax.scm:145"), "\001\003\001\001", "\021\030\004\021\030\f\t\003\b\021\030\0249\021\030\034\t\020\b\033\030$ę\r\021\030\f\t\013\b\021\030,Q\b\021\0304\b\021\030<\b\003Y\021\030D\t\003\b\021\030L\b\003\030T\b\021\030\f\t\023\b\021\030,Q\b\021\0304\b\021\030<\b\003Y\021\030\\\t\003\b\021\030d\b\003\030l", tmp3517_3514, 1); kawa.lang.SyntaxRule[] tmp3614_3483 = tmp3483_3439; Object[] tmp3648_3645 = new Object[15]; Object[] tmp3649_3648 = tmp3648_3645;tmp3649_3648[0] = Lit60; Object[] tmp3655_3649 = tmp3649_3648;tmp3655_3649[1] = Lit182; Object[] tmp3661_3655 = tmp3655_3649;tmp3661_3655[2] = Lit183; Object[] tmp3667_3661 = tmp3661_3655;tmp3667_3661[3] = Lit181; Object[] tmp3673_3667 = tmp3667_3661;tmp3673_3667[4] = Lit188; Object[] tmp3679_3673 = tmp3673_3667;tmp3679_3673[5] = Lit184; Object[] tmp3685_3679 = tmp3679_3673;tmp3685_3679[6] = Lit185; Object[] tmp3692_3685 = tmp3685_3679;tmp3692_3685[7] = Lit189; Object[] tmp3699_3692 = tmp3692_3685;tmp3699_3692[8] = Lit190; Object[] tmp3706_3699 = tmp3699_3692;tmp3706_3699[9] = Lit191; Object[] tmp3713_3706 = tmp3706_3699;tmp3713_3706[10] = Lit187; Object[] tmp3720_3713 = tmp3713_3706;tmp3720_3713[11] = gnu.mapping.Symbol.valueOf("cdr"); Object[] tmp3730_3720 = tmp3720_3713;tmp3730_3720[12] = Lit186; Object[] tmp3737_3730 = tmp3730_3720;tmp3737_3730[13] = Lit192;tmp3737_3730[14] = Lit187;tmp3614_3483[3] = new kawa.lang.SyntaxRule(new kawa.lang.SyntaxPattern("\f\030D\f\007\r\017\b\b\016\023\f\037\b", Lit151, 4, "syntax.scm:158"), "\001\003\000\001", "\021\030\004\021\030\f\t\003\b\021\030\0249\021\030\034\t\020\b\033\030$ę\r\021\030\f\t\013\b\021\030,Q\b\021\0304\b\021\030<\b\003Y\021\030D\t\003\b\021\030L\b\003\030T\b\021\030\f\t\022\b\021\030,Q\b\021\0304\b\021\030\\\b\003Y\021\030d\t\003\b\021\030l\b\003\030t", tmp3648_3645, 1); Object[] tmp3787_3784 = new Object[4]; Object[] tmp3788_3787 = tmp3787_3784;tmp3788_3787[0] = Lit182; Object[] tmp3794_3788 = tmp3788_3787;tmp3794_3788[1] = Lit183; Object[] tmp3800_3794 = tmp3794_3788;tmp3800_3794[2] = Lit181;tmp3800_3794[3] = Lit188;tmp3614_3483[4] = new kawa.lang.SyntaxRule(new kawa.lang.SyntaxPattern("\f\030\f\007\f\017\b", Lit151, 2, "syntax.scm:171"), "\001\001", "\021\030\004\t\003\b\021\030\f9\021\030\024\t\020\b\013\030\034", tmp3787_3784, 0);Lit115 = new kawa.lang.SyntaxRules(Lit151, tmp3331_3328, 4, syntax.Lit114 = gnu.mapping.Symbol.valueOf("define-values"));Lit113 = new SyntaxTemplate("\000\000", "\n", Lit151, 0);Lit112 = new kawa.lang.SyntaxPattern("\013", Lit151, 2, "syntax.scm:132");Lit111 = new kawa.lang.SyntaxPattern("\b", Lit151, 1, "syntax.scm:130");Lit110 = new SyntaxTemplate("\000\001\000\000", "\032", Lit151, 0);Lit109 = new SyntaxTemplate("\000\001\000\000", "\b\021\030\004\t\013\022", new Object[] { Lit181 }, 0);Lit108 = new kawa.lang.SyntaxPattern("\034\f\017\023\033", Lit151, 4, "syntax.scm:128");Lit107 = new SyntaxTemplate("\000", "\002", Lit151, 0);Lit106 = new SyntaxTemplate("\000", "\030\004", new Object[] { gnu.lists.Pair.make(gnu.lists.PairWithPosition.make(Lit158, gnu.lists.Pair.make(gnu.mapping.Symbol.valueOf("gnu.expr.GenericProc"), gnu.lists.Pair.make(gnu.lists.Pair.make(Lit160, gnu.lists.Pair.make(gnu.mapping.Symbol.valueOf("makeWithoutSorting"), gnu.lists.LList.Empty)), gnu.lists.LList.Empty)), "/mnt/hgfs/trunk/kawaForAndroid/kawa-2.4/kawa/lib/syntax.scm", 512009), gnu.lists.LList.Empty) }, 0);Lit105 = new kawa.lang.SyntaxPattern("\f\030\003", Lit151, 1, "syntax.scm:124");Lit104 = gnu.mapping.Symbol.valueOf("case-lambda"); kawa.lang.SyntaxRule[] tmp4095_4092 = new kawa.lang.SyntaxRule[2]; kawa.lang.SyntaxRule[] tmp4096_4095 = tmp4095_4092;tmp4096_4095[0] = new kawa.lang.SyntaxRule(new kawa.lang.SyntaxPattern("\f\030\f\b\f\007\r\017\b\b\b", Lit151, 2, "syntax.scm:115"), "\001\003", "\021\030\004\t\003\b\r\013", new Object[] { Lit60 }, 1); Object[] tmp4172_4169 = new Object[2]; Object[] tmp4173_4172 = tmp4172_4169; gnu.mapping.SimpleSymbol tmp4181_4178 = gnu.mapping.Symbol.valueOf("let-values");Lit65 = tmp4181_4178;tmp4173_4172[0] = tmp4181_4178; gnu.mapping.SimpleSymbol tmp4193_4190 = gnu.mapping.Symbol.valueOf("let*-values");Lit102 = tmp4193_4190;tmp4173_4172[1] = tmp4193_4190;tmp4096_4095[1] = new kawa.lang.SyntaxRule(new kawa.lang.SyntaxPattern("\f\030<\f\007\r\017\b\b\b\f\027\r\037\030\b\b", Lit151, 4, "syntax.scm:118"), "\001\003\001\003", "\021\030\004\021\b\003\b\021\030\f\031\b\r\013\t\023\b\035\033", tmp4172_4169, 1);Lit103 = new kawa.lang.SyntaxRules(Lit151, tmp4095_4092, 4, Lit102);Lit101 = new SyntaxTemplate("\001\001\001\003\001\003\001", "\020", Lit151, 0);Lit100 = new SyntaxTemplate("\001\001\001\003\001\003\001", "\020", Lit151, 0);Lit99 = new SyntaxTemplate("\001\001\001\003\001\003\001", "\b3", Lit151, 0);Lit98 = new SyntaxTemplate("\001\001\001\003\001\003\001", "\020", Lit151, 0);Lit97 = new SyntaxTemplate("\001\001\001\003\001\003\001", "\020", Lit151, 0);Lit96 = new SyntaxTemplate("\001\001\001\003\001\003\001", "\b\013", Lit151, 0);Lit95 = new SyntaxTemplate("\001\001\001\003\001\003\001", "\b-+", Lit151, 1);Lit94 = new SyntaxTemplate("\001\001\001\003\001\003\001", "\t\003\t\004\b#", Lit195, 0);Lit93 = new SyntaxTemplate("\001\001\001\003\001\003\001", "\b\035\033", Lit151, 1);Lit92 = new SyntaxTemplate("\001\001\001\003\001\003\001", "\030\004", new Object[] { gnu.lists.Pair.make(Lit181, gnu.lists.LList.Empty) }, 0);Lit91 = new SyntaxTemplate("\001\001\001\003\001\003\001", "\021\030\004\b\021\030\f\t\020\b\023", Lit196, 0);Lit90 = new SyntaxTemplate("\001\001\001\003\001\003\001", "\013", Lit151, 0);Lit89 = new SyntaxTemplate("\001\001\001\003\001\003\001", "\030\004", Lit194, 0);Lit88 = new kawa.lang.SyntaxPattern("\f\007\f\002\f\017\f\027,\r\037\030\b\b\f',\r/(\b\b\f7\b", Lit193, 7, "syntax.scm:106");Lit87 = new SyntaxTemplate("\001\001\000\001\003\001\003\001", "\b;", Lit151, 0);Lit86 = new SyntaxTemplate("\001\001\000\001\003\001\003\001", "\020", Lit151, 0);Lit85 = new SyntaxTemplate("\001\001\000\001\003\001\003\001", "\020", Lit151, 0);Lit84 = new SyntaxTemplate("\001\001\000\001\003\001\003\001", "\b\013", Lit151, 0);Lit83 = new SyntaxTemplate("\001\001\000\001\003\001\003\001", "\b53", Lit151, 1);Lit82 = new SyntaxTemplate("\001\001\000\001\003\001\003\001", "\b+", Lit151, 0);Lit81 = new SyntaxTemplate("\001\001\000\001\003\001\003\001", "\020", Lit151, 0);Lit80 = new SyntaxTemplate("\001\001\000\001\003\001\003\001", "\b%#", Lit151, 1);Lit79 = new SyntaxTemplate("\001\001\000\001\003\001\003\001", "\t\003\t\004\t\022\b\033", Lit193, 0);Lit78 = new SyntaxTemplate("\001\001\000\001\003\001\003\001", "\013", Lit151, 0);Lit77 = new SyntaxTemplate("\001\001\000\001\003\001\003\001", "\030\004", Lit194, 0);Lit76 = new kawa.lang.SyntaxPattern("\f\007\f\002\034\f\017\023\f\037,\r' \b\b\f/,\r70\b\b\f?\b", Lit193, 8, "syntax.scm:101"); Object[] tmp4762_4759 = new Object[3]; Object[] tmp4763_4762 = tmp4762_4759;tmp4763_4762[0] = Lit183; Object[] tmp4769_4763 = tmp4763_4762;tmp4769_4763[1] = Lit181;tmp4769_4763[2] = "bind";Lit75 = new SyntaxTemplate("\001\001\001\001\001\001", "\021\030\0049\021\030\f\t\020\b\013\b\021\030\f\t\023\b\t\003\t\024\t\033\t#\b+", tmp4762_4759, 0);Lit74 = new kawa.lang.SyntaxPattern("\f\007\f\002\f\b\f\017\f\027\f\037\f'\f/\b", Lit193, 6, "syntax.scm:95");Lit73 = new SyntaxTemplate("\001\001\001\003\001\001", "\t\003\t\004\t\013\t\023\t\020\031\b\035\033\t#\b+", Lit193, 1);Lit72 = new kawa.lang.SyntaxPattern("\f\007\f\002\\,\f\017\f\027\b\r\037\030\b\b\f'\f/\b", Lit195, 6, "syntax.scm:92");Lit71 = new SyntaxTemplate("\001\001\001", "\021\030\004\t\013\b\023", new Object[] { Lit184 }, 0);Lit70 = new kawa.lang.SyntaxPattern("\f\007\f\002\f\b\f\017\f\027\b", Lit195, 3, "syntax.scm:89"); Object[] tmp4910_4907 = new Object[2]; Object[] tmp4911_4910 = tmp4910_4907;tmp4911_4910[0] = "bind";tmp4911_4910[1] = Lit60;Lit69 = new SyntaxTemplate("\001\003\001\003", "\t\003\t\004\031\b\r\013\t\020\b\021\030\f\t\023\b\035\033", tmp4910_4907, 1);Lit68 = new kawa.lang.SyntaxPattern("\f\007,\r\017\b\b\b\f\027\r\037\030\b\b", Lit151, 4, "syntax.scm:87");Lit67 = new SyntaxTemplate("\001\001\001\000", "\021\030\0049\021\030\f\t\020\b\023\b\021\030\f\t\013\032", Lit196, 0);Lit66 = new kawa.lang.SyntaxPattern("\f\007<,\f\017\f\027\b\b\033", Lit151, 4, "syntax.scm:83"); kawa.lang.SyntaxRule[] tmp5000_4997 = new kawa.lang.SyntaxRule[1]; Object[] tmp5033_5030 = new Object[2]; Object[] tmp5034_5033 = tmp5033_5030; gnu.mapping.SimpleSymbol tmp5042_5039 = gnu.mapping.Symbol.valueOf("begin-for-syntax");Lit58 = tmp5042_5039;tmp5034_5033[0] = tmp5042_5039;tmp5034_5033[1] = Lit182;tmp5000_4997[0] = new kawa.lang.SyntaxRule(new kawa.lang.SyntaxPattern("\f\030\003", Lit151, 1, "syntax.scm:69"), "\000", "\021\030\004\b\021\030\f\002", tmp5033_5030, 0);Lit64 = new kawa.lang.SyntaxRules(Lit151, tmp5000_4997, 1, syntax.Lit63 = gnu.mapping.Symbol.valueOf("define-for-syntax"));Lit62 = new SyntaxTemplate("\001\000", "\030\004", new Object[] { gnu.mapping.Values.empty }, 0);Lit61 = new SyntaxTemplate("\001\000", "\n", Lit151, 0);Lit59 = new kawa.lang.SyntaxPattern("\f\007\013", Lit151, 2, "syntax.scm:63");Lit57 = new SyntaxTemplate("\001\000", "\n", Lit151, 0);Lit56 = new SyntaxTemplate("\001\000", "\003", Lit151, 0);Lit55 = new kawa.lang.SyntaxPattern("\f\030\f\007\013", Lit151, 2, "syntax.scm:54");Lit54 = gnu.mapping.Symbol.valueOf("synchronized");Lit53 = new SyntaxTemplate("\001\001", "\013", Lit151, 0);Lit52 = new SyntaxTemplate("\001\001", "\003", Lit151, 0);Lit51 = new kawa.lang.SyntaxPattern("\f\030\f\007\f\017\b", Lit151, 2, "syntax.scm:46");Lit50 = gnu.mapping.Symbol.valueOf("try-finally"); kawa.lang.SyntaxRule[] tmp5290_5287 = new kawa.lang.SyntaxRule[1]; Object[] tmp5323_5320 = new Object[3]; Object[] tmp5324_5323 = tmp5323_5320;tmp5324_5323[0] = Lit197; Object[] tmp5330_5324 = tmp5324_5323;tmp5330_5324[1] = gnu.mapping.Symbol.valueOf("not");tmp5330_5324[2] = Lit60;tmp5290_5287[0] = new kawa.lang.SyntaxRule(new kawa.lang.SyntaxPattern("\f\030\f\007\r\017\b\b\b", Lit151, 2, "syntax.scm:40"), "\001\003", "\021\030\004)\021\030\f\b\003\b\021\030\024\b\r\013", tmp5323_5320, 1);Lit49 = new kawa.lang.SyntaxRules(Lit151, tmp5290_5287, 2, syntax.Lit48 = gnu.mapping.Symbol.valueOf("unless")); kawa.lang.SyntaxRule[] tmp5377_5374 = new kawa.lang.SyntaxRule[1]; Object[] tmp5410_5407 = new Object[2]; Object[] tmp5411_5410 = tmp5410_5407;tmp5411_5410[0] = Lit197;tmp5411_5410[1] = Lit60;tmp5377_5374[0] = new kawa.lang.SyntaxRule(new kawa.lang.SyntaxPattern("\f\030\f\007\r\017\b\b\b", Lit151, 2, "syntax.scm:36"), "\001\003", "\021\030\004\t\003\b\021\030\f\b\r\013", tmp5410_5407, 1);Lit47 = new kawa.lang.SyntaxRules(Lit151, tmp5377_5374, 2, syntax.Lit46 = gnu.mapping.Symbol.valueOf("when")); kawa.lang.SyntaxRule[] tmp5455_5452 = new kawa.lang.SyntaxRule[1]; Object[] tmp5488_5485 = new Object[5]; Object[] tmp5489_5488 = tmp5488_5485;tmp5489_5488[0] = Lit198; Object[] tmp5495_5489 = tmp5489_5488;tmp5495_5489[1] = Lit181; Object[] tmp5501_5495 = tmp5495_5489;tmp5501_5495[2] = gnu.lists.PairWithPosition.make(Lit199, gnu.lists.LList.Empty, "/mnt/hgfs/trunk/kawaForAndroid/kawa-2.4/kawa/lib/syntax.scm", 131089); Object[] tmp5519_5501 = tmp5501_5495;tmp5519_5501[3] = gnu.mapping.Symbol.valueOf("syntax-case");tmp5519_5501[4] = Lit199;tmp5455_5452[0] = new kawa.lang.SyntaxRule(new kawa.lang.SyntaxPattern("\f\030\f\007\f\017\023", Lit151, 3, "syntax.scm:30"), "\001\001\000", "\021\030\004\t\003\b\021\030\f\021\030\024\b\021\030\034\021\030$\t\013\022", tmp5488_5485, 0);Lit45 = new kawa.lang.SyntaxRules(Lit151, tmp5455_5452, 3, syntax.Lit44 = gnu.mapping.Symbol.valueOf("define-syntax-case")); kawa.lang.SyntaxRule[] tmp5565_5562 = new kawa.lang.SyntaxRule[2]; kawa.lang.SyntaxRule[] tmp5566_5565 = tmp5565_5562;tmp5566_5565[0] = new kawa.lang.SyntaxRule(new kawa.lang.SyntaxPattern("\f\030\034\f\007\013\023", Lit151, 3, "syntax.scm:23"), "\001\000\000", "\021\030\004\t\003\b\021\030\f\t\n\022", Lit201, 0);tmp5566_5565[1] = new kawa.lang.SyntaxRule(new kawa.lang.SyntaxPattern("\f\030\f\007\f\017\b", Lit151, 2, "syntax.scm:25"), "\001\001", "\021\030\004\t\003\b\013", new Object[] { Lit200 }, 0);Lit43 = new kawa.lang.SyntaxRules(Lit151, tmp5565_5562, 3, syntax.Lit42 = gnu.mapping.Symbol.valueOf("define-macro"));Lit41 = new kawa.lang.SyntaxRules(Lit151, new kawa.lang.SyntaxRule[] { new kawa.lang.SyntaxRule(new kawa.lang.SyntaxPattern("\f\030\f\007\f\017\023", Lit151, 3, "syntax.scm:18"), "\001\001\000", "\021\030\004\t\003\b\021\030\f\t\013\022", Lit201, 0) }, 3, syntax.Lit40 = gnu.mapping.Symbol.valueOf("defmacro"));Lit39 = new SyntaxTemplate("\001\000", "\n", Lit151, 0);Lit38 = new SyntaxTemplate("\001\000", "\b\003", Lit151, 0);Lit37 = new kawa.lang.SyntaxPattern("\f\007\013", Lit151, 2, "syntax.scm:244");Lit36 = new SyntaxTemplate("\001\000", "\n", Lit151, 0);Lit35 = new SyntaxTemplate("\001\000", "\b\003", Lit151, 0);Lit34 = new kawa.lang.SyntaxPattern(",\f\002\f\007\b\013", Lit203, 2, "syntax.scm:242");Lit33 = new SyntaxTemplate("\000", "\002", Lit151, 0);Lit32 = new kawa.lang.SyntaxPattern("\f\002\003", Lit150, 1, "syntax.scm:240");Lit31 = new kawa.lang.SyntaxPattern("\b", Lit151, 0, "syntax.scm:239");Lit30 = new SyntaxTemplate("\001\000", "\n", Lit151, 0);Lit29 = new kawa.lang.SyntaxPattern("\f\007\013", Lit151, 2, "syntax.scm:233");Lit28 = new SyntaxTemplate("\001\000\000", "\022", Lit151, 0);Lit27 = new SyntaxTemplate("\001\000\000", "\b\t\003\n", Lit151, 0);Lit26 = new kawa.lang.SyntaxPattern("\034\f\007\013\023", Lit151, 3, "syntax.scm:231");Lit25 = new SyntaxTemplate("\001\003\000", "\022", Lit151, 0);Lit24 = new SyntaxTemplate("\001\003\000", "\b\r\013", Lit151, 1);Lit23 = new kawa.lang.SyntaxPattern("L\f\002\f\007\r\017\b\b\b\023", Lit206, 3, "syntax.scm:229");Lit22 = new SyntaxTemplate("\000", "\002", Lit151, 0);Lit21 = new kawa.lang.SyntaxPattern("\f\002\003", Lit148, 1, "syntax.scm:227");Lit20 = new kawa.lang.SyntaxPattern("\b", Lit151, 0, "syntax.scm:226");Lit19 = new SyntaxTemplate("\001\000", "\n", Lit151, 0);Lit18 = new kawa.lang.SyntaxPattern("\f\007\013", Lit151, 2, "syntax.scm:220");Lit17 = new SyntaxTemplate("\001\000", "\n", Lit151, 0);Lit16 = new SyntaxTemplate("\001\000", "\030\004", new Object[] { gnu.lists.Pair.make("~}", gnu.lists.LList.Empty) }, 0);Lit15 = new SyntaxTemplate("\001\000", "\030\004", new Object[] { gnu.lists.Pair.make(Lit174, gnu.lists.PairWithPosition.make(Lit202, gnu.lists.PairWithPosition.make("~{", gnu.lists.LList.Empty, "/mnt/hgfs/trunk/kawaForAndroid/kawa-2.4/kawa/lib/syntax.scm", 892971), "/mnt/hgfs/trunk/kawaForAndroid/kawa-2.4/kawa/lib/syntax.scm", 892957)) }, 0);Lit14 = new kawa.lang.SyntaxPattern(",\f\002\f\007\b\013", Lit203, 2, "syntax.scm:217");Lit13 = new SyntaxTemplate("\000", "\002", Lit151, 0);Lit12 = new kawa.lang.SyntaxPattern("\f\002\003", Lit150, 1, "syntax.scm:215");Lit11 = new kawa.lang.SyntaxPattern("\b", Lit151, 0, "syntax.scm:214");Lit10 = new SyntaxTemplate("\001\000", "\n", Lit151, 0); Object[] tmp6392_6389 = new Object[4]; Object[] tmp6393_6392 = tmp6392_6389;tmp6393_6392[0] = Lit174; Object[] tmp6399_6393 = tmp6393_6392;tmp6399_6393[1] = Lit204; Object[] tmp6405_6399 = tmp6399_6393;tmp6405_6399[2] = gnu.lists.PairWithPosition.make(Lit205, gnu.lists.LList.Empty, "/mnt/hgfs/trunk/kawaForAndroid/kawa-2.4/kawa/lib/syntax.scm", 843836);tmp6405_6399[3] = gnu.lists.PairWithPosition.make(gnu.lists.PairWithPosition.make(Lit176, gnu.lists.PairWithPosition.make(gnu.mapping.Symbol.valueOf("replace"), gnu.lists.LList.Empty, "/mnt/hgfs/trunk/kawaForAndroid/kawa-2.4/kawa/lib/syntax.scm", 847902), "/mnt/hgfs/trunk/kawaForAndroid/kawa-2.4/kawa/lib/syntax.scm", 847902), gnu.lists.PairWithPosition.make("~", gnu.lists.PairWithPosition.make("~~", gnu.lists.LList.Empty, "/mnt/hgfs/trunk/kawaForAndroid/kawa-2.4/kawa/lib/syntax.scm", 847914), "/mnt/hgfs/trunk/kawaForAndroid/kawa-2.4/kawa/lib/syntax.scm", 847910), "/mnt/hgfs/trunk/kawaForAndroid/kawa-2.4/kawa/lib/syntax.scm", 847901);Lit9 = new SyntaxTemplate("\001\000", "\021\030\004\021\030\fQ\021\030\004\021\030\f\t\003\030\024\030\034", tmp6392_6389, 0);Lit8 = new kawa.lang.SyntaxPattern("\f\007\013", Lit151, 2, "syntax.scm:205");Lit7 = new SyntaxTemplate("\001\000\000", "\022", Lit151, 0);Lit6 = new kawa.lang.SyntaxPattern("\034\f\007\013\023", Lit151, 3, "syntax.scm:203");Lit5 = new SyntaxTemplate("\001\000\000", "\022", Lit151, 0);Lit4 = new SyntaxTemplate("\001\000\000", "\003", Lit151, 0);Lit3 = new kawa.lang.SyntaxPattern(",\f\002\f\007\013\023", Lit206, 3, "syntax.scm:201");Lit2 = new SyntaxTemplate("\000", "\002", Lit151, 0);Lit1 = new kawa.lang.SyntaxPattern("\f\002\003", Lit148, 1, "syntax.scm:199");Lit0 = new kawa.lang.SyntaxPattern("\b", Lit151, 0, "syntax.scm:198");$instance = new syntax();$Prvt$define$Mnsyntax = gnu.kawa.reflect.StaticFieldLocation.make("kawa.lib.prim_syntax", "define$Mnsyntax");$Prvt$define = gnu.kawa.reflect.StaticFieldLocation.make("kawa.lib.prim_syntax", "define");$Prvt$define$Mnconstant = gnu.kawa.reflect.StaticFieldLocation.make("kawa.lib.prim_syntax", "define$Mnconstant");$Prvt$if = gnu.kawa.reflect.StaticFieldLocation.make("kawa.lib.prim_syntax", "if");$Prvt$try$Mncatch = gnu.kawa.reflect.StaticFieldLocation.make("kawa.lib.prim_syntax", "try$Mncatch");
    $Prvt$let = gnu.kawa.reflect.StaticFieldLocation.make("kawa.lib.std_syntax", "let");$Prvt$_ = gnu.kawa.reflect.StaticFieldLocation.make("kawa.lib.std_syntax", "_");
    











































































































    $Prvt$set$Mncdr$Ex = gnu.kawa.reflect.StaticFieldLocation.make("kawa.lib.lists", "set$Mncdr$Ex");$Prvt$car = gnu.kawa.reflect.StaticFieldLocation.make("kawa.lib.lists", "car");$Prvt$cdr = gnu.kawa.reflect.StaticFieldLocation.make("kawa.lib.lists", "cdr");$Prvt$cadr = gnu.kawa.reflect.StaticFieldLocation.make("kawa.lib.lists", "cadr");$Prvt$cddr = gnu.kawa.reflect.StaticFieldLocation.make("kawa.lib.lists", "cddr");$Prvt$begin = gnu.kawa.reflect.StaticFieldLocation.make("kawa.standard.begin", "begin");$Prvt$call$Mnwith$Mnvalues = gnu.kawa.reflect.StaticFieldLocation.make("gnu.kawa.functions.CallWithValues", "callWithValues");$Prvt$lambda = gnu.kawa.reflect.StaticFieldLocation.make("kawa.standard.SchemeCompilation", "lambda");$Prvt$list = gnu.kawa.reflect.StaticFieldLocation.make("gnu.kawa.lispexpr.LangObjType", "listType");$Prvt$not = gnu.kawa.reflect.StaticFieldLocation.make("kawa.standard.Scheme", "not");$Prvt$quasiquote = gnu.kawa.reflect.StaticFieldLocation.make("kawa.lang.Quote", "quasiQuote");$Prvt$quote = gnu.kawa.reflect.StaticFieldLocation.make("kawa.lang.Quote", "plainQuote");$Prvt$set$Ex = gnu.kawa.reflect.StaticFieldLocation.make("kawa.standard.set_b", "set");$Prvt$syntax$Mnrules = gnu.kawa.reflect.StaticFieldLocation.make("kawa.standard.syntax_rules", "syntax_rules");defmacro = kawa.lang.Macro.make(Lit40, Lit41, "kawa.lib.syntax");define$Mnmacro = kawa.lang.Macro.make(Lit42, Lit43, "kawa.lib.syntax");define$Mnsyntax$Mncase = kawa.lang.Macro.make(Lit44, Lit45, "kawa.lib.syntax");when = kawa.lang.Macro.make(Lit46, Lit47, "kawa.lib.syntax");unless = kawa.lang.Macro.make(Lit48, Lit49, "kawa.lib.syntax");syntax localSyntax1 = $instance; void tmp7023_7020 = new gnu.expr.ModuleMethod(localSyntax1, 1, null, 4097);tmp7023_7020.setProperty("source-location", "/mnt/hgfs/trunk/kawaForAndroid/kawa-2.4/kawa/lib/syntax.scm:44");try$Mnfinally = kawa.lang.Macro.makeSkipScanForm(Lit50, tmp7023_7020, "kawa.lib.syntax");syntax localSyntax2 = $instance; void tmp7062_7059 = new gnu.expr.ModuleMethod(localSyntax2, 2, null, 4097);tmp7062_7059.setProperty("source-location", "/mnt/hgfs/trunk/kawaForAndroid/kawa-2.4/kawa/lib/syntax.scm:52");synchronized = kawa.lang.Macro.makeSkipScanForm(Lit54, tmp7062_7059, "kawa.lib.syntax");syntax localSyntax3 = $instance; void tmp7101_7098 = new gnu.expr.ModuleMethod(localSyntax3, 3, null, 4097);tmp7101_7098.setProperty("source-location", "/mnt/hgfs/trunk/kawaForAndroid/kawa-2.4/kawa/lib/syntax.scm:61");begin$Mnfor$Mnsyntax = kawa.lang.Macro.make(Lit58, tmp7101_7098, "kawa.lib.syntax");define$Mnfor$Mnsyntax = kawa.lang.Macro.make(Lit63, Lit64, "kawa.lib.syntax");syntax localSyntax4 = $instance; void tmp7155_7152 = new gnu.expr.ModuleMethod(localSyntax4, 4, null, 4097);tmp7155_7152.setProperty("source-location", "/mnt/hgfs/trunk/kawaForAndroid/kawa-2.4/kawa/lib/syntax.scm:79");let$Mnvalues = kawa.lang.Macro.make(Lit65, tmp7155_7152, "kawa.lib.syntax");let$St$Mnvalues = kawa.lang.Macro.make(Lit102, Lit103, "kawa.lib.syntax");syntax localSyntax5 = $instance;case$Mnlambda = kawa.lang.Macro.make(Lit104, new gnu.expr.ModuleMethod(localSyntax5, 5, null, 4097), "kawa.lib.syntax");define$Mnvalues = kawa.lang.Macro.make(Lit114, Lit115, "kawa.lib.syntax");define$Mnalias$Mnparameter = kawa.lang.Macro.make(Lit116, Lit117, "kawa.lib.syntax");
    































































































































    syntax localSyntax6 = $instance; void tmp7273_7270 = new gnu.expr.ModuleMethod(localSyntax6, 6, null, 4097);tmp7273_7270.setProperty("source-location", "/mnt/hgfs/trunk/kawaForAndroid/kawa-2.4/kawa/lib/syntax.scm:248");$string$Mnwith$Mndefault$Mnformat$ = kawa.lang.Macro.make(Lit118, tmp7273_7270, "kawa.lib.syntax");$string$ = kawa.lang.Macro.make(Lit127, Lit128, "kawa.lib.syntax");$string$Mnwith$Mndelimiter$Mnmarks$ = kawa.lang.Macro.make(Lit129, Lit130, "kawa.lib.syntax");$format$ = kawa.lang.Macro.make(Lit131, Lit132, "kawa.lib.syntax");$sprintf$ = kawa.lang.Macro.make(Lit133, Lit134, "kawa.lib.syntax");$bracket$Mnlist$ = kawa.lang.Macro.make(Lit135, Lit136, "kawa.lib.syntax");
    
































































    syntax localSyntax7 = $instance; void tmp7390_7387 = new gnu.expr.ModuleMethod(localSyntax7, 7, null, 4097);tmp7390_7387.setProperty("source-location", "/mnt/hgfs/trunk/kawaForAndroid/kawa-2.4/kawa/lib/syntax.scm:314");define$Mnsimple$Mnconstructor = kawa.lang.Macro.make(Lit137, tmp7390_7387, "kawa.lib.syntax");$Prvt$$Pcsimple$Mnconstruct$Mnbuilder = kawa.lang.Macro.make(Lit145, Lit146, "kawa.lib.syntax");$runBody$();
  }
  
  public Object apply1(gnu.expr.ModuleMethod paramModuleMethod, Object paramObject)
  {
    switch (selector) {case 1:  return lambda1(paramObject);
    





    case 2: 
      return lambda2(paramObject);
    






    case 3: 
      return lambda3(paramObject);
    















    case 4: 
      return lambda4(paramObject); case 5:  return lambda5(paramObject);
    






































































































































































    case 6: 
      return lambda7(paramObject);
    































































    case 7: 
      return lambda8(paramObject); } return super.apply1(paramModuleMethod, paramObject); }
  static Object lambda8(Object form) { Object localObject1 = form;Object[] arrayOfObject = kawa.lang.SyntaxPattern.allocVars(3, null);
    
    kawa.lang.TemplateScope localTemplateScope = kawa.lang.TemplateScope.make();localTemplateScope = kawa.lang.TemplateScope.make(); Object tmp57_54 = gnu.mapping.Promise.force(std_syntax.syntax$To$Datum(Lit140.execute(arrayOfObject, localTemplateScope)), String.class);tmp57_54;Object cname = std_syntax.datum$To$Syntax(Lit139.execute(arrayOfObject, localTemplateScope), gnu.mapping.Symbol.valueOf(tmp57_54 == null ? null : tmp57_54.toString(), gnu.kawa.lispexpr.LispLanguage.constructNamespace));
    localTemplateScope = kawa.lang.TemplateScope.make();
    



    cname = kawa.lang.TemplateScope.make();return Lit143.match(form, arrayOfObject, 0) ? Lit144.execute(arrayOfObject, cname) : Lit138.match(form, arrayOfObject, 0) ? kawa.lang.Quote.append$V(new Object[] { Lit141.execute(arrayOfObject, localTemplateScope), kawa.lang.Quote.consX$V(new Object[] { cname, Lit142.execute(arrayOfObject, localTemplateScope) }) }) : kawa.standard.syntax_case.error("syntax-case", form);
  }
  
  public syntax()
  {
    gnu.expr.ModuleInfo.register(this);
  }
  
  public void apply(gnu.mapping.CallContext paramCallContext)
  {
    gnu.expr.ModuleMethod.applyError();
  }
  
  public class frame
    extends gnu.expr.ModuleBody
  {
    Object[] $unnamed$0;
    
    public frame() {}
    
    /* Error */
    public Object lambda6loop(Object paramObject1, Object clauses)
    {
      // Byte code:
      //   0: aload_2
      //   1: astore_3
      //   2: iconst_4
      //   3: aload_0
      //   4: getfield 6	kawa/lib/syntax$frame:$unnamed$0	[Ljava/lang/Object;
      //   7: invokestatic 12	kawa/lang/SyntaxPattern:allocVars	(I[Ljava/lang/Object;)[Ljava/lang/Object;
      //   10: astore 4
      //   12: getstatic 18	kawa/lib/syntax:Lit108	Lkawa/lang/SyntaxPattern;
      //   15: aload_2
      //   16: aload 4
      //   18: iconst_0
      //   19: invokevirtual 24	kawa/lang/Pattern:match	(Ljava/lang/Object;[Ljava/lang/Object;I)Z
      //   22: ifeq +64 -> 86
      //   25: iconst_2
      //   26: anewarray 26	java/lang/Object
      //   29: dup
      //   30: iconst_0
      //   31: getstatic 30	kawa/lib/syntax:Lit109	Lkawa/lang/SyntaxTemplate;
      //   34: aload 4
      //   36: aload_1
      //   37: ldc 32
      //   39: invokestatic 38	gnu/mapping/Promise:force	(Ljava/lang/Object;Ljava/lang/Class;)Ljava/lang/Object;
      //   42: dup
      //   43: astore 5
      //   45: checkcast 32	kawa/lang/TemplateScope
      //   48: invokevirtual 54	kawa/lang/SyntaxTemplate:execute	([Ljava/lang/Object;Lkawa/lang/TemplateScope;)Ljava/lang/Object;
      //   51: aastore
      //   52: dup
      //   53: iconst_1
      //   54: aload_0
      //   55: aload_1
      //   56: getstatic 57	kawa/lib/syntax:Lit110	Lkawa/lang/SyntaxTemplate;
      //   59: aload 4
      //   61: aload_1
      //   62: ldc 32
      //   64: invokestatic 38	gnu/mapping/Promise:force	(Ljava/lang/Object;Ljava/lang/Class;)Ljava/lang/Object;
      //   67: dup
      //   68: astore 5
      //   70: checkcast 32	kawa/lang/TemplateScope
      //   73: invokevirtual 54	kawa/lang/SyntaxTemplate:execute	([Ljava/lang/Object;Lkawa/lang/TemplateScope;)Ljava/lang/Object;
      //   76: invokevirtual 61	kawa/lib/syntax$frame:lambda6loop	(Ljava/lang/Object;Ljava/lang/Object;)Ljava/lang/Object;
      //   79: aastore
      //   80: invokestatic 67	kawa/lang/Quote:append$V	([Ljava/lang/Object;)Ljava/lang/Object;
      //   83: goto +79 -> 162
      //   86: getstatic 70	kawa/lib/syntax:Lit111	Lkawa/lang/SyntaxPattern;
      //   89: aload_2
      //   90: aload 4
      //   92: iconst_0
      //   93: invokevirtual 24	kawa/lang/Pattern:match	(Ljava/lang/Object;[Ljava/lang/Object;I)Z
      //   96: ifeq +9 -> 105
      //   99: getstatic 76	gnu/lists/LList:Empty	Lgnu/lists/EmptyList;
      //   102: goto +60 -> 162
      //   105: getstatic 79	kawa/lib/syntax:Lit112	Lkawa/lang/SyntaxPattern;
      //   108: aload_2
      //   109: aload 4
      //   111: iconst_0
      //   112: invokevirtual 24	kawa/lang/Pattern:match	(Ljava/lang/Object;[Ljava/lang/Object;I)Z
      //   115: ifeq +41 -> 156
      //   118: getstatic 82	kawa/lib/syntax:Lit113	Lkawa/lang/SyntaxTemplate;
      //   121: aload 4
      //   123: aload_1
      //   124: ldc 32
      //   126: invokestatic 38	gnu/mapping/Promise:force	(Ljava/lang/Object;Ljava/lang/Class;)Ljava/lang/Object;
      //   129: dup
      //   130: astore 5
      //   132: checkcast 32	kawa/lang/TemplateScope
      //   135: invokevirtual 54	kawa/lang/SyntaxTemplate:execute	([Ljava/lang/Object;Lkawa/lang/TemplateScope;)Ljava/lang/Object;
      //   138: iconst_1
      //   139: anewarray 26	java/lang/Object
      //   142: dup
      //   143: iconst_0
      //   144: ldc 84
      //   146: aastore
      //   147: invokestatic 90	kawa/lib/prim_syntax:reportSyntaxError	(Ljava/lang/Object;[Ljava/lang/Object;)Lgnu/expr/Expression;
      //   150: invokestatic 94	gnu/lists/LList:list1	(Ljava/lang/Object;)Lgnu/lists/Pair;
      //   153: goto +9 -> 162
      //   156: ldc 96
      //   158: aload_2
      //   159: invokestatic 102	kawa/standard/syntax_case:error	(Ljava/lang/String;Ljava/lang/Object;)Ljava/lang/Object;
      //   162: areturn
      //   163: new 42	gnu/mapping/WrongType
      //   166: dup_x1
      //   167: swap
      //   168: ldc 44
      //   170: iconst_3
      //   171: aload 5
      //   173: invokespecial 48	gnu/mapping/WrongType:<init>	(Ljava/lang/ClassCastException;Ljava/lang/String;ILjava/lang/Object;)V
      //   176: athrow
      //   177: new 42	gnu/mapping/WrongType
      //   180: dup_x1
      //   181: swap
      //   182: ldc 44
      //   184: iconst_3
      //   185: aload 5
      //   187: invokespecial 48	gnu/mapping/WrongType:<init>	(Ljava/lang/ClassCastException;Ljava/lang/String;ILjava/lang/Object;)V
      //   190: athrow
      //   191: new 42	gnu/mapping/WrongType
      //   194: dup_x1
      //   195: swap
      //   196: ldc 44
      //   198: iconst_3
      //   199: aload 5
      //   201: invokespecial 48	gnu/mapping/WrongType:<init>	(Ljava/lang/ClassCastException;Ljava/lang/String;ILjava/lang/Object;)V
      //   204: athrow
      // Line number table:
      //   Java source line #127	-> byte code offset #0
      //   Java source line #129	-> byte code offset #25
      //   Java source line #133	-> byte code offset #118
      //   Java source line #129	-> byte code offset #163
      //   Java source line #133	-> byte code offset #191
      // Local variable table:
      //   start	length	slot	name	signature
      //   0	163	0	this	frame
      //   0	205	1	paramObject1	Object
      //   0	162	2	clauses	Object
      //   1	1	3	localObject1	Object
      //   10	112	4	arrayOfObject	Object[]
      //   43	157	5	localObject2	Object
      //   163	1	6	localClassCastException1	ClassCastException
      //   177	1	7	localClassCastException2	ClassCastException
      //   191	1	8	localClassCastException3	ClassCastException
      // Exception table:
      //   from	to	target	type
      //   45	48	163	java/lang/ClassCastException
      //   70	73	177	java/lang/ClassCastException
      //   132	135	191	java/lang/ClassCastException
    }
  }
}
