package kawa.lib; import gnu.expr.ModuleMethod;

public class uniform extends gnu.expr.ModuleBody { public static final gnu.kawa.reflect.StaticFieldLocation $Prvt$let; public static final gnu.kawa.reflect.StaticFieldLocation $Prvt$let$St; public static final ModuleMethod s8vector$Qu; public static final ModuleMethod make$Mns8vector; public static final ModuleMethod s8vector; public static final ModuleMethod s8vector$Mnlength; public static final ModuleMethod s8vector$Mnref; public static final ModuleMethod s8vector$Mnset$Ex; public static final ModuleMethod s8vector$Mn$Grlist; public static final kawa.lang.Macro $Pclist$Mn$Grarray; public static final ModuleMethod list$Mn$Grs8vector; public static final ModuleMethod u8vector$Qu; public static final ModuleMethod make$Mnu8vector; public static final ModuleMethod u8vector; public static final ModuleMethod u8vector$Mnlength; public static final ModuleMethod u8vector$Mnref; public static final ModuleMethod u8vector$Mnset$Ex; public static final ModuleMethod u8vector$Mn$Grlist; public static final ModuleMethod list$Mn$Gru8vector; public static final ModuleMethod s16vector$Qu; public static final ModuleMethod make$Mns16vector; public static final ModuleMethod s16vector; public static final ModuleMethod s16vector$Mnlength; public static final ModuleMethod s16vector$Mnref; public static final ModuleMethod s16vector$Mnset$Ex; public static final ModuleMethod s16vector$Mn$Grlist; public static final ModuleMethod list$Mn$Grs16vector; public static final ModuleMethod u16vector$Qu; public static final ModuleMethod make$Mnu16vector; public static final ModuleMethod u16vector; public static final ModuleMethod u16vector$Mnlength; public static final ModuleMethod u16vector$Mnref; public static final ModuleMethod u16vector$Mnset$Ex; public static final ModuleMethod u16vector$Mn$Grlist; public static final ModuleMethod list$Mn$Gru16vector; public static final ModuleMethod s32vector$Qu; public static final ModuleMethod make$Mns32vector; public static final ModuleMethod s32vector; public static final ModuleMethod s32vector$Mnlength; public static final ModuleMethod s32vector$Mnref; public static final ModuleMethod s32vector$Mnset$Ex; public static final ModuleMethod s32vector$Mn$Grlist; public static final ModuleMethod list$Mn$Grs32vector; public static final ModuleMethod u32vector$Qu; public static final ModuleMethod make$Mnu32vector; public static final ModuleMethod u32vector; public static final ModuleMethod u32vector$Mnlength; public static final ModuleMethod u32vector$Mnref; public static final ModuleMethod u32vector$Mnset$Ex; public static final ModuleMethod u32vector$Mn$Grlist; public static final ModuleMethod list$Mn$Gru32vector; public static final ModuleMethod s64vector$Qu; public static final ModuleMethod make$Mns64vector; public static final ModuleMethod s64vector; public static final ModuleMethod s64vector$Mnlength; public static final ModuleMethod s64vector$Mnref; public static final ModuleMethod s64vector$Mnset$Ex; public static final ModuleMethod s64vector$Mn$Grlist; public static final ModuleMethod list$Mn$Grs64vector; public static final ModuleMethod u64vector$Qu; public static final ModuleMethod make$Mnu64vector; public static final ModuleMethod u64vector; public static final ModuleMethod u64vector$Mnlength; public static final ModuleMethod u64vector$Mnref; public static final ModuleMethod u64vector$Mnset$Ex; public static final ModuleMethod u64vector$Mn$Grlist; public static final ModuleMethod list$Mn$Gru64vector; public static final ModuleMethod f32vector$Qu; public static final ModuleMethod make$Mnf32vector; public static final ModuleMethod f32vector; public static final ModuleMethod f32vector$Mnlength; public static final ModuleMethod f32vector$Mnref; public static final ModuleMethod f32vector$Mnset$Ex; public static final ModuleMethod f32vector$Mn$Grlist; public static final ModuleMethod list$Mn$Grf32vector; public static final ModuleMethod f64vector$Qu; public static final ModuleMethod make$Mnf64vector; public static final ModuleMethod f64vector; public static final ModuleMethod f64vector$Mnlength; public static final ModuleMethod f64vector$Mnref; public static final ModuleMethod f64vector$Mnset$Ex; public static final ModuleMethod f64vector$Mn$Grlist; public static final ModuleMethod list$Mn$Grf64vector; static final gnu.math.IntNum Lit0; public static uniform $instance; static final gnu.mapping.SimpleSymbol Lit1; static final gnu.mapping.SimpleSymbol Lit2; static final gnu.mapping.SimpleSymbol Lit3; static final gnu.mapping.SimpleSymbol Lit4; static final gnu.mapping.SimpleSymbol Lit5; static final gnu.mapping.SimpleSymbol Lit6; static final gnu.mapping.SimpleSymbol Lit7; private static void $runBody$() { ; gnu.lists.Consumer $result = getInstanceconsumer; }
  static final gnu.mapping.SimpleSymbol Lit8; static final kawa.lang.SyntaxRules Lit9; static final gnu.mapping.SimpleSymbol Lit10; static final gnu.mapping.SimpleSymbol Lit11; static final gnu.mapping.SimpleSymbol Lit12; static final gnu.mapping.SimpleSymbol Lit13; static final gnu.mapping.SimpleSymbol Lit14; static final gnu.mapping.SimpleSymbol Lit15; static final gnu.mapping.SimpleSymbol Lit16; static final gnu.mapping.SimpleSymbol Lit17; static final gnu.mapping.SimpleSymbol Lit18; static final gnu.mapping.SimpleSymbol Lit19; static final gnu.mapping.SimpleSymbol Lit20; static final gnu.mapping.SimpleSymbol Lit21; static final gnu.mapping.SimpleSymbol Lit22; static final gnu.mapping.SimpleSymbol Lit23; static final gnu.mapping.SimpleSymbol Lit24; static final gnu.mapping.SimpleSymbol Lit25; static final gnu.mapping.SimpleSymbol Lit26; static final gnu.mapping.SimpleSymbol Lit27; static final gnu.mapping.SimpleSymbol Lit28; static final gnu.mapping.SimpleSymbol Lit29; static final gnu.mapping.SimpleSymbol Lit30; static final gnu.mapping.SimpleSymbol Lit31; static final gnu.mapping.SimpleSymbol Lit32; static final gnu.mapping.SimpleSymbol Lit33; static final gnu.mapping.SimpleSymbol Lit34; static final gnu.mapping.SimpleSymbol Lit35; static final gnu.mapping.SimpleSymbol Lit36; static final gnu.mapping.SimpleSymbol Lit37; static final gnu.mapping.SimpleSymbol Lit38; static final gnu.mapping.SimpleSymbol Lit39; static final gnu.mapping.SimpleSymbol Lit40; static final gnu.mapping.SimpleSymbol Lit41; static final gnu.mapping.SimpleSymbol Lit42; static final gnu.mapping.SimpleSymbol Lit43; static final gnu.mapping.SimpleSymbol Lit44; static final gnu.mapping.SimpleSymbol Lit45; static final gnu.mapping.SimpleSymbol Lit46; static final gnu.mapping.SimpleSymbol Lit47; static final gnu.mapping.SimpleSymbol Lit48; static final gnu.mapping.SimpleSymbol Lit49; static final gnu.mapping.SimpleSymbol Lit50; static final gnu.mapping.SimpleSymbol Lit51; static final gnu.mapping.SimpleSymbol Lit52; static final gnu.mapping.SimpleSymbol Lit53; static final gnu.mapping.SimpleSymbol Lit54; static final gnu.mapping.SimpleSymbol Lit55; static final gnu.mapping.SimpleSymbol Lit56; static { Lit89 = gnu.mapping.Symbol.valueOf("v");Lit88 = gnu.lists.PairWithPosition.make(gnu.mapping.Symbol.valueOf("x"), gnu.lists.LList.Empty, "/mnt/hgfs/trunk/kawaForAndroid/kawa-2.4/kawa/lib/uniform.scm", 139290);Lit87 = gnu.mapping.Symbol.valueOf("::");Lit86 = gnu.mapping.Symbol.valueOf("i");Lit85 = gnu.mapping.Symbol.valueOf("arr");Lit84 = gnu.mapping.Symbol.valueOf("n");Lit83 = new Object[0];Lit82 = gnu.mapping.Symbol.valueOf("list->f64vector");Lit81 = gnu.mapping.Symbol.valueOf("f64vector->list");Lit80 = gnu.mapping.Symbol.valueOf("f64vector-set!");Lit79 = gnu.mapping.Symbol.valueOf("f64vector-ref");Lit78 = gnu.mapping.Symbol.valueOf("f64vector-length");Lit77 = gnu.mapping.Symbol.valueOf("f64vector");Lit76 = gnu.mapping.Symbol.valueOf("make-f64vector");Lit75 = gnu.mapping.Symbol.valueOf("f64vector?");Lit74 = gnu.mapping.Symbol.valueOf("list->f32vector");Lit73 = gnu.mapping.Symbol.valueOf("f32vector->list");Lit72 = gnu.mapping.Symbol.valueOf("f32vector-set!");Lit71 = gnu.mapping.Symbol.valueOf("f32vector-ref");Lit70 = gnu.mapping.Symbol.valueOf("f32vector-length");Lit69 = gnu.mapping.Symbol.valueOf("f32vector");Lit68 = gnu.mapping.Symbol.valueOf("make-f32vector");Lit67 = gnu.mapping.Symbol.valueOf("f32vector?");Lit66 = gnu.mapping.Symbol.valueOf("list->u64vector");Lit65 = gnu.mapping.Symbol.valueOf("u64vector->list");Lit64 = gnu.mapping.Symbol.valueOf("u64vector-set!");Lit63 = gnu.mapping.Symbol.valueOf("u64vector-ref");Lit62 = gnu.mapping.Symbol.valueOf("u64vector-length");Lit61 = gnu.mapping.Symbol.valueOf("u64vector");Lit60 = gnu.mapping.Symbol.valueOf("make-u64vector");Lit59 = gnu.mapping.Symbol.valueOf("u64vector?");Lit58 = gnu.mapping.Symbol.valueOf("list->s64vector");Lit57 = gnu.mapping.Symbol.valueOf("s64vector->list");Lit56 = gnu.mapping.Symbol.valueOf("s64vector-set!");Lit55 = gnu.mapping.Symbol.valueOf("s64vector-ref");Lit54 = gnu.mapping.Symbol.valueOf("s64vector-length");Lit53 = gnu.mapping.Symbol.valueOf("s64vector");Lit52 = gnu.mapping.Symbol.valueOf("make-s64vector");Lit51 = gnu.mapping.Symbol.valueOf("s64vector?");Lit50 = gnu.mapping.Symbol.valueOf("list->u32vector");Lit49 = gnu.mapping.Symbol.valueOf("u32vector->list");Lit48 = gnu.mapping.Symbol.valueOf("u32vector-set!");Lit47 = gnu.mapping.Symbol.valueOf("u32vector-ref");Lit46 = gnu.mapping.Symbol.valueOf("u32vector-length");Lit45 = gnu.mapping.Symbol.valueOf("u32vector");Lit44 = gnu.mapping.Symbol.valueOf("make-u32vector");Lit43 = gnu.mapping.Symbol.valueOf("u32vector?");Lit42 = gnu.mapping.Symbol.valueOf("list->s32vector");Lit41 = gnu.mapping.Symbol.valueOf("s32vector->list");Lit40 = gnu.mapping.Symbol.valueOf("s32vector-set!");Lit39 = gnu.mapping.Symbol.valueOf("s32vector-ref");Lit38 = gnu.mapping.Symbol.valueOf("s32vector-length");Lit37 = gnu.mapping.Symbol.valueOf("s32vector");Lit36 = gnu.mapping.Symbol.valueOf("make-s32vector");Lit35 = gnu.mapping.Symbol.valueOf("s32vector?");Lit34 = gnu.mapping.Symbol.valueOf("list->u16vector");Lit33 = gnu.mapping.Symbol.valueOf("u16vector->list");Lit32 = gnu.mapping.Symbol.valueOf("u16vector-set!");Lit31 = gnu.mapping.Symbol.valueOf("u16vector-ref");Lit30 = gnu.mapping.Symbol.valueOf("u16vector-length");Lit29 = gnu.mapping.Symbol.valueOf("u16vector");Lit28 = gnu.mapping.Symbol.valueOf("make-u16vector");Lit27 = gnu.mapping.Symbol.valueOf("u16vector?");Lit26 = gnu.mapping.Symbol.valueOf("list->s16vector");Lit25 = gnu.mapping.Symbol.valueOf("s16vector->list");Lit24 = gnu.mapping.Symbol.valueOf("s16vector-set!");Lit23 = gnu.mapping.Symbol.valueOf("s16vector-ref");Lit22 = gnu.mapping.Symbol.valueOf("s16vector-length");Lit21 = gnu.mapping.Symbol.valueOf("s16vector");Lit20 = gnu.mapping.Symbol.valueOf("make-s16vector");Lit19 = gnu.mapping.Symbol.valueOf("s16vector?");Lit18 = gnu.mapping.Symbol.valueOf("list->u8vector");Lit17 = gnu.mapping.Symbol.valueOf("u8vector->list");Lit16 = gnu.mapping.Symbol.valueOf("u8vector-set!");Lit15 = gnu.mapping.Symbol.valueOf("u8vector-ref");Lit14 = gnu.mapping.Symbol.valueOf("u8vector-length");Lit13 = gnu.mapping.Symbol.valueOf("u8vector");Lit12 = gnu.mapping.Symbol.valueOf("make-u8vector");Lit11 = gnu.mapping.Symbol.valueOf("u8vector?");Lit10 = gnu.mapping.Symbol.valueOf("list->s8vector"); kawa.lang.SyntaxRule[] tmp749_746 = new kawa.lang.SyntaxRule[1]; Object[] tmp783_780 = new Object[19]; Object[] tmp784_783 = tmp783_780;tmp784_783[0] = gnu.mapping.Symbol.valueOf("let*"); Object[] tmp793_784 = tmp784_783;tmp793_784[1] = Lit84; Object[] tmp799_793 = tmp793_784;tmp799_793[2] = gnu.mapping.Symbol.valueOf("length"); Object[] tmp808_799 = tmp799_793;tmp808_799[3] = Lit85; Object[] tmp814_808 = tmp808_799;tmp814_808[4] = gnu.mapping.Symbol.valueOf("$bracket-apply$"); Object[] tmp823_814 = tmp814_808;tmp823_814[5] = gnu.lists.PairWithPosition.make(gnu.expr.Keyword.make("length"), gnu.lists.PairWithPosition.make(Lit84, gnu.lists.LList.Empty, "/mnt/hgfs/trunk/kawaForAndroid/kawa-2.4/kawa/lib/uniform.scm", 131113), "/mnt/hgfs/trunk/kawaForAndroid/kawa-2.4/kawa/lib/uniform.scm", 131105); Object[] tmp856_823 = tmp823_814; gnu.math.IntNum tmp875_872 = gnu.math.IntNum.valueOf(0);Lit0 = tmp875_872;tmp856_823[6] = gnu.lists.PairWithPosition.make(gnu.lists.PairWithPosition.make(Lit86, gnu.lists.PairWithPosition.make(Lit87, gnu.lists.PairWithPosition.make(gnu.mapping.Symbol.valueOf("int"), gnu.lists.PairWithPosition.make(tmp875_872, gnu.lists.LList.Empty, "/mnt/hgfs/trunk/kawaForAndroid/kawa-2.4/kawa/lib/uniform.scm", 135190), "/mnt/hgfs/trunk/kawaForAndroid/kawa-2.4/kawa/lib/uniform.scm", 135186), "/mnt/hgfs/trunk/kawaForAndroid/kawa-2.4/kawa/lib/uniform.scm", 135184), "/mnt/hgfs/trunk/kawaForAndroid/kawa-2.4/kawa/lib/uniform.scm", 135181), gnu.lists.LList.Empty, "/mnt/hgfs/trunk/kawaForAndroid/kawa-2.4/kawa/lib/uniform.scm", 135181); Object[] tmp931_856 = tmp856_823;tmp931_856[7] = gnu.mapping.Symbol.valueOf("for-each"); Object[] tmp941_931 = tmp931_856;tmp941_931[8] = gnu.mapping.Symbol.valueOf("lambda"); Object[] tmp951_941 = tmp941_931;tmp951_941[9] = Lit88; Object[] tmp958_951 = tmp951_941;tmp958_951[10] = Lit90; Object[] tmp965_958 = tmp958_951;tmp965_958[11] = gnu.lists.PairWithPosition.make(Lit85, gnu.lists.PairWithPosition.make(Lit86, gnu.lists.LList.Empty, "/mnt/hgfs/trunk/kawaForAndroid/kawa-2.4/kawa/lib/uniform.scm", 143391), "/mnt/hgfs/trunk/kawaForAndroid/kawa-2.4/kawa/lib/uniform.scm", 143386); Object[] tmp996_965 = tmp965_958;tmp996_965[12] = gnu.mapping.Symbol.valueOf("let"); Object[] tmp1006_996 = tmp996_965;tmp1006_996[13] = Lit89; Object[] tmp1013_1006 = tmp1006_996;tmp1013_1006[14] = Lit87; Object[] tmp1020_1013 = tmp1013_1006;tmp1020_1013[15] = Lit88; Object[] tmp1027_1020 = tmp1020_1013;tmp1027_1020[16] = gnu.lists.PairWithPosition.make(Lit89, gnu.lists.LList.Empty, "/mnt/hgfs/trunk/kawaForAndroid/kawa-2.4/kawa/lib/uniform.scm", 143418); Object[] tmp1046_1027 = tmp1027_1020;tmp1046_1027[17] = gnu.lists.PairWithPosition.make(gnu.lists.PairWithPosition.make(Lit90, gnu.lists.PairWithPosition.make(Lit86, gnu.lists.PairWithPosition.make(gnu.lists.PairWithPosition.make(gnu.mapping.Symbol.valueOf("+"), gnu.lists.PairWithPosition.make(Lit86, gnu.lists.PairWithPosition.make(gnu.math.IntNum.valueOf(1), gnu.lists.LList.Empty, "/mnt/hgfs/trunk/kawaForAndroid/kawa-2.4/kawa/lib/uniform.scm", 147489), "/mnt/hgfs/trunk/kawaForAndroid/kawa-2.4/kawa/lib/uniform.scm", 147487), "/mnt/hgfs/trunk/kawaForAndroid/kawa-2.4/kawa/lib/uniform.scm", 147484), gnu.lists.LList.Empty, "/mnt/hgfs/trunk/kawaForAndroid/kawa-2.4/kawa/lib/uniform.scm", 147484), "/mnt/hgfs/trunk/kawaForAndroid/kawa-2.4/kawa/lib/uniform.scm", 147482), "/mnt/hgfs/trunk/kawaForAndroid/kawa-2.4/kawa/lib/uniform.scm", 147476), gnu.lists.LList.Empty, "/mnt/hgfs/trunk/kawaForAndroid/kawa-2.4/kawa/lib/uniform.scm", 147476);tmp1046_1027[18] = gnu.lists.PairWithPosition.make(Lit85, gnu.lists.LList.Empty, "/mnt/hgfs/trunk/kawaForAndroid/kawa-2.4/kawa/lib/uniform.scm", 155656);tmp749_746[0] = new kawa.lang.SyntaxRule(new kawa.lang.SyntaxPattern("\f\030\f\007\f\017\f\027\b", Lit83, 3, "uniform.scm:30"), "\001\001\001", "\021\030\004ÉI\021\030\f\b\021\030\024\b\003a\021\030\034\b)\021\030$\b\023\030,\0304Ĺ\021\030<ĉ\021\030D\021\030LÁ\021\030T\021\030\\\b\021\030dY\b\021\030l\021\030t\t\013\030|\030\030\b\003\030", tmp783_780, 0);Lit9 = new kawa.lang.SyntaxRules(Lit83, tmp749_746, 3, uniform.Lit8 = gnu.mapping.Symbol.valueOf("%list->array"));Lit7 = gnu.mapping.Symbol.valueOf("s8vector->list");Lit6 = gnu.mapping.Symbol.valueOf("s8vector-set!");Lit5 = gnu.mapping.Symbol.valueOf("s8vector-ref");Lit4 = gnu.mapping.Symbol.valueOf("s8vector-length");Lit3 = gnu.mapping.Symbol.valueOf("s8vector");Lit2 = gnu.mapping.Symbol.valueOf("make-s8vector");Lit1 = gnu.mapping.Symbol.valueOf("s8vector?");$instance = new uniform();$Prvt$let = gnu.kawa.reflect.StaticFieldLocation.make("kawa.lib.std_syntax", "let");$Prvt$let$St = gnu.kawa.reflect.StaticFieldLocation.make("kawa.lib.std_syntax", "let$St");uniform localUniform = $instance;s8vector$Qu = new ModuleMethod(localUniform, 1, Lit1, 4097);make$Mns8vector = new ModuleMethod(localUniform, 2, Lit2, 8193);s8vector = new ModuleMethod(localUniform, 4, Lit3, 61440);s8vector$Mnlength = new ModuleMethod(localUniform, 5, Lit4, 4097);s8vector$Mnref = new ModuleMethod(localUniform, 6, Lit5, 8194);s8vector$Mnset$Ex = new ModuleMethod(localUniform, 7, Lit6, 12291);s8vector$Mn$Grlist = new ModuleMethod(localUniform, 8, Lit7, 4097);$Pclist$Mn$Grarray = kawa.lang.Macro.make(Lit8, Lit9, "kawa.lib.uniform");list$Mn$Grs8vector = new ModuleMethod(localUniform, 9, Lit10, 4097);u8vector$Qu = new ModuleMethod(localUniform, 10, Lit11, 4097);make$Mnu8vector = new ModuleMethod(localUniform, 11, Lit12, 8193);u8vector = new ModuleMethod(localUniform, 13, Lit13, 61440);u8vector$Mnlength = new ModuleMethod(localUniform, 14, Lit14, 4097);u8vector$Mnref = new ModuleMethod(localUniform, 15, Lit15, 8194);u8vector$Mnset$Ex = new ModuleMethod(localUniform, 16, Lit16, 12291);u8vector$Mn$Grlist = new ModuleMethod(localUniform, 17, Lit17, 4097);list$Mn$Gru8vector = new ModuleMethod(localUniform, 18, Lit18, 4097);s16vector$Qu = new ModuleMethod(localUniform, 19, Lit19, 4097);make$Mns16vector = new ModuleMethod(localUniform, 20, Lit20, 8193);s16vector = new ModuleMethod(localUniform, 22, Lit21, 61440);s16vector$Mnlength = new ModuleMethod(localUniform, 23, Lit22, 4097);s16vector$Mnref = new ModuleMethod(localUniform, 24, Lit23, 8194);s16vector$Mnset$Ex = new ModuleMethod(localUniform, 25, Lit24, 12291);s16vector$Mn$Grlist = new ModuleMethod(localUniform, 26, Lit25, 4097);list$Mn$Grs16vector = new ModuleMethod(localUniform, 27, Lit26, 4097);u16vector$Qu = new ModuleMethod(localUniform, 28, Lit27, 4097);make$Mnu16vector = new ModuleMethod(localUniform, 29, Lit28, 8193);u16vector = new ModuleMethod(localUniform, 31, Lit29, 61440);u16vector$Mnlength = new ModuleMethod(localUniform, 32, Lit30, 4097);u16vector$Mnref = new ModuleMethod(localUniform, 33, Lit31, 8194);u16vector$Mnset$Ex = new ModuleMethod(localUniform, 34, Lit32, 12291);u16vector$Mn$Grlist = new ModuleMethod(localUniform, 35, Lit33, 4097);list$Mn$Gru16vector = new ModuleMethod(localUniform, 36, Lit34, 4097);s32vector$Qu = new ModuleMethod(localUniform, 37, Lit35, 4097);make$Mns32vector = new ModuleMethod(localUniform, 38, Lit36, 8193);s32vector = new ModuleMethod(localUniform, 40, Lit37, 61440);s32vector$Mnlength = new ModuleMethod(localUniform, 41, Lit38, 4097);s32vector$Mnref = new ModuleMethod(localUniform, 42, Lit39, 8194);s32vector$Mnset$Ex = new ModuleMethod(localUniform, 43, Lit40, 12291);s32vector$Mn$Grlist = new ModuleMethod(localUniform, 44, Lit41, 4097);list$Mn$Grs32vector = new ModuleMethod(localUniform, 45, Lit42, 4097);u32vector$Qu = new ModuleMethod(localUniform, 46, Lit43, 4097);make$Mnu32vector = new ModuleMethod(localUniform, 47, Lit44, 8193);u32vector = new ModuleMethod(localUniform, 49, Lit45, 61440);u32vector$Mnlength = new ModuleMethod(localUniform, 50, Lit46, 4097);u32vector$Mnref = new ModuleMethod(localUniform, 51, Lit47, 8194);u32vector$Mnset$Ex = new ModuleMethod(localUniform, 52, Lit48, 12291);u32vector$Mn$Grlist = new ModuleMethod(localUniform, 53, Lit49, 4097);list$Mn$Gru32vector = new ModuleMethod(localUniform, 54, Lit50, 4097);s64vector$Qu = new ModuleMethod(localUniform, 55, Lit51, 4097);make$Mns64vector = new ModuleMethod(localUniform, 56, Lit52, 8193);s64vector = new ModuleMethod(localUniform, 58, Lit53, 61440);s64vector$Mnlength = new ModuleMethod(localUniform, 59, Lit54, 4097);s64vector$Mnref = new ModuleMethod(localUniform, 60, Lit55, 8194);s64vector$Mnset$Ex = new ModuleMethod(localUniform, 61, Lit56, 12291);s64vector$Mn$Grlist = new ModuleMethod(localUniform, 62, Lit57, 4097);list$Mn$Grs64vector = new ModuleMethod(localUniform, 63, Lit58, 4097);u64vector$Qu = new ModuleMethod(localUniform, 64, Lit59, 4097);make$Mnu64vector = new ModuleMethod(localUniform, 65, Lit60, 8193);u64vector = new ModuleMethod(localUniform, 67, Lit61, 61440);u64vector$Mnlength = new ModuleMethod(localUniform, 68, Lit62, 4097);u64vector$Mnref = new ModuleMethod(localUniform, 69, Lit63, 8194);u64vector$Mnset$Ex = new ModuleMethod(localUniform, 70, Lit64, 12291);u64vector$Mn$Grlist = new ModuleMethod(localUniform, 71, Lit65, 4097);list$Mn$Gru64vector = new ModuleMethod(localUniform, 72, Lit66, 4097);f32vector$Qu = new ModuleMethod(localUniform, 73, Lit67, 4097);make$Mnf32vector = new ModuleMethod(localUniform, 74, Lit68, 8193);f32vector = new ModuleMethod(localUniform, 76, Lit69, 61440);f32vector$Mnlength = new ModuleMethod(localUniform, 77, Lit70, 4097);f32vector$Mnref = new ModuleMethod(localUniform, 78, Lit71, 8194);f32vector$Mnset$Ex = new ModuleMethod(localUniform, 79, Lit72, 12291);f32vector$Mn$Grlist = new ModuleMethod(localUniform, 80, Lit73, 4097);list$Mn$Grf32vector = new ModuleMethod(localUniform, 81, Lit74, 4097);f64vector$Qu = new ModuleMethod(localUniform, 82, Lit75, 4097);make$Mnf64vector = new ModuleMethod(localUniform, 83, Lit76, 8193);f64vector = new ModuleMethod(localUniform, 85, Lit77, 61440);f64vector$Mnlength = new ModuleMethod(localUniform, 86, Lit78, 4097);f64vector$Mnref = new ModuleMethod(localUniform, 87, Lit79, 8194);f64vector$Mnset$Ex = new ModuleMethod(localUniform, 88, Lit80, 12291);f64vector$Mn$Grlist = new ModuleMethod(localUniform, 89, Lit81, 4097);list$Mn$Grf64vector = new ModuleMethod(localUniform, 90, Lit82, 4097);$runBody$(); } static final gnu.mapping.SimpleSymbol Lit57; static final gnu.mapping.SimpleSymbol Lit58; static final gnu.mapping.SimpleSymbol Lit59; static final gnu.mapping.SimpleSymbol Lit60; static final gnu.mapping.SimpleSymbol Lit61; static final gnu.mapping.SimpleSymbol Lit62; static final gnu.mapping.SimpleSymbol Lit63; static final gnu.mapping.SimpleSymbol Lit64; static final gnu.mapping.SimpleSymbol Lit65; static final gnu.mapping.SimpleSymbol Lit66; static final gnu.mapping.SimpleSymbol Lit67; static final gnu.mapping.SimpleSymbol Lit68; static final gnu.mapping.SimpleSymbol Lit69; static final gnu.mapping.SimpleSymbol Lit70; static final gnu.mapping.SimpleSymbol Lit71; static final gnu.mapping.SimpleSymbol Lit72; static final gnu.mapping.SimpleSymbol Lit73; static final gnu.mapping.SimpleSymbol Lit74; static final gnu.mapping.SimpleSymbol Lit75; static final gnu.mapping.SimpleSymbol Lit76; static final gnu.mapping.SimpleSymbol Lit77; static final gnu.mapping.SimpleSymbol Lit78; static final gnu.mapping.SimpleSymbol Lit79; static final gnu.mapping.SimpleSymbol Lit80; static final gnu.mapping.SimpleSymbol Lit81; static final gnu.mapping.SimpleSymbol Lit82; static final Object[] Lit83; static final gnu.mapping.SimpleSymbol Lit84; static final gnu.mapping.SimpleSymbol Lit85; static final gnu.mapping.SimpleSymbol Lit86; static final gnu.mapping.SimpleSymbol Lit87; static final gnu.lists.PairWithPosition Lit88; static final gnu.mapping.SimpleSymbol Lit89; static final gnu.mapping.SimpleSymbol Lit90 = gnu.mapping.Symbol.valueOf("set!");
  
  public static boolean isS8vector(Object x)
  {
    return x instanceof gnu.lists.S8Vector;
  }
  
  public static gnu.lists.S8Vector makeS8vector(int n, int init) { return new gnu.lists.S8Vector(n, (byte)init); }
  


































































































































































































































  public int matchN(ModuleMethod paramModuleMethod, Object[] paramArrayOfObject, gnu.mapping.CallContext paramCallContext)
  {
    switch (selector) {case 85:  values = paramArrayOfObject;proc = paramModuleMethod;pc = 5;return 0;
    case 76: 
      values = paramArrayOfObject;proc = paramModuleMethod;pc = 5;return 0;
    case 67: 
      values = paramArrayOfObject;proc = paramModuleMethod;pc = 5;return 0;
    case 58: 
      values = paramArrayOfObject;proc = paramModuleMethod;pc = 5;return 0;
    case 49: 
      values = paramArrayOfObject;proc = paramModuleMethod;pc = 5;return 0;
    case 40: 
      values = paramArrayOfObject;proc = paramModuleMethod;pc = 5;return 0;
    case 31: 
      values = paramArrayOfObject;proc = paramModuleMethod;pc = 5;return 0;
    case 22: 
      values = paramArrayOfObject;proc = paramModuleMethod;pc = 5;return 0;
    case 13: 
      values = paramArrayOfObject;proc = paramModuleMethod;pc = 5;return 0;
    case 4: 
      values = paramArrayOfObject;proc = paramModuleMethod;pc = 5;return 0; } return super.matchN(paramModuleMethod, paramArrayOfObject, paramCallContext); } public static gnu.lists.S8Vector s8vector$V(Object[] argsArray) { gnu.lists.LList localLList1; gnu.lists.LList values = localLList1 = gnu.lists.LList.makeList(argsArray, 0);
    return list$To$S8vector(values);
  }
  
  public static int s8vectorLength(gnu.lists.S8Vector v) { return v.size(); }
  
  public static byte s8vectorRef(gnu.lists.S8Vector v, int i) {
    return v.getByte(i);
  }
  
  public static void s8vectorSet$Ex(gnu.lists.S8Vector v, int i, byte x) { v.setByte(i, x); }
  
  public static gnu.lists.LList s8vector$To$List(gnu.lists.S8Vector v) {
    return gnu.lists.LList.makeList(v);
  }
  










  public static gnu.lists.S8Vector list$To$S8vector(gnu.lists.LList l)
  {
    int n = l.size();byte[] arr = new byte[n];int i = 0;Object localObject1 = l;
    gnu.lists.Pair localPair;
    for (;; )
    {




      if (localObject1 != gnu.lists.LList.Empty) { localPair = (gnu.lists.Pair)gnu.mapping.Promise.force(localObject1, gnu.lists.Pair.class);Object localObject2 = localPair.getCar();localObject3 = gnu.mapping.Promise.force(localObject2);
      }
    }
    byte[] arrayOfByte1 = arr;return new gnu.lists.S8Vector(arrayOfByte1);
  }
  






















  public static gnu.lists.U8Vector list$To$U8vector(gnu.lists.LList l)
  {
    int n = l.size();byte[] arr = new byte[n];int i = 0;Object localObject1 = l;
    gnu.lists.Pair localPair;
    for (;; )
    {




























      if (localObject1 != gnu.lists.LList.Empty) { localPair = (gnu.lists.Pair)gnu.mapping.Promise.force(localObject1, gnu.lists.Pair.class);Object localObject2 = localPair.getCar();localObject3 = gnu.mapping.Promise.force(localObject2);
      }
    }
    byte[] arrayOfByte1 = arr;return new gnu.lists.U8Vector(arrayOfByte1);
  }
  














































  public static gnu.lists.S16Vector list$To$S16vector(gnu.lists.LList l)
  {
    int n = l.size();short[] arr = new short[n];int i = 0;Object localObject1 = l;
    gnu.lists.Pair localPair;
    for (;; )
    {




















































      if (localObject1 != gnu.lists.LList.Empty) { localPair = (gnu.lists.Pair)gnu.mapping.Promise.force(localObject1, gnu.lists.Pair.class);Object localObject2 = localPair.getCar();localObject3 = gnu.mapping.Promise.force(localObject2);
      }
    }
    short[] arrayOfShort1 = arr;return new gnu.lists.S16Vector(arrayOfShort1);
  }
  






































































  public static gnu.lists.U16Vector list$To$U16vector(gnu.lists.LList l)
  {
    int n = l.size();short[] arr = new short[n];int i = 0;Object localObject1 = l;
    gnu.lists.Pair localPair;
    for (;; )
    {












































































      if (localObject1 != gnu.lists.LList.Empty) { localPair = (gnu.lists.Pair)gnu.mapping.Promise.force(localObject1, gnu.lists.Pair.class);Object localObject2 = localPair.getCar();localObject3 = gnu.mapping.Promise.force(localObject2);
      }
    }
    short[] arrayOfShort1 = arr;return new gnu.lists.U16Vector(arrayOfShort1);
  }
  






























































































  public static gnu.lists.S32Vector list$To$S32vector(gnu.lists.LList l)
  {
    int n = l.size();int[] arr = new int[n];int i = 0;Object localObject1 = l;
    gnu.lists.Pair localPair;
    for (;; )
    {




































































































      if (localObject1 != gnu.lists.LList.Empty) { localPair = (gnu.lists.Pair)gnu.mapping.Promise.force(localObject1, gnu.lists.Pair.class);Object localObject2 = localPair.getCar();localObject3 = gnu.mapping.Promise.force(localObject2);
      }
    }
    int[] arrayOfInt1 = arr;return new gnu.lists.S32Vector(arrayOfInt1);
  }
  






















































































































  public static gnu.lists.U32Vector list$To$U32vector(gnu.lists.LList l)
  {
    int n = l.size();int[] arr = new int[n];int i = 0;Object localObject1 = l;
    gnu.lists.Pair localPair;
    for (;; )
    {




























































































































      if (localObject1 != gnu.lists.LList.Empty) { localPair = (gnu.lists.Pair)gnu.mapping.Promise.force(localObject1, gnu.lists.Pair.class);Object localObject2 = localPair.getCar();localObject3 = gnu.mapping.Promise.force(localObject2);
      }
    }
    int[] arrayOfInt1 = arr;return new gnu.lists.U32Vector(arrayOfInt1);
  }
  














































































































































  public static gnu.lists.S64Vector list$To$S64vector(gnu.lists.LList l)
  {
    int n = l.size();long[] arr = new long[n];int i = 0;Object localObject1 = l;
    gnu.lists.Pair localPair;
    for (;; )
    {




















































































































































      if (localObject1 != gnu.lists.LList.Empty) { localPair = (gnu.lists.Pair)gnu.mapping.Promise.force(localObject1, gnu.lists.Pair.class);Object localObject2 = localPair.getCar();localObject3 = gnu.mapping.Promise.force(localObject2);
      }
    }
    long[] arrayOfLong1 = arr;return new gnu.lists.S64Vector(arrayOfLong1);
  }
  






































































































































































  public static gnu.lists.U64Vector list$To$U64vector(gnu.lists.LList l)
  {
    int n = l.size();long[] arr = new long[n];int i = 0;Object localObject1 = l;
    gnu.lists.Pair localPair;
    for (;; )
    {












































































































































































      if (localObject1 != gnu.lists.LList.Empty) { localPair = (gnu.lists.Pair)gnu.mapping.Promise.force(localObject1, gnu.lists.Pair.class);Object localObject2 = localPair.getCar();localObject3 = gnu.mapping.Promise.force(localObject2);
      }
    }
    long[] arrayOfLong1 = arr;return new gnu.lists.U64Vector(arrayOfLong1);
  }
  






























































































































































































  public static gnu.lists.F32Vector list$To$F32vector(gnu.lists.LList l)
  {
    int n = l.size();float[] arr = new float[n];int i = 0;Object localObject1 = l;
    gnu.lists.Pair localPair;
    for (;; )
    {




































































































































































































      if (localObject1 != gnu.lists.LList.Empty) { localPair = (gnu.lists.Pair)gnu.mapping.Promise.force(localObject1, gnu.lists.Pair.class);Object localObject2 = localPair.getCar();localObject3 = gnu.mapping.Promise.force(localObject2);
      }
    }
    float[] arrayOfFloat1 = arr;return new gnu.lists.F32Vector(arrayOfFloat1);
  }
  






















































































































































































































  public static gnu.lists.F64Vector list$To$F64vector(gnu.lists.LList l)
  {
    int n = l.size();double[] arr = new double[n];int i = 0;Object localObject1 = l;
    gnu.lists.Pair localPair;
    for (;; )
    {




























































































































































































































      if (localObject1 != gnu.lists.LList.Empty) { localPair = (gnu.lists.Pair)gnu.mapping.Promise.force(localObject1, gnu.lists.Pair.class);Object localObject2 = localPair.getCar();localObject3 = gnu.mapping.Promise.force(localObject2);
      }
    }
    double[] arrayOfDouble1 = arr;return new gnu.lists.F64Vector(arrayOfDouble1);
  }
  

  public static boolean isU8vector(Object x)
  {
    return x instanceof gnu.lists.U8Vector;
  }
  
  public static gnu.lists.U8Vector makeU8vector(int n, int init) { return new gnu.lists.U8Vector(n, (byte)init); }
  
  public static gnu.lists.U8Vector u8vector$V(Object[] argsArray) { gnu.lists.LList localLList1; gnu.lists.LList values = localLList1 = gnu.lists.LList.makeList(argsArray, 0);
    return list$To$U8vector(values);
  }
  
  public static int u8vectorLength(gnu.lists.U8Vector v) { return v.size(); }
  
  @kawa.SourceMethodType({"ubyte"})
  public static int u8vectorRef(gnu.lists.U8Vector v, int i) { return v.getByte(i); }
  
  @kawa.SourceMethodType({"", "", "", "ubyte"})
  public static void u8vectorSet$Ex(gnu.lists.U8Vector v, int i, int x) { v.setByte(i, x); }
  
  public static gnu.lists.LList u8vector$To$List(gnu.lists.U8Vector v) {
    return gnu.lists.LList.makeList(v);
  }
  

  public static boolean isS16vector(Object x)
  {
    return x instanceof gnu.lists.S16Vector;
  }
  
  public static gnu.lists.S16Vector makeS16vector(int n, int init) { return new gnu.lists.S16Vector(n, (short)init); }
  
  public static gnu.lists.S16Vector s16vector$V(Object[] argsArray) { gnu.lists.LList localLList1; gnu.lists.LList values = localLList1 = gnu.lists.LList.makeList(argsArray, 0);
    return list$To$S16vector(values);
  }
  
  public static int s16vectorLength(gnu.lists.S16Vector v) { return v.size(); }
  
  public static short s16vectorRef(gnu.lists.S16Vector v, int i) {
    return v.getShort(i);
  }
  
  public static void s16vectorSet$Ex(gnu.lists.S16Vector v, int i, short x) { v.setShort(i, x); }
  
  public static gnu.lists.LList s16vector$To$List(gnu.lists.S16Vector v) {
    return gnu.lists.LList.makeList(v);
  }
  

  public static boolean isU16vector(Object x)
  {
    return x instanceof gnu.lists.U16Vector;
  }
  
  public static gnu.lists.U16Vector makeU16vector(int n, int init) { return new gnu.lists.U16Vector(n, (short)init); }
  
  public static gnu.lists.U16Vector u16vector$V(Object[] argsArray) { gnu.lists.LList localLList1; gnu.lists.LList values = localLList1 = gnu.lists.LList.makeList(argsArray, 0);
    return list$To$U16vector(values);
  }
  
  public static int u16vectorLength(gnu.lists.U16Vector v) { return v.size(); }
  
  @kawa.SourceMethodType({"ushort"})
  public static int u16vectorRef(gnu.lists.U16Vector v, int i) { return v.getShort(i); }
  
  @kawa.SourceMethodType({"", "", "", "ushort"})
  public static void u16vectorSet$Ex(gnu.lists.U16Vector v, int i, int x) { v.setShort(i, x); }
  
  public static gnu.lists.LList u16vector$To$List(gnu.lists.U16Vector v) {
    return gnu.lists.LList.makeList(v);
  }
  

  public static boolean isS32vector(Object x)
  {
    return x instanceof gnu.lists.S32Vector;
  }
  
  public static gnu.lists.S32Vector makeS32vector(int n, int init) { return new gnu.lists.S32Vector(n, init); }
  
  public static gnu.lists.S32Vector s32vector$V(Object[] argsArray) { gnu.lists.LList localLList1; gnu.lists.LList values = localLList1 = gnu.lists.LList.makeList(argsArray, 0);
    return list$To$S32vector(values);
  }
  
  public static int s32vectorLength(gnu.lists.S32Vector v) { return v.size(); }
  
  public static int s32vectorRef(gnu.lists.S32Vector v, int i) {
    return v.getInt(i);
  }
  
  public static void s32vectorSet$Ex(gnu.lists.S32Vector v, int i, int x) { v.setInt(i, x); }
  
  public static gnu.lists.LList s32vector$To$List(gnu.lists.S32Vector v) {
    return gnu.lists.LList.makeList(v);
  }
  

  public static boolean isU32vector(Object x)
  {
    return x instanceof gnu.lists.U32Vector;
  }
  
  public static gnu.lists.U32Vector makeU32vector(int n, long init) { return new gnu.lists.U32Vector(n, (int)init); }
  
  public static gnu.lists.U32Vector u32vector$V(Object[] argsArray) { gnu.lists.LList localLList1; gnu.lists.LList values = localLList1 = gnu.lists.LList.makeList(argsArray, 0);
    return list$To$U32vector(values);
  }
  
  public static int u32vectorLength(gnu.lists.U32Vector v) { return v.size(); }
  
  @kawa.SourceMethodType({"uint"})
  public static int u32vectorRef(gnu.lists.U32Vector v, int i) { return v.getInt(i); }
  
  @kawa.SourceMethodType({"", "", "", "uint"})
  public static void u32vectorSet$Ex(gnu.lists.U32Vector v, int i, int x) { v.setInt(i, x); }
  
  public static gnu.lists.LList u32vector$To$List(gnu.lists.U32Vector v) {
    return gnu.lists.LList.makeList(v);
  }
  

  public static boolean isS64vector(Object x)
  {
    return x instanceof gnu.lists.S64Vector;
  }
  
  public static gnu.lists.S64Vector makeS64vector(int n, long init) { return new gnu.lists.S64Vector(n, init); }
  
  public static gnu.lists.S64Vector s64vector$V(Object[] argsArray) { gnu.lists.LList localLList1; gnu.lists.LList values = localLList1 = gnu.lists.LList.makeList(argsArray, 0);
    return list$To$S64vector(values);
  }
  
  public static int s64vectorLength(gnu.lists.S64Vector v) { return v.size(); }
  
  public static long s64vectorRef(gnu.lists.S64Vector v, int i) {
    return v.getLong(i);
  }
  
  public static void s64vectorSet$Ex(gnu.lists.S64Vector v, int i, long x) { v.setLong(i, x); }
  
  public static gnu.lists.LList s64vector$To$List(gnu.lists.S64Vector v) {
    return gnu.lists.LList.makeList(v);
  }
  



  public static boolean isU64vector(Object x) { return x instanceof gnu.lists.U64Vector; }
  
  public static gnu.lists.U64Vector makeU64vector(int n, gnu.math.IntNum init) {
    try { return new gnu.lists.U64Vector(n, (localIntNum = init).longValue()); } catch (ClassCastException localClassCastException) { gnu.math.IntNum localIntNum; throw new gnu.mapping.WrongType(localClassCastException, "gnu.lists.U64Vector.<init>(int,long)", 2, localIntNum); } }
  
  public static gnu.lists.U64Vector u64vector$V(Object[] argsArray) { gnu.lists.LList localLList1; gnu.lists.LList values = localLList1 = gnu.lists.LList.makeList(argsArray, 0);
    return list$To$U64vector(values);
  }
  
  public static int u64vectorLength(gnu.lists.U64Vector v) { return v.size(); }
  
  @kawa.SourceMethodType({"ulong"})
  public static long u64vectorRef(gnu.lists.U64Vector v, int i) { return v.getLong(i); }
  
  @kawa.SourceMethodType({"", "", "", "ulong"})
  public static void u64vectorSet$Ex(gnu.lists.U64Vector v, int i, long x) { v.setLong(i, x); }
  
  public static gnu.lists.LList u64vector$To$List(gnu.lists.U64Vector v) {
    return gnu.lists.LList.makeList(v);
  }
  

  public static boolean isF32vector(Object x)
  {
    return x instanceof gnu.lists.F32Vector;
  }
  
  public static gnu.lists.F32Vector makeF32vector(int n, float init) { return new gnu.lists.F32Vector(n, init); }
  
  public static gnu.lists.F32Vector f32vector$V(Object[] argsArray) { gnu.lists.LList localLList1; gnu.lists.LList values = localLList1 = gnu.lists.LList.makeList(argsArray, 0);
    return list$To$F32vector(values);
  }
  
  public static int f32vectorLength(gnu.lists.F32Vector v) { return v.size(); }
  
  public static float f32vectorRef(gnu.lists.F32Vector v, int i) {
    return v.getFloat(i);
  }
  
  public static void f32vectorSet$Ex(gnu.lists.F32Vector v, int i, float x) { v.setFloat(i, x); }
  
  public static gnu.lists.LList f32vector$To$List(gnu.lists.F32Vector v) {
    return gnu.lists.LList.makeList(v);
  }
  

  public static boolean isF64vector(Object x)
  {
    return x instanceof gnu.lists.F64Vector;
  }
  
  public static gnu.lists.F64Vector makeF64vector(int n, double init) { return new gnu.lists.F64Vector(n, init);
  }
  
  public Object applyN(ModuleMethod paramModuleMethod, Object[] paramArrayOfObject)
  {
    switch (selector) {case 4:  return s8vector$V(paramArrayOfObject);
    

































    case 13: 
      return u8vector$V(paramArrayOfObject);
    





















    case 22: 
      return s16vector$V(paramArrayOfObject);
    





















    case 31: 
      return u16vector$V(paramArrayOfObject);
    





















    case 40: 
      return s32vector$V(paramArrayOfObject);
    





















    case 49: 
      return u32vector$V(paramArrayOfObject);
    





















    case 58: 
      return s64vector$V(paramArrayOfObject);
    





















    case 67: 
      return u64vector$V(paramArrayOfObject);
    





















    case 76: 
      return f32vector$V(paramArrayOfObject);
    





















    case 85: 
      return f64vector$V(paramArrayOfObject); } return super.applyN(paramModuleMethod, paramArrayOfObject); } public static gnu.lists.F64Vector f64vector$V(Object[] argsArray) { gnu.lists.LList localLList1; gnu.lists.LList values = localLList1 = gnu.lists.LList.makeList(argsArray, 0);
    return list$To$F64vector(values);
  }
  
  public static int f64vectorLength(gnu.lists.F64Vector v) { return v.size(); }
  
  public static double f64vectorRef(gnu.lists.F64Vector v, int i) {
    return v.getDouble(i);
  }
  
  public static void f64vectorSet$Ex(gnu.lists.F64Vector v, int i, double x) { v.setDouble(i, x); }
  
  public static gnu.lists.LList f64vector$To$List(gnu.lists.F64Vector v) {
    return gnu.lists.LList.makeList(v);
  }
  
  public Object apply1(ModuleMethod paramModuleMethod, Object paramObject)
  {
    switch (selector) {case 1:  return isS8vector(paramObject) ? Boolean.TRUE : Boolean.FALSE;
    }
    try {
      return makeS8vector(((Number)gnu.mapping.Promise.force(paramObject)).intValue()); } catch (ClassCastException localClassCastException1) { throw new gnu.mapping.WrongType(
      




















































































































































































































































        localClassCastException1, "make-s8vector", 1, paramObject);
    }
    try
    {
      return Integer.valueOf(s8vectorLength((gnu.lists.S8Vector)gnu.mapping.Promise.force(paramObject, gnu.lists.S8Vector.class))); } catch (ClassCastException localClassCastException2) { throw new gnu.mapping.WrongType(localClassCastException2, "s8vector-length", 1, paramObject);
    }
    




    try
    {
      return s8vector$To$List((gnu.lists.S8Vector)gnu.mapping.Promise.force(paramObject, gnu.lists.S8Vector.class)); } catch (ClassCastException localClassCastException3) { throw new gnu.mapping.WrongType(localClassCastException3, "s8vector->list", 1, paramObject);
    }
    










    try
    {
      return list$To$S8vector((gnu.lists.LList)gnu.mapping.Promise.force(paramObject, gnu.lists.LList.class)); } catch (ClassCastException localClassCastException4) { throw new gnu.mapping.WrongType(localClassCastException4, "list->s8vector", 1, paramObject);
    }
    
    return isU8vector(paramObject) ? Boolean.TRUE : Boolean.FALSE;
    try
    {
      return makeU8vector(((Number)gnu.mapping.Promise.force(paramObject)).intValue()); } catch (ClassCastException localClassCastException5) { throw new gnu.mapping.WrongType(localClassCastException5, "make-u8vector", 1, paramObject);
    }
    

    try
    {
      return Integer.valueOf(u8vectorLength((gnu.lists.U8Vector)gnu.mapping.Promise.force(paramObject, gnu.lists.U8Vector.class))); } catch (ClassCastException localClassCastException6) { throw new gnu.mapping.WrongType(localClassCastException6, "u8vector-length", 1, paramObject);
    }
    




    try
    {
      return u8vector$To$List((gnu.lists.U8Vector)gnu.mapping.Promise.force(paramObject, gnu.lists.U8Vector.class)); } catch (ClassCastException localClassCastException7) { throw new gnu.mapping.WrongType(localClassCastException7, "u8vector->list", 1, paramObject);
    }
    try {
      return list$To$U8vector((gnu.lists.LList)gnu.mapping.Promise.force(paramObject, gnu.lists.LList.class)); } catch (ClassCastException localClassCastException8) { throw new gnu.mapping.WrongType(localClassCastException8, "list->u8vector", 1, paramObject);
    }
    
    return isS16vector(paramObject) ? Boolean.TRUE : Boolean.FALSE;
    try
    {
      return makeS16vector(((Number)gnu.mapping.Promise.force(paramObject)).intValue()); } catch (ClassCastException localClassCastException9) { throw new gnu.mapping.WrongType(localClassCastException9, "make-s16vector", 1, paramObject);
    }
    

    try
    {
      return Integer.valueOf(s16vectorLength((gnu.lists.S16Vector)gnu.mapping.Promise.force(paramObject, gnu.lists.S16Vector.class))); } catch (ClassCastException localClassCastException10) { throw new gnu.mapping.WrongType(localClassCastException10, "s16vector-length", 1, paramObject);
    }
    




    try
    {
      return s16vector$To$List((gnu.lists.S16Vector)gnu.mapping.Promise.force(paramObject, gnu.lists.S16Vector.class)); } catch (ClassCastException localClassCastException11) { throw new gnu.mapping.WrongType(localClassCastException11, "s16vector->list", 1, paramObject);
    }
    try {
      return list$To$S16vector((gnu.lists.LList)gnu.mapping.Promise.force(paramObject, gnu.lists.LList.class)); } catch (ClassCastException localClassCastException12) { throw new gnu.mapping.WrongType(localClassCastException12, "list->s16vector", 1, paramObject);
    }
    
    return isU16vector(paramObject) ? Boolean.TRUE : Boolean.FALSE;
    try
    {
      return makeU16vector(((Number)gnu.mapping.Promise.force(paramObject)).intValue()); } catch (ClassCastException localClassCastException13) { throw new gnu.mapping.WrongType(localClassCastException13, "make-u16vector", 1, paramObject);
    }
    

    try
    {
      return Integer.valueOf(u16vectorLength((gnu.lists.U16Vector)gnu.mapping.Promise.force(paramObject, gnu.lists.U16Vector.class))); } catch (ClassCastException localClassCastException14) { throw new gnu.mapping.WrongType(localClassCastException14, "u16vector-length", 1, paramObject);
    }
    




    try
    {
      return u16vector$To$List((gnu.lists.U16Vector)gnu.mapping.Promise.force(paramObject, gnu.lists.U16Vector.class)); } catch (ClassCastException localClassCastException15) { throw new gnu.mapping.WrongType(localClassCastException15, "u16vector->list", 1, paramObject);
    }
    try {
      return list$To$U16vector((gnu.lists.LList)gnu.mapping.Promise.force(paramObject, gnu.lists.LList.class)); } catch (ClassCastException localClassCastException16) { throw new gnu.mapping.WrongType(localClassCastException16, "list->u16vector", 1, paramObject);
    }
    
    return isS32vector(paramObject) ? Boolean.TRUE : Boolean.FALSE;
    try
    {
      return makeS32vector(((Number)gnu.mapping.Promise.force(paramObject)).intValue()); } catch (ClassCastException localClassCastException17) { throw new gnu.mapping.WrongType(localClassCastException17, "make-s32vector", 1, paramObject);
    }
    

    try
    {
      return Integer.valueOf(s32vectorLength((gnu.lists.S32Vector)gnu.mapping.Promise.force(paramObject, gnu.lists.S32Vector.class))); } catch (ClassCastException localClassCastException18) { throw new gnu.mapping.WrongType(localClassCastException18, "s32vector-length", 1, paramObject);
    }
    




    try
    {
      return s32vector$To$List((gnu.lists.S32Vector)gnu.mapping.Promise.force(paramObject, gnu.lists.S32Vector.class)); } catch (ClassCastException localClassCastException19) { throw new gnu.mapping.WrongType(localClassCastException19, "s32vector->list", 1, paramObject);
    }
    try {
      return list$To$S32vector((gnu.lists.LList)gnu.mapping.Promise.force(paramObject, gnu.lists.LList.class)); } catch (ClassCastException localClassCastException20) { throw new gnu.mapping.WrongType(localClassCastException20, "list->s32vector", 1, paramObject);
    }
    
    return isU32vector(paramObject) ? Boolean.TRUE : Boolean.FALSE;
    try
    {
      return makeU32vector(((Number)gnu.mapping.Promise.force(paramObject)).intValue()); } catch (ClassCastException localClassCastException21) { throw new gnu.mapping.WrongType(localClassCastException21, "make-u32vector", 1, paramObject);
    }
    

    try
    {
      return Integer.valueOf(u32vectorLength((gnu.lists.U32Vector)gnu.mapping.Promise.force(paramObject, gnu.lists.U32Vector.class))); } catch (ClassCastException localClassCastException22) { throw new gnu.mapping.WrongType(localClassCastException22, "u32vector-length", 1, paramObject);
    }
    




    try
    {
      return u32vector$To$List((gnu.lists.U32Vector)gnu.mapping.Promise.force(paramObject, gnu.lists.U32Vector.class)); } catch (ClassCastException localClassCastException23) { throw new gnu.mapping.WrongType(localClassCastException23, "u32vector->list", 1, paramObject);
    }
    try {
      return list$To$U32vector((gnu.lists.LList)gnu.mapping.Promise.force(paramObject, gnu.lists.LList.class)); } catch (ClassCastException localClassCastException24) { throw new gnu.mapping.WrongType(localClassCastException24, "list->u32vector", 1, paramObject);
    }
    
    return isS64vector(paramObject) ? Boolean.TRUE : Boolean.FALSE;
    try
    {
      return makeS64vector(((Number)gnu.mapping.Promise.force(paramObject)).intValue()); } catch (ClassCastException localClassCastException25) { throw new gnu.mapping.WrongType(localClassCastException25, "make-s64vector", 1, paramObject);
    }
    

    try
    {
      return Integer.valueOf(s64vectorLength((gnu.lists.S64Vector)gnu.mapping.Promise.force(paramObject, gnu.lists.S64Vector.class))); } catch (ClassCastException localClassCastException26) { throw new gnu.mapping.WrongType(localClassCastException26, "s64vector-length", 1, paramObject);
    }
    




    try
    {
      return s64vector$To$List((gnu.lists.S64Vector)gnu.mapping.Promise.force(paramObject, gnu.lists.S64Vector.class)); } catch (ClassCastException localClassCastException27) { throw new gnu.mapping.WrongType(localClassCastException27, "s64vector->list", 1, paramObject);
    }
    try {
      return list$To$S64vector((gnu.lists.LList)gnu.mapping.Promise.force(paramObject, gnu.lists.LList.class)); } catch (ClassCastException localClassCastException28) { throw new gnu.mapping.WrongType(localClassCastException28, "list->s64vector", 1, paramObject);
    }
    
    return isU64vector(paramObject) ? Boolean.TRUE : Boolean.FALSE;
    try
    {
      return makeU64vector(((Number)gnu.mapping.Promise.force(paramObject)).intValue()); } catch (ClassCastException localClassCastException29) { throw new gnu.mapping.WrongType(localClassCastException29, "make-u64vector", 1, paramObject);
    }
    

    try
    {
      return Integer.valueOf(u64vectorLength((gnu.lists.U64Vector)gnu.mapping.Promise.force(paramObject, gnu.lists.U64Vector.class))); } catch (ClassCastException localClassCastException30) { throw new gnu.mapping.WrongType(localClassCastException30, "u64vector-length", 1, paramObject);
    }
    




    try
    {
      return u64vector$To$List((gnu.lists.U64Vector)gnu.mapping.Promise.force(paramObject, gnu.lists.U64Vector.class)); } catch (ClassCastException localClassCastException31) { throw new gnu.mapping.WrongType(localClassCastException31, "u64vector->list", 1, paramObject);
    }
    try {
      return list$To$U64vector((gnu.lists.LList)gnu.mapping.Promise.force(paramObject, gnu.lists.LList.class)); } catch (ClassCastException localClassCastException32) { throw new gnu.mapping.WrongType(localClassCastException32, "list->u64vector", 1, paramObject);
    }
    
    return isF32vector(paramObject) ? Boolean.TRUE : Boolean.FALSE;
    try
    {
      return makeF32vector(((Number)gnu.mapping.Promise.force(paramObject)).intValue()); } catch (ClassCastException localClassCastException33) { throw new gnu.mapping.WrongType(localClassCastException33, "make-f32vector", 1, paramObject);
    }
    

    try
    {
      return Integer.valueOf(f32vectorLength((gnu.lists.F32Vector)gnu.mapping.Promise.force(paramObject, gnu.lists.F32Vector.class))); } catch (ClassCastException localClassCastException34) { throw new gnu.mapping.WrongType(localClassCastException34, "f32vector-length", 1, paramObject);
    }
    




    try
    {
      return f32vector$To$List((gnu.lists.F32Vector)gnu.mapping.Promise.force(paramObject, gnu.lists.F32Vector.class)); } catch (ClassCastException localClassCastException35) { throw new gnu.mapping.WrongType(localClassCastException35, "f32vector->list", 1, paramObject);
    }
    try {
      return list$To$F32vector((gnu.lists.LList)gnu.mapping.Promise.force(paramObject, gnu.lists.LList.class)); } catch (ClassCastException localClassCastException36) { throw new gnu.mapping.WrongType(localClassCastException36, "list->f32vector", 1, paramObject);
    }
    
    return isF64vector(paramObject) ? Boolean.TRUE : Boolean.FALSE;
    try
    {
      return makeF64vector(((Number)gnu.mapping.Promise.force(paramObject)).intValue()); } catch (ClassCastException localClassCastException37) { throw new gnu.mapping.WrongType(localClassCastException37, "make-f64vector", 1, paramObject);
    }
    

    try
    {
      return Integer.valueOf(f64vectorLength((gnu.lists.F64Vector)gnu.mapping.Promise.force(paramObject, gnu.lists.F64Vector.class))); } catch (ClassCastException localClassCastException38) { throw new gnu.mapping.WrongType(localClassCastException38, "f64vector-length", 1, paramObject);
    }
    




    try
    {
      return f64vector$To$List((gnu.lists.F64Vector)gnu.mapping.Promise.force(paramObject, gnu.lists.F64Vector.class)); } catch (ClassCastException localClassCastException39) { throw new gnu.mapping.WrongType(localClassCastException39, "f64vector->list", 1, paramObject);
    }
    try {
      return list$To$F64vector((gnu.lists.LList)gnu.mapping.Promise.force(paramObject, gnu.lists.LList.class)); } catch (ClassCastException localClassCastException40) { throw new gnu.mapping.WrongType(localClassCastException40, "list->f64vector", 1, paramObject); } return super.apply1(paramModuleMethod, paramObject);
  }
  
  public static gnu.lists.S8Vector makeS8vector(int paramInt)
  {
    return makeS8vector(paramInt, 0);
  }
  
  public static gnu.lists.U8Vector makeU8vector(int paramInt)
  {
    return makeU8vector(paramInt, 0);
  }
  
  public static gnu.lists.S16Vector makeS16vector(int paramInt)
  {
    return makeS16vector(paramInt, 0);
  }
  
  public static gnu.lists.U16Vector makeU16vector(int paramInt)
  {
    return makeU16vector(paramInt, 0);
  }
  
  public static gnu.lists.S32Vector makeS32vector(int paramInt)
  {
    return makeS32vector(paramInt, 0);
  }
  
  public static gnu.lists.U32Vector makeU32vector(int paramInt)
  {
    return makeU32vector(paramInt, 0L);
  }
  
  public static gnu.lists.S64Vector makeS64vector(int paramInt)
  {
    return makeS64vector(paramInt, 0L);
  }
  
  public static gnu.lists.U64Vector makeU64vector(int paramInt)
  {
    return makeU64vector(paramInt, Lit0);
  }
  
  public static gnu.lists.F32Vector makeF32vector(int paramInt)
  {
    return makeF32vector(paramInt, 0.0F);
  }
  
  public static gnu.lists.F64Vector makeF64vector(int paramInt)
  {
    return makeF64vector(paramInt, 0.0D);
  }
  
  public uniform()
  {
    gnu.expr.ModuleInfo.register(this);
  }
  
  /* Error */
  public int match1(ModuleMethod arg1, Object arg2, gnu.mapping.CallContext arg3)
  {
    // Byte code:
    //   0: aload_1
    //   1: getfield 831	gnu/expr/ModuleMethod:selector	I
    //   4: tableswitch	default:+1768->1772, 1:+1751->1755, 2:+1731->1735, 3:+1768->1772, 4:+1768->1772, 5:+1698->1702, 6:+1768->1772, 7:+1768->1772, 8:+1665->1669, 9:+1629->1633, 10:+1612->1616, 11:+1592->1596, 12:+1768->1772, 13:+1768->1772, 14:+1559->1563, 15:+1768->1772, 16:+1768->1772, 17:+1526->1530, 18:+1490->1494, 19:+1473->1477, 20:+1453->1457, 21:+1768->1772, 22:+1768->1772, 23:+1420->1424, 24:+1768->1772, 25:+1768->1772, 26:+1387->1391, 27:+1351->1355, 28:+1334->1338, 29:+1314->1318, 30:+1768->1772, 31:+1768->1772, 32:+1281->1285, 33:+1768->1772, 34:+1768->1772, 35:+1248->1252, 36:+1212->1216, 37:+1195->1199, 38:+1175->1179, 39:+1768->1772, 40:+1768->1772, 41:+1142->1146, 42:+1768->1772, 43:+1768->1772, 44:+1109->1113, 45:+1073->1077, 46:+1056->1060, 47:+1036->1040, 48:+1768->1772, 49:+1768->1772, 50:+1003->1007, 51:+1768->1772, 52:+1768->1772, 53:+970->974, 54:+934->938, 55:+917->921, 56:+897->901, 57:+1768->1772, 58:+1768->1772, 59:+864->868, 60:+1768->1772, 61:+1768->1772, 62:+831->835, 63:+795->799, 64:+778->782, 65:+758->762, 66:+1768->1772, 67:+1768->1772, 68:+725->729, 69:+1768->1772, 70:+1768->1772, 71:+692->696, 72:+656->660, 73:+639->643, 74:+619->623, 75:+1768->1772, 76:+1768->1772, 77:+586->590, 78:+1768->1772, 79:+1768->1772, 80:+553->557, 81:+517->521, 82:+500->504, 83:+480->484, 84:+1768->1772, 85:+1768->1772, 86:+446->450, 87:+1768->1772, 88:+1768->1772, 89:+412->416, 90:+376->380
    //   380: aload_3
    //   381: aload_2
    //   382: ldc 24
    //   384: invokestatic 59	gnu/mapping/Promise:force	(Ljava/lang/Object;Ljava/lang/Class;)Ljava/lang/Object;
    //   387: dup
    //   388: instanceof 24
    //   391: ifeq +6 -> 397
    //   394: goto +7 -> 401
    //   397: ldc_w 832
    //   400: ireturn
    //   401: putfield 836	gnu/mapping/CallContext:value1	Ljava/lang/Object;
    //   404: aload_3
    //   405: aload_1
    //   406: putfield 840	gnu/mapping/CallContext:proc	Lgnu/mapping/Procedure;
    //   409: aload_3
    //   410: iconst_1
    //   411: putfield 843	gnu/mapping/CallContext:pc	I
    //   414: iconst_0
    //   415: ireturn
    //   416: aload_3
    //   417: aload_2
    //   418: ldc_w 258
    //   421: invokestatic 59	gnu/mapping/Promise:force	(Ljava/lang/Object;Ljava/lang/Class;)Ljava/lang/Object;
    //   424: dup
    //   425: instanceof 258
    //   428: ifne +7 -> 435
    //   431: ldc_w 832
    //   434: ireturn
    //   435: putfield 836	gnu/mapping/CallContext:value1	Ljava/lang/Object;
    //   438: aload_3
    //   439: aload_1
    //   440: putfield 840	gnu/mapping/CallContext:proc	Lgnu/mapping/Procedure;
    //   443: aload_3
    //   444: iconst_1
    //   445: putfield 843	gnu/mapping/CallContext:pc	I
    //   448: iconst_0
    //   449: ireturn
    //   450: aload_3
    //   451: aload_2
    //   452: ldc_w 258
    //   455: invokestatic 59	gnu/mapping/Promise:force	(Ljava/lang/Object;Ljava/lang/Class;)Ljava/lang/Object;
    //   458: dup
    //   459: instanceof 258
    //   462: ifne +7 -> 469
    //   465: ldc_w 832
    //   468: ireturn
    //   469: putfield 836	gnu/mapping/CallContext:value1	Ljava/lang/Object;
    //   472: aload_3
    //   473: aload_1
    //   474: putfield 840	gnu/mapping/CallContext:proc	Lgnu/mapping/Procedure;
    //   477: aload_3
    //   478: iconst_1
    //   479: putfield 843	gnu/mapping/CallContext:pc	I
    //   482: iconst_0
    //   483: ireturn
    //   484: aload_3
    //   485: aload_2
    //   486: invokestatic 66	gnu/mapping/Promise:force	(Ljava/lang/Object;)Ljava/lang/Object;
    //   489: putfield 836	gnu/mapping/CallContext:value1	Ljava/lang/Object;
    //   492: aload_3
    //   493: aload_1
    //   494: putfield 840	gnu/mapping/CallContext:proc	Lgnu/mapping/Procedure;
    //   497: aload_3
    //   498: iconst_1
    //   499: putfield 843	gnu/mapping/CallContext:pc	I
    //   502: iconst_0
    //   503: ireturn
    //   504: aload_3
    //   505: aload_2
    //   506: putfield 836	gnu/mapping/CallContext:value1	Ljava/lang/Object;
    //   509: aload_3
    //   510: aload_1
    //   511: putfield 840	gnu/mapping/CallContext:proc	Lgnu/mapping/Procedure;
    //   514: aload_3
    //   515: iconst_1
    //   516: putfield 843	gnu/mapping/CallContext:pc	I
    //   519: iconst_0
    //   520: ireturn
    //   521: aload_3
    //   522: aload_2
    //   523: ldc 24
    //   525: invokestatic 59	gnu/mapping/Promise:force	(Ljava/lang/Object;Ljava/lang/Class;)Ljava/lang/Object;
    //   528: dup
    //   529: instanceof 24
    //   532: ifeq +6 -> 538
    //   535: goto +7 -> 542
    //   538: ldc_w 832
    //   541: ireturn
    //   542: putfield 836	gnu/mapping/CallContext:value1	Ljava/lang/Object;
    //   545: aload_3
    //   546: aload_1
    //   547: putfield 840	gnu/mapping/CallContext:proc	Lgnu/mapping/Procedure;
    //   550: aload_3
    //   551: iconst_1
    //   552: putfield 843	gnu/mapping/CallContext:pc	I
    //   555: iconst_0
    //   556: ireturn
    //   557: aload_3
    //   558: aload_2
    //   559: ldc -26
    //   561: invokestatic 59	gnu/mapping/Promise:force	(Ljava/lang/Object;Ljava/lang/Class;)Ljava/lang/Object;
    //   564: dup
    //   565: instanceof 230
    //   568: ifne +7 -> 575
    //   571: ldc_w 832
    //   574: ireturn
    //   575: putfield 836	gnu/mapping/CallContext:value1	Ljava/lang/Object;
    //   578: aload_3
    //   579: aload_1
    //   580: putfield 840	gnu/mapping/CallContext:proc	Lgnu/mapping/Procedure;
    //   583: aload_3
    //   584: iconst_1
    //   585: putfield 843	gnu/mapping/CallContext:pc	I
    //   588: iconst_0
    //   589: ireturn
    //   590: aload_3
    //   591: aload_2
    //   592: ldc -26
    //   594: invokestatic 59	gnu/mapping/Promise:force	(Ljava/lang/Object;Ljava/lang/Class;)Ljava/lang/Object;
    //   597: dup
    //   598: instanceof 230
    //   601: ifne +7 -> 608
    //   604: ldc_w 832
    //   607: ireturn
    //   608: putfield 836	gnu/mapping/CallContext:value1	Ljava/lang/Object;
    //   611: aload_3
    //   612: aload_1
    //   613: putfield 840	gnu/mapping/CallContext:proc	Lgnu/mapping/Procedure;
    //   616: aload_3
    //   617: iconst_1
    //   618: putfield 843	gnu/mapping/CallContext:pc	I
    //   621: iconst_0
    //   622: ireturn
    //   623: aload_3
    //   624: aload_2
    //   625: invokestatic 66	gnu/mapping/Promise:force	(Ljava/lang/Object;)Ljava/lang/Object;
    //   628: putfield 836	gnu/mapping/CallContext:value1	Ljava/lang/Object;
    //   631: aload_3
    //   632: aload_1
    //   633: putfield 840	gnu/mapping/CallContext:proc	Lgnu/mapping/Procedure;
    //   636: aload_3
    //   637: iconst_1
    //   638: putfield 843	gnu/mapping/CallContext:pc	I
    //   641: iconst_0
    //   642: ireturn
    //   643: aload_3
    //   644: aload_2
    //   645: putfield 836	gnu/mapping/CallContext:value1	Ljava/lang/Object;
    //   648: aload_3
    //   649: aload_1
    //   650: putfield 840	gnu/mapping/CallContext:proc	Lgnu/mapping/Procedure;
    //   653: aload_3
    //   654: iconst_1
    //   655: putfield 843	gnu/mapping/CallContext:pc	I
    //   658: iconst_0
    //   659: ireturn
    //   660: aload_3
    //   661: aload_2
    //   662: ldc 24
    //   664: invokestatic 59	gnu/mapping/Promise:force	(Ljava/lang/Object;Ljava/lang/Class;)Ljava/lang/Object;
    //   667: dup
    //   668: instanceof 24
    //   671: ifeq +6 -> 677
    //   674: goto +7 -> 681
    //   677: ldc_w 832
    //   680: ireturn
    //   681: putfield 836	gnu/mapping/CallContext:value1	Ljava/lang/Object;
    //   684: aload_3
    //   685: aload_1
    //   686: putfield 840	gnu/mapping/CallContext:proc	Lgnu/mapping/Procedure;
    //   689: aload_3
    //   690: iconst_1
    //   691: putfield 843	gnu/mapping/CallContext:pc	I
    //   694: iconst_0
    //   695: ireturn
    //   696: aload_3
    //   697: aload_2
    //   698: ldc -47
    //   700: invokestatic 59	gnu/mapping/Promise:force	(Ljava/lang/Object;Ljava/lang/Class;)Ljava/lang/Object;
    //   703: dup
    //   704: instanceof 209
    //   707: ifne +7 -> 714
    //   710: ldc_w 832
    //   713: ireturn
    //   714: putfield 836	gnu/mapping/CallContext:value1	Ljava/lang/Object;
    //   717: aload_3
    //   718: aload_1
    //   719: putfield 840	gnu/mapping/CallContext:proc	Lgnu/mapping/Procedure;
    //   722: aload_3
    //   723: iconst_1
    //   724: putfield 843	gnu/mapping/CallContext:pc	I
    //   727: iconst_0
    //   728: ireturn
    //   729: aload_3
    //   730: aload_2
    //   731: ldc -47
    //   733: invokestatic 59	gnu/mapping/Promise:force	(Ljava/lang/Object;Ljava/lang/Class;)Ljava/lang/Object;
    //   736: dup
    //   737: instanceof 209
    //   740: ifne +7 -> 747
    //   743: ldc_w 832
    //   746: ireturn
    //   747: putfield 836	gnu/mapping/CallContext:value1	Ljava/lang/Object;
    //   750: aload_3
    //   751: aload_1
    //   752: putfield 840	gnu/mapping/CallContext:proc	Lgnu/mapping/Procedure;
    //   755: aload_3
    //   756: iconst_1
    //   757: putfield 843	gnu/mapping/CallContext:pc	I
    //   760: iconst_0
    //   761: ireturn
    //   762: aload_3
    //   763: aload_2
    //   764: invokestatic 66	gnu/mapping/Promise:force	(Ljava/lang/Object;)Ljava/lang/Object;
    //   767: putfield 836	gnu/mapping/CallContext:value1	Ljava/lang/Object;
    //   770: aload_3
    //   771: aload_1
    //   772: putfield 840	gnu/mapping/CallContext:proc	Lgnu/mapping/Procedure;
    //   775: aload_3
    //   776: iconst_1
    //   777: putfield 843	gnu/mapping/CallContext:pc	I
    //   780: iconst_0
    //   781: ireturn
    //   782: aload_3
    //   783: aload_2
    //   784: putfield 836	gnu/mapping/CallContext:value1	Ljava/lang/Object;
    //   787: aload_3
    //   788: aload_1
    //   789: putfield 840	gnu/mapping/CallContext:proc	Lgnu/mapping/Procedure;
    //   792: aload_3
    //   793: iconst_1
    //   794: putfield 843	gnu/mapping/CallContext:pc	I
    //   797: iconst_0
    //   798: ireturn
    //   799: aload_3
    //   800: aload_2
    //   801: ldc 24
    //   803: invokestatic 59	gnu/mapping/Promise:force	(Ljava/lang/Object;Ljava/lang/Class;)Ljava/lang/Object;
    //   806: dup
    //   807: instanceof 24
    //   810: ifeq +6 -> 816
    //   813: goto +7 -> 820
    //   816: ldc_w 832
    //   819: ireturn
    //   820: putfield 836	gnu/mapping/CallContext:value1	Ljava/lang/Object;
    //   823: aload_3
    //   824: aload_1
    //   825: putfield 840	gnu/mapping/CallContext:proc	Lgnu/mapping/Procedure;
    //   828: aload_3
    //   829: iconst_1
    //   830: putfield 843	gnu/mapping/CallContext:pc	I
    //   833: iconst_0
    //   834: ireturn
    //   835: aload_3
    //   836: aload_2
    //   837: ldc -75
    //   839: invokestatic 59	gnu/mapping/Promise:force	(Ljava/lang/Object;Ljava/lang/Class;)Ljava/lang/Object;
    //   842: dup
    //   843: instanceof 181
    //   846: ifne +7 -> 853
    //   849: ldc_w 832
    //   852: ireturn
    //   853: putfield 836	gnu/mapping/CallContext:value1	Ljava/lang/Object;
    //   856: aload_3
    //   857: aload_1
    //   858: putfield 840	gnu/mapping/CallContext:proc	Lgnu/mapping/Procedure;
    //   861: aload_3
    //   862: iconst_1
    //   863: putfield 843	gnu/mapping/CallContext:pc	I
    //   866: iconst_0
    //   867: ireturn
    //   868: aload_3
    //   869: aload_2
    //   870: ldc -75
    //   872: invokestatic 59	gnu/mapping/Promise:force	(Ljava/lang/Object;Ljava/lang/Class;)Ljava/lang/Object;
    //   875: dup
    //   876: instanceof 181
    //   879: ifne +7 -> 886
    //   882: ldc_w 832
    //   885: ireturn
    //   886: putfield 836	gnu/mapping/CallContext:value1	Ljava/lang/Object;
    //   889: aload_3
    //   890: aload_1
    //   891: putfield 840	gnu/mapping/CallContext:proc	Lgnu/mapping/Procedure;
    //   894: aload_3
    //   895: iconst_1
    //   896: putfield 843	gnu/mapping/CallContext:pc	I
    //   899: iconst_0
    //   900: ireturn
    //   901: aload_3
    //   902: aload_2
    //   903: invokestatic 66	gnu/mapping/Promise:force	(Ljava/lang/Object;)Ljava/lang/Object;
    //   906: putfield 836	gnu/mapping/CallContext:value1	Ljava/lang/Object;
    //   909: aload_3
    //   910: aload_1
    //   911: putfield 840	gnu/mapping/CallContext:proc	Lgnu/mapping/Procedure;
    //   914: aload_3
    //   915: iconst_1
    //   916: putfield 843	gnu/mapping/CallContext:pc	I
    //   919: iconst_0
    //   920: ireturn
    //   921: aload_3
    //   922: aload_2
    //   923: putfield 836	gnu/mapping/CallContext:value1	Ljava/lang/Object;
    //   926: aload_3
    //   927: aload_1
    //   928: putfield 840	gnu/mapping/CallContext:proc	Lgnu/mapping/Procedure;
    //   931: aload_3
    //   932: iconst_1
    //   933: putfield 843	gnu/mapping/CallContext:pc	I
    //   936: iconst_0
    //   937: ireturn
    //   938: aload_3
    //   939: aload_2
    //   940: ldc 24
    //   942: invokestatic 59	gnu/mapping/Promise:force	(Ljava/lang/Object;Ljava/lang/Class;)Ljava/lang/Object;
    //   945: dup
    //   946: instanceof 24
    //   949: ifeq +6 -> 955
    //   952: goto +7 -> 959
    //   955: ldc_w 832
    //   958: ireturn
    //   959: putfield 836	gnu/mapping/CallContext:value1	Ljava/lang/Object;
    //   962: aload_3
    //   963: aload_1
    //   964: putfield 840	gnu/mapping/CallContext:proc	Lgnu/mapping/Procedure;
    //   967: aload_3
    //   968: iconst_1
    //   969: putfield 843	gnu/mapping/CallContext:pc	I
    //   972: iconst_0
    //   973: ireturn
    //   974: aload_3
    //   975: aload_2
    //   976: ldc -90
    //   978: invokestatic 59	gnu/mapping/Promise:force	(Ljava/lang/Object;Ljava/lang/Class;)Ljava/lang/Object;
    //   981: dup
    //   982: instanceof 166
    //   985: ifne +7 -> 992
    //   988: ldc_w 832
    //   991: ireturn
    //   992: putfield 836	gnu/mapping/CallContext:value1	Ljava/lang/Object;
    //   995: aload_3
    //   996: aload_1
    //   997: putfield 840	gnu/mapping/CallContext:proc	Lgnu/mapping/Procedure;
    //   1000: aload_3
    //   1001: iconst_1
    //   1002: putfield 843	gnu/mapping/CallContext:pc	I
    //   1005: iconst_0
    //   1006: ireturn
    //   1007: aload_3
    //   1008: aload_2
    //   1009: ldc -90
    //   1011: invokestatic 59	gnu/mapping/Promise:force	(Ljava/lang/Object;Ljava/lang/Class;)Ljava/lang/Object;
    //   1014: dup
    //   1015: instanceof 166
    //   1018: ifne +7 -> 1025
    //   1021: ldc_w 832
    //   1024: ireturn
    //   1025: putfield 836	gnu/mapping/CallContext:value1	Ljava/lang/Object;
    //   1028: aload_3
    //   1029: aload_1
    //   1030: putfield 840	gnu/mapping/CallContext:proc	Lgnu/mapping/Procedure;
    //   1033: aload_3
    //   1034: iconst_1
    //   1035: putfield 843	gnu/mapping/CallContext:pc	I
    //   1038: iconst_0
    //   1039: ireturn
    //   1040: aload_3
    //   1041: aload_2
    //   1042: invokestatic 66	gnu/mapping/Promise:force	(Ljava/lang/Object;)Ljava/lang/Object;
    //   1045: putfield 836	gnu/mapping/CallContext:value1	Ljava/lang/Object;
    //   1048: aload_3
    //   1049: aload_1
    //   1050: putfield 840	gnu/mapping/CallContext:proc	Lgnu/mapping/Procedure;
    //   1053: aload_3
    //   1054: iconst_1
    //   1055: putfield 843	gnu/mapping/CallContext:pc	I
    //   1058: iconst_0
    //   1059: ireturn
    //   1060: aload_3
    //   1061: aload_2
    //   1062: putfield 836	gnu/mapping/CallContext:value1	Ljava/lang/Object;
    //   1065: aload_3
    //   1066: aload_1
    //   1067: putfield 840	gnu/mapping/CallContext:proc	Lgnu/mapping/Procedure;
    //   1070: aload_3
    //   1071: iconst_1
    //   1072: putfield 843	gnu/mapping/CallContext:pc	I
    //   1075: iconst_0
    //   1076: ireturn
    //   1077: aload_3
    //   1078: aload_2
    //   1079: ldc 24
    //   1081: invokestatic 59	gnu/mapping/Promise:force	(Ljava/lang/Object;Ljava/lang/Class;)Ljava/lang/Object;
    //   1084: dup
    //   1085: instanceof 24
    //   1088: ifeq +6 -> 1094
    //   1091: goto +7 -> 1098
    //   1094: ldc_w 832
    //   1097: ireturn
    //   1098: putfield 836	gnu/mapping/CallContext:value1	Ljava/lang/Object;
    //   1101: aload_3
    //   1102: aload_1
    //   1103: putfield 840	gnu/mapping/CallContext:proc	Lgnu/mapping/Procedure;
    //   1106: aload_3
    //   1107: iconst_1
    //   1108: putfield 843	gnu/mapping/CallContext:pc	I
    //   1111: iconst_0
    //   1112: ireturn
    //   1113: aload_3
    //   1114: aload_2
    //   1115: ldc -114
    //   1117: invokestatic 59	gnu/mapping/Promise:force	(Ljava/lang/Object;Ljava/lang/Class;)Ljava/lang/Object;
    //   1120: dup
    //   1121: instanceof 142
    //   1124: ifne +7 -> 1131
    //   1127: ldc_w 832
    //   1130: ireturn
    //   1131: putfield 836	gnu/mapping/CallContext:value1	Ljava/lang/Object;
    //   1134: aload_3
    //   1135: aload_1
    //   1136: putfield 840	gnu/mapping/CallContext:proc	Lgnu/mapping/Procedure;
    //   1139: aload_3
    //   1140: iconst_1
    //   1141: putfield 843	gnu/mapping/CallContext:pc	I
    //   1144: iconst_0
    //   1145: ireturn
    //   1146: aload_3
    //   1147: aload_2
    //   1148: ldc -114
    //   1150: invokestatic 59	gnu/mapping/Promise:force	(Ljava/lang/Object;Ljava/lang/Class;)Ljava/lang/Object;
    //   1153: dup
    //   1154: instanceof 142
    //   1157: ifne +7 -> 1164
    //   1160: ldc_w 832
    //   1163: ireturn
    //   1164: putfield 836	gnu/mapping/CallContext:value1	Ljava/lang/Object;
    //   1167: aload_3
    //   1168: aload_1
    //   1169: putfield 840	gnu/mapping/CallContext:proc	Lgnu/mapping/Procedure;
    //   1172: aload_3
    //   1173: iconst_1
    //   1174: putfield 843	gnu/mapping/CallContext:pc	I
    //   1177: iconst_0
    //   1178: ireturn
    //   1179: aload_3
    //   1180: aload_2
    //   1181: invokestatic 66	gnu/mapping/Promise:force	(Ljava/lang/Object;)Ljava/lang/Object;
    //   1184: putfield 836	gnu/mapping/CallContext:value1	Ljava/lang/Object;
    //   1187: aload_3
    //   1188: aload_1
    //   1189: putfield 840	gnu/mapping/CallContext:proc	Lgnu/mapping/Procedure;
    //   1192: aload_3
    //   1193: iconst_1
    //   1194: putfield 843	gnu/mapping/CallContext:pc	I
    //   1197: iconst_0
    //   1198: ireturn
    //   1199: aload_3
    //   1200: aload_2
    //   1201: putfield 836	gnu/mapping/CallContext:value1	Ljava/lang/Object;
    //   1204: aload_3
    //   1205: aload_1
    //   1206: putfield 840	gnu/mapping/CallContext:proc	Lgnu/mapping/Procedure;
    //   1209: aload_3
    //   1210: iconst_1
    //   1211: putfield 843	gnu/mapping/CallContext:pc	I
    //   1214: iconst_0
    //   1215: ireturn
    //   1216: aload_3
    //   1217: aload_2
    //   1218: ldc 24
    //   1220: invokestatic 59	gnu/mapping/Promise:force	(Ljava/lang/Object;Ljava/lang/Class;)Ljava/lang/Object;
    //   1223: dup
    //   1224: instanceof 24
    //   1227: ifeq +6 -> 1233
    //   1230: goto +7 -> 1237
    //   1233: ldc_w 832
    //   1236: ireturn
    //   1237: putfield 836	gnu/mapping/CallContext:value1	Ljava/lang/Object;
    //   1240: aload_3
    //   1241: aload_1
    //   1242: putfield 840	gnu/mapping/CallContext:proc	Lgnu/mapping/Procedure;
    //   1245: aload_3
    //   1246: iconst_1
    //   1247: putfield 843	gnu/mapping/CallContext:pc	I
    //   1250: iconst_0
    //   1251: ireturn
    //   1252: aload_3
    //   1253: aload_2
    //   1254: ldc 127
    //   1256: invokestatic 59	gnu/mapping/Promise:force	(Ljava/lang/Object;Ljava/lang/Class;)Ljava/lang/Object;
    //   1259: dup
    //   1260: instanceof 127
    //   1263: ifne +7 -> 1270
    //   1266: ldc_w 832
    //   1269: ireturn
    //   1270: putfield 836	gnu/mapping/CallContext:value1	Ljava/lang/Object;
    //   1273: aload_3
    //   1274: aload_1
    //   1275: putfield 840	gnu/mapping/CallContext:proc	Lgnu/mapping/Procedure;
    //   1278: aload_3
    //   1279: iconst_1
    //   1280: putfield 843	gnu/mapping/CallContext:pc	I
    //   1283: iconst_0
    //   1284: ireturn
    //   1285: aload_3
    //   1286: aload_2
    //   1287: ldc 127
    //   1289: invokestatic 59	gnu/mapping/Promise:force	(Ljava/lang/Object;Ljava/lang/Class;)Ljava/lang/Object;
    //   1292: dup
    //   1293: instanceof 127
    //   1296: ifne +7 -> 1303
    //   1299: ldc_w 832
    //   1302: ireturn
    //   1303: putfield 836	gnu/mapping/CallContext:value1	Ljava/lang/Object;
    //   1306: aload_3
    //   1307: aload_1
    //   1308: putfield 840	gnu/mapping/CallContext:proc	Lgnu/mapping/Procedure;
    //   1311: aload_3
    //   1312: iconst_1
    //   1313: putfield 843	gnu/mapping/CallContext:pc	I
    //   1316: iconst_0
    //   1317: ireturn
    //   1318: aload_3
    //   1319: aload_2
    //   1320: invokestatic 66	gnu/mapping/Promise:force	(Ljava/lang/Object;)Ljava/lang/Object;
    //   1323: putfield 836	gnu/mapping/CallContext:value1	Ljava/lang/Object;
    //   1326: aload_3
    //   1327: aload_1
    //   1328: putfield 840	gnu/mapping/CallContext:proc	Lgnu/mapping/Procedure;
    //   1331: aload_3
    //   1332: iconst_1
    //   1333: putfield 843	gnu/mapping/CallContext:pc	I
    //   1336: iconst_0
    //   1337: ireturn
    //   1338: aload_3
    //   1339: aload_2
    //   1340: putfield 836	gnu/mapping/CallContext:value1	Ljava/lang/Object;
    //   1343: aload_3
    //   1344: aload_1
    //   1345: putfield 840	gnu/mapping/CallContext:proc	Lgnu/mapping/Procedure;
    //   1348: aload_3
    //   1349: iconst_1
    //   1350: putfield 843	gnu/mapping/CallContext:pc	I
    //   1353: iconst_0
    //   1354: ireturn
    //   1355: aload_3
    //   1356: aload_2
    //   1357: ldc 24
    //   1359: invokestatic 59	gnu/mapping/Promise:force	(Ljava/lang/Object;Ljava/lang/Class;)Ljava/lang/Object;
    //   1362: dup
    //   1363: instanceof 24
    //   1366: ifeq +6 -> 1372
    //   1369: goto +7 -> 1376
    //   1372: ldc_w 832
    //   1375: ireturn
    //   1376: putfield 836	gnu/mapping/CallContext:value1	Ljava/lang/Object;
    //   1379: aload_3
    //   1380: aload_1
    //   1381: putfield 840	gnu/mapping/CallContext:proc	Lgnu/mapping/Procedure;
    //   1384: aload_3
    //   1385: iconst_1
    //   1386: putfield 843	gnu/mapping/CallContext:pc	I
    //   1389: iconst_0
    //   1390: ireturn
    //   1391: aload_3
    //   1392: aload_2
    //   1393: ldc 103
    //   1395: invokestatic 59	gnu/mapping/Promise:force	(Ljava/lang/Object;Ljava/lang/Class;)Ljava/lang/Object;
    //   1398: dup
    //   1399: instanceof 103
    //   1402: ifne +7 -> 1409
    //   1405: ldc_w 832
    //   1408: ireturn
    //   1409: putfield 836	gnu/mapping/CallContext:value1	Ljava/lang/Object;
    //   1412: aload_3
    //   1413: aload_1
    //   1414: putfield 840	gnu/mapping/CallContext:proc	Lgnu/mapping/Procedure;
    //   1417: aload_3
    //   1418: iconst_1
    //   1419: putfield 843	gnu/mapping/CallContext:pc	I
    //   1422: iconst_0
    //   1423: ireturn
    //   1424: aload_3
    //   1425: aload_2
    //   1426: ldc 103
    //   1428: invokestatic 59	gnu/mapping/Promise:force	(Ljava/lang/Object;Ljava/lang/Class;)Ljava/lang/Object;
    //   1431: dup
    //   1432: instanceof 103
    //   1435: ifne +7 -> 1442
    //   1438: ldc_w 832
    //   1441: ireturn
    //   1442: putfield 836	gnu/mapping/CallContext:value1	Ljava/lang/Object;
    //   1445: aload_3
    //   1446: aload_1
    //   1447: putfield 840	gnu/mapping/CallContext:proc	Lgnu/mapping/Procedure;
    //   1450: aload_3
    //   1451: iconst_1
    //   1452: putfield 843	gnu/mapping/CallContext:pc	I
    //   1455: iconst_0
    //   1456: ireturn
    //   1457: aload_3
    //   1458: aload_2
    //   1459: invokestatic 66	gnu/mapping/Promise:force	(Ljava/lang/Object;)Ljava/lang/Object;
    //   1462: putfield 836	gnu/mapping/CallContext:value1	Ljava/lang/Object;
    //   1465: aload_3
    //   1466: aload_1
    //   1467: putfield 840	gnu/mapping/CallContext:proc	Lgnu/mapping/Procedure;
    //   1470: aload_3
    //   1471: iconst_1
    //   1472: putfield 843	gnu/mapping/CallContext:pc	I
    //   1475: iconst_0
    //   1476: ireturn
    //   1477: aload_3
    //   1478: aload_2
    //   1479: putfield 836	gnu/mapping/CallContext:value1	Ljava/lang/Object;
    //   1482: aload_3
    //   1483: aload_1
    //   1484: putfield 840	gnu/mapping/CallContext:proc	Lgnu/mapping/Procedure;
    //   1487: aload_3
    //   1488: iconst_1
    //   1489: putfield 843	gnu/mapping/CallContext:pc	I
    //   1492: iconst_0
    //   1493: ireturn
    //   1494: aload_3
    //   1495: aload_2
    //   1496: ldc 24
    //   1498: invokestatic 59	gnu/mapping/Promise:force	(Ljava/lang/Object;Ljava/lang/Class;)Ljava/lang/Object;
    //   1501: dup
    //   1502: instanceof 24
    //   1505: ifeq +6 -> 1511
    //   1508: goto +7 -> 1515
    //   1511: ldc_w 832
    //   1514: ireturn
    //   1515: putfield 836	gnu/mapping/CallContext:value1	Ljava/lang/Object;
    //   1518: aload_3
    //   1519: aload_1
    //   1520: putfield 840	gnu/mapping/CallContext:proc	Lgnu/mapping/Procedure;
    //   1523: aload_3
    //   1524: iconst_1
    //   1525: putfield 843	gnu/mapping/CallContext:pc	I
    //   1528: iconst_0
    //   1529: ireturn
    //   1530: aload_3
    //   1531: aload_2
    //   1532: ldc 88
    //   1534: invokestatic 59	gnu/mapping/Promise:force	(Ljava/lang/Object;Ljava/lang/Class;)Ljava/lang/Object;
    //   1537: dup
    //   1538: instanceof 88
    //   1541: ifne +7 -> 1548
    //   1544: ldc_w 832
    //   1547: ireturn
    //   1548: putfield 836	gnu/mapping/CallContext:value1	Ljava/lang/Object;
    //   1551: aload_3
    //   1552: aload_1
    //   1553: putfield 840	gnu/mapping/CallContext:proc	Lgnu/mapping/Procedure;
    //   1556: aload_3
    //   1557: iconst_1
    //   1558: putfield 843	gnu/mapping/CallContext:pc	I
    //   1561: iconst_0
    //   1562: ireturn
    //   1563: aload_3
    //   1564: aload_2
    //   1565: ldc 88
    //   1567: invokestatic 59	gnu/mapping/Promise:force	(Ljava/lang/Object;Ljava/lang/Class;)Ljava/lang/Object;
    //   1570: dup
    //   1571: instanceof 88
    //   1574: ifne +7 -> 1581
    //   1577: ldc_w 832
    //   1580: ireturn
    //   1581: putfield 836	gnu/mapping/CallContext:value1	Ljava/lang/Object;
    //   1584: aload_3
    //   1585: aload_1
    //   1586: putfield 840	gnu/mapping/CallContext:proc	Lgnu/mapping/Procedure;
    //   1589: aload_3
    //   1590: iconst_1
    //   1591: putfield 843	gnu/mapping/CallContext:pc	I
    //   1594: iconst_0
    //   1595: ireturn
    //   1596: aload_3
    //   1597: aload_2
    //   1598: invokestatic 66	gnu/mapping/Promise:force	(Ljava/lang/Object;)Ljava/lang/Object;
    //   1601: putfield 836	gnu/mapping/CallContext:value1	Ljava/lang/Object;
    //   1604: aload_3
    //   1605: aload_1
    //   1606: putfield 840	gnu/mapping/CallContext:proc	Lgnu/mapping/Procedure;
    //   1609: aload_3
    //   1610: iconst_1
    //   1611: putfield 843	gnu/mapping/CallContext:pc	I
    //   1614: iconst_0
    //   1615: ireturn
    //   1616: aload_3
    //   1617: aload_2
    //   1618: putfield 836	gnu/mapping/CallContext:value1	Ljava/lang/Object;
    //   1621: aload_3
    //   1622: aload_1
    //   1623: putfield 840	gnu/mapping/CallContext:proc	Lgnu/mapping/Procedure;
    //   1626: aload_3
    //   1627: iconst_1
    //   1628: putfield 843	gnu/mapping/CallContext:pc	I
    //   1631: iconst_0
    //   1632: ireturn
    //   1633: aload_3
    //   1634: aload_2
    //   1635: ldc 24
    //   1637: invokestatic 59	gnu/mapping/Promise:force	(Ljava/lang/Object;Ljava/lang/Class;)Ljava/lang/Object;
    //   1640: dup
    //   1641: instanceof 24
    //   1644: ifeq +6 -> 1650
    //   1647: goto +7 -> 1654
    //   1650: ldc_w 832
    //   1653: ireturn
    //   1654: putfield 836	gnu/mapping/CallContext:value1	Ljava/lang/Object;
    //   1657: aload_3
    //   1658: aload_1
    //   1659: putfield 840	gnu/mapping/CallContext:proc	Lgnu/mapping/Procedure;
    //   1662: aload_3
    //   1663: iconst_1
    //   1664: putfield 843	gnu/mapping/CallContext:pc	I
    //   1667: iconst_0
    //   1668: ireturn
    //   1669: aload_3
    //   1670: aload_2
    //   1671: ldc 12
    //   1673: invokestatic 59	gnu/mapping/Promise:force	(Ljava/lang/Object;Ljava/lang/Class;)Ljava/lang/Object;
    //   1676: dup
    //   1677: instanceof 12
    //   1680: ifne +7 -> 1687
    //   1683: ldc_w 832
    //   1686: ireturn
    //   1687: putfield 836	gnu/mapping/CallContext:value1	Ljava/lang/Object;
    //   1690: aload_3
    //   1691: aload_1
    //   1692: putfield 840	gnu/mapping/CallContext:proc	Lgnu/mapping/Procedure;
    //   1695: aload_3
    //   1696: iconst_1
    //   1697: putfield 843	gnu/mapping/CallContext:pc	I
    //   1700: iconst_0
    //   1701: ireturn
    //   1702: aload_3
    //   1703: aload_2
    //   1704: ldc 12
    //   1706: invokestatic 59	gnu/mapping/Promise:force	(Ljava/lang/Object;Ljava/lang/Class;)Ljava/lang/Object;
    //   1709: dup
    //   1710: instanceof 12
    //   1713: ifne +7 -> 1720
    //   1716: ldc_w 832
    //   1719: ireturn
    //   1720: putfield 836	gnu/mapping/CallContext:value1	Ljava/lang/Object;
    //   1723: aload_3
    //   1724: aload_1
    //   1725: putfield 840	gnu/mapping/CallContext:proc	Lgnu/mapping/Procedure;
    //   1728: aload_3
    //   1729: iconst_1
    //   1730: putfield 843	gnu/mapping/CallContext:pc	I
    //   1733: iconst_0
    //   1734: ireturn
    //   1735: aload_3
    //   1736: aload_2
    //   1737: invokestatic 66	gnu/mapping/Promise:force	(Ljava/lang/Object;)Ljava/lang/Object;
    //   1740: putfield 836	gnu/mapping/CallContext:value1	Ljava/lang/Object;
    //   1743: aload_3
    //   1744: aload_1
    //   1745: putfield 840	gnu/mapping/CallContext:proc	Lgnu/mapping/Procedure;
    //   1748: aload_3
    //   1749: iconst_1
    //   1750: putfield 843	gnu/mapping/CallContext:pc	I
    //   1753: iconst_0
    //   1754: ireturn
    //   1755: aload_3
    //   1756: aload_2
    //   1757: putfield 836	gnu/mapping/CallContext:value1	Ljava/lang/Object;
    //   1760: aload_3
    //   1761: aload_1
    //   1762: putfield 840	gnu/mapping/CallContext:proc	Lgnu/mapping/Procedure;
    //   1765: aload_3
    //   1766: iconst_1
    //   1767: putfield 843	gnu/mapping/CallContext:pc	I
    //   1770: iconst_0
    //   1771: ireturn
    //   1772: aload_0
    //   1773: aload_1
    //   1774: aload_2
    //   1775: aload_3
    //   1776: invokespecial 847	gnu/expr/ModuleBody:match1	(Lgnu/expr/ModuleMethod;Ljava/lang/Object;Lgnu/mapping/CallContext;)I
    //   1779: ireturn
    // Line number table:
    //   Java source line #256	-> byte code offset #380
    //   Java source line #253	-> byte code offset #416
    //   Java source line #244	-> byte code offset #450
    //   Java source line #238	-> byte code offset #484
    //   Java source line #235	-> byte code offset #504
    //   Java source line #232	-> byte code offset #521
    //   Java source line #229	-> byte code offset #557
    //   Java source line #220	-> byte code offset #590
    //   Java source line #214	-> byte code offset #623
    //   Java source line #211	-> byte code offset #643
    //   Java source line #208	-> byte code offset #660
    //   Java source line #205	-> byte code offset #696
    //   Java source line #196	-> byte code offset #729
    //   Java source line #190	-> byte code offset #762
    //   Java source line #187	-> byte code offset #782
    //   Java source line #184	-> byte code offset #799
    //   Java source line #181	-> byte code offset #835
    //   Java source line #172	-> byte code offset #868
    //   Java source line #166	-> byte code offset #901
    //   Java source line #163	-> byte code offset #921
    //   Java source line #160	-> byte code offset #938
    //   Java source line #157	-> byte code offset #974
    //   Java source line #148	-> byte code offset #1007
    //   Java source line #142	-> byte code offset #1040
    //   Java source line #139	-> byte code offset #1060
    //   Java source line #136	-> byte code offset #1077
    //   Java source line #133	-> byte code offset #1113
    //   Java source line #124	-> byte code offset #1146
    //   Java source line #118	-> byte code offset #1179
    //   Java source line #115	-> byte code offset #1199
    //   Java source line #112	-> byte code offset #1216
    //   Java source line #109	-> byte code offset #1252
    //   Java source line #100	-> byte code offset #1285
    //   Java source line #94	-> byte code offset #1318
    //   Java source line #91	-> byte code offset #1338
    //   Java source line #88	-> byte code offset #1355
    //   Java source line #85	-> byte code offset #1391
    //   Java source line #76	-> byte code offset #1424
    //   Java source line #70	-> byte code offset #1457
    //   Java source line #67	-> byte code offset #1477
    //   Java source line #64	-> byte code offset #1494
    //   Java source line #61	-> byte code offset #1530
    //   Java source line #52	-> byte code offset #1563
    //   Java source line #46	-> byte code offset #1596
    //   Java source line #43	-> byte code offset #1616
    //   Java source line #40	-> byte code offset #1633
    //   Java source line #25	-> byte code offset #1669
    //   Java source line #16	-> byte code offset #1702
    //   Java source line #10	-> byte code offset #1735
    //   Java source line #7	-> byte code offset #1755
  }
  
  /* Error */
  public int match2(ModuleMethod arg1, Object arg2, Object arg3, gnu.mapping.CallContext arg4)
  {
    // Byte code:
    //   0: aload_1
    //   1: getfield 831	gnu/expr/ModuleMethod:selector	I
    //   4: lookupswitch	default:+960->964, 2:+928->932, 6:+883->887, 11:+851->855, 15:+806->810, 20:+774->778, 24:+729->733, 29:+697->701, 33:+652->656, 38:+620->624, 42:+575->579, 47:+543->547, 51:+498->502, 56:+466->470, 60:+421->425, 65:+372->376, 69:+327->331, 74:+295->299, 78:+250->254, 83:+218->222, 87:+172->176
    //   176: aload 4
    //   178: aload_2
    //   179: ldc_w 258
    //   182: invokestatic 59	gnu/mapping/Promise:force	(Ljava/lang/Object;Ljava/lang/Class;)Ljava/lang/Object;
    //   185: dup
    //   186: instanceof 258
    //   189: ifne +7 -> 196
    //   192: ldc_w 832
    //   195: ireturn
    //   196: putfield 836	gnu/mapping/CallContext:value1	Ljava/lang/Object;
    //   199: aload 4
    //   201: aload_3
    //   202: invokestatic 66	gnu/mapping/Promise:force	(Ljava/lang/Object;)Ljava/lang/Object;
    //   205: putfield 850	gnu/mapping/CallContext:value2	Ljava/lang/Object;
    //   208: aload 4
    //   210: aload_1
    //   211: putfield 840	gnu/mapping/CallContext:proc	Lgnu/mapping/Procedure;
    //   214: aload 4
    //   216: iconst_2
    //   217: putfield 843	gnu/mapping/CallContext:pc	I
    //   220: iconst_0
    //   221: ireturn
    //   222: aload 4
    //   224: aload_2
    //   225: invokestatic 66	gnu/mapping/Promise:force	(Ljava/lang/Object;)Ljava/lang/Object;
    //   228: putfield 836	gnu/mapping/CallContext:value1	Ljava/lang/Object;
    //   231: aload 4
    //   233: aload_3
    //   234: invokestatic 66	gnu/mapping/Promise:force	(Ljava/lang/Object;)Ljava/lang/Object;
    //   237: putfield 850	gnu/mapping/CallContext:value2	Ljava/lang/Object;
    //   240: aload 4
    //   242: aload_1
    //   243: putfield 840	gnu/mapping/CallContext:proc	Lgnu/mapping/Procedure;
    //   246: aload 4
    //   248: iconst_2
    //   249: putfield 843	gnu/mapping/CallContext:pc	I
    //   252: iconst_0
    //   253: ireturn
    //   254: aload 4
    //   256: aload_2
    //   257: ldc -26
    //   259: invokestatic 59	gnu/mapping/Promise:force	(Ljava/lang/Object;Ljava/lang/Class;)Ljava/lang/Object;
    //   262: dup
    //   263: instanceof 230
    //   266: ifne +7 -> 273
    //   269: ldc_w 832
    //   272: ireturn
    //   273: putfield 836	gnu/mapping/CallContext:value1	Ljava/lang/Object;
    //   276: aload 4
    //   278: aload_3
    //   279: invokestatic 66	gnu/mapping/Promise:force	(Ljava/lang/Object;)Ljava/lang/Object;
    //   282: putfield 850	gnu/mapping/CallContext:value2	Ljava/lang/Object;
    //   285: aload 4
    //   287: aload_1
    //   288: putfield 840	gnu/mapping/CallContext:proc	Lgnu/mapping/Procedure;
    //   291: aload 4
    //   293: iconst_2
    //   294: putfield 843	gnu/mapping/CallContext:pc	I
    //   297: iconst_0
    //   298: ireturn
    //   299: aload 4
    //   301: aload_2
    //   302: invokestatic 66	gnu/mapping/Promise:force	(Ljava/lang/Object;)Ljava/lang/Object;
    //   305: putfield 836	gnu/mapping/CallContext:value1	Ljava/lang/Object;
    //   308: aload 4
    //   310: aload_3
    //   311: invokestatic 66	gnu/mapping/Promise:force	(Ljava/lang/Object;)Ljava/lang/Object;
    //   314: putfield 850	gnu/mapping/CallContext:value2	Ljava/lang/Object;
    //   317: aload 4
    //   319: aload_1
    //   320: putfield 840	gnu/mapping/CallContext:proc	Lgnu/mapping/Procedure;
    //   323: aload 4
    //   325: iconst_2
    //   326: putfield 843	gnu/mapping/CallContext:pc	I
    //   329: iconst_0
    //   330: ireturn
    //   331: aload 4
    //   333: aload_2
    //   334: ldc -47
    //   336: invokestatic 59	gnu/mapping/Promise:force	(Ljava/lang/Object;Ljava/lang/Class;)Ljava/lang/Object;
    //   339: dup
    //   340: instanceof 209
    //   343: ifne +7 -> 350
    //   346: ldc_w 832
    //   349: ireturn
    //   350: putfield 836	gnu/mapping/CallContext:value1	Ljava/lang/Object;
    //   353: aload 4
    //   355: aload_3
    //   356: invokestatic 66	gnu/mapping/Promise:force	(Ljava/lang/Object;)Ljava/lang/Object;
    //   359: putfield 850	gnu/mapping/CallContext:value2	Ljava/lang/Object;
    //   362: aload 4
    //   364: aload_1
    //   365: putfield 840	gnu/mapping/CallContext:proc	Lgnu/mapping/Procedure;
    //   368: aload 4
    //   370: iconst_2
    //   371: putfield 843	gnu/mapping/CallContext:pc	I
    //   374: iconst_0
    //   375: ireturn
    //   376: aload 4
    //   378: aload_2
    //   379: invokestatic 66	gnu/mapping/Promise:force	(Ljava/lang/Object;)Ljava/lang/Object;
    //   382: putfield 836	gnu/mapping/CallContext:value1	Ljava/lang/Object;
    //   385: aload 4
    //   387: aload_3
    //   388: ldc_w 852
    //   391: invokestatic 59	gnu/mapping/Promise:force	(Ljava/lang/Object;Ljava/lang/Class;)Ljava/lang/Object;
    //   394: dup
    //   395: invokestatic 856	gnu/math/IntNum:asIntNumOrNull	(Ljava/lang/Object;)Lgnu/math/IntNum;
    //   398: ifnull +6 -> 404
    //   401: goto +7 -> 408
    //   404: ldc_w 857
    //   407: ireturn
    //   408: putfield 850	gnu/mapping/CallContext:value2	Ljava/lang/Object;
    //   411: aload 4
    //   413: aload_1
    //   414: putfield 840	gnu/mapping/CallContext:proc	Lgnu/mapping/Procedure;
    //   417: aload 4
    //   419: iconst_2
    //   420: putfield 843	gnu/mapping/CallContext:pc	I
    //   423: iconst_0
    //   424: ireturn
    //   425: aload 4
    //   427: aload_2
    //   428: ldc -75
    //   430: invokestatic 59	gnu/mapping/Promise:force	(Ljava/lang/Object;Ljava/lang/Class;)Ljava/lang/Object;
    //   433: dup
    //   434: instanceof 181
    //   437: ifne +7 -> 444
    //   440: ldc_w 832
    //   443: ireturn
    //   444: putfield 836	gnu/mapping/CallContext:value1	Ljava/lang/Object;
    //   447: aload 4
    //   449: aload_3
    //   450: invokestatic 66	gnu/mapping/Promise:force	(Ljava/lang/Object;)Ljava/lang/Object;
    //   453: putfield 850	gnu/mapping/CallContext:value2	Ljava/lang/Object;
    //   456: aload 4
    //   458: aload_1
    //   459: putfield 840	gnu/mapping/CallContext:proc	Lgnu/mapping/Procedure;
    //   462: aload 4
    //   464: iconst_2
    //   465: putfield 843	gnu/mapping/CallContext:pc	I
    //   468: iconst_0
    //   469: ireturn
    //   470: aload 4
    //   472: aload_2
    //   473: invokestatic 66	gnu/mapping/Promise:force	(Ljava/lang/Object;)Ljava/lang/Object;
    //   476: putfield 836	gnu/mapping/CallContext:value1	Ljava/lang/Object;
    //   479: aload 4
    //   481: aload_3
    //   482: invokestatic 66	gnu/mapping/Promise:force	(Ljava/lang/Object;)Ljava/lang/Object;
    //   485: putfield 850	gnu/mapping/CallContext:value2	Ljava/lang/Object;
    //   488: aload 4
    //   490: aload_1
    //   491: putfield 840	gnu/mapping/CallContext:proc	Lgnu/mapping/Procedure;
    //   494: aload 4
    //   496: iconst_2
    //   497: putfield 843	gnu/mapping/CallContext:pc	I
    //   500: iconst_0
    //   501: ireturn
    //   502: aload 4
    //   504: aload_2
    //   505: ldc -90
    //   507: invokestatic 59	gnu/mapping/Promise:force	(Ljava/lang/Object;Ljava/lang/Class;)Ljava/lang/Object;
    //   510: dup
    //   511: instanceof 166
    //   514: ifne +7 -> 521
    //   517: ldc_w 832
    //   520: ireturn
    //   521: putfield 836	gnu/mapping/CallContext:value1	Ljava/lang/Object;
    //   524: aload 4
    //   526: aload_3
    //   527: invokestatic 66	gnu/mapping/Promise:force	(Ljava/lang/Object;)Ljava/lang/Object;
    //   530: putfield 850	gnu/mapping/CallContext:value2	Ljava/lang/Object;
    //   533: aload 4
    //   535: aload_1
    //   536: putfield 840	gnu/mapping/CallContext:proc	Lgnu/mapping/Procedure;
    //   539: aload 4
    //   541: iconst_2
    //   542: putfield 843	gnu/mapping/CallContext:pc	I
    //   545: iconst_0
    //   546: ireturn
    //   547: aload 4
    //   549: aload_2
    //   550: invokestatic 66	gnu/mapping/Promise:force	(Ljava/lang/Object;)Ljava/lang/Object;
    //   553: putfield 836	gnu/mapping/CallContext:value1	Ljava/lang/Object;
    //   556: aload 4
    //   558: aload_3
    //   559: invokestatic 66	gnu/mapping/Promise:force	(Ljava/lang/Object;)Ljava/lang/Object;
    //   562: putfield 850	gnu/mapping/CallContext:value2	Ljava/lang/Object;
    //   565: aload 4
    //   567: aload_1
    //   568: putfield 840	gnu/mapping/CallContext:proc	Lgnu/mapping/Procedure;
    //   571: aload 4
    //   573: iconst_2
    //   574: putfield 843	gnu/mapping/CallContext:pc	I
    //   577: iconst_0
    //   578: ireturn
    //   579: aload 4
    //   581: aload_2
    //   582: ldc -114
    //   584: invokestatic 59	gnu/mapping/Promise:force	(Ljava/lang/Object;Ljava/lang/Class;)Ljava/lang/Object;
    //   587: dup
    //   588: instanceof 142
    //   591: ifne +7 -> 598
    //   594: ldc_w 832
    //   597: ireturn
    //   598: putfield 836	gnu/mapping/CallContext:value1	Ljava/lang/Object;
    //   601: aload 4
    //   603: aload_3
    //   604: invokestatic 66	gnu/mapping/Promise:force	(Ljava/lang/Object;)Ljava/lang/Object;
    //   607: putfield 850	gnu/mapping/CallContext:value2	Ljava/lang/Object;
    //   610: aload 4
    //   612: aload_1
    //   613: putfield 840	gnu/mapping/CallContext:proc	Lgnu/mapping/Procedure;
    //   616: aload 4
    //   618: iconst_2
    //   619: putfield 843	gnu/mapping/CallContext:pc	I
    //   622: iconst_0
    //   623: ireturn
    //   624: aload 4
    //   626: aload_2
    //   627: invokestatic 66	gnu/mapping/Promise:force	(Ljava/lang/Object;)Ljava/lang/Object;
    //   630: putfield 836	gnu/mapping/CallContext:value1	Ljava/lang/Object;
    //   633: aload 4
    //   635: aload_3
    //   636: invokestatic 66	gnu/mapping/Promise:force	(Ljava/lang/Object;)Ljava/lang/Object;
    //   639: putfield 850	gnu/mapping/CallContext:value2	Ljava/lang/Object;
    //   642: aload 4
    //   644: aload_1
    //   645: putfield 840	gnu/mapping/CallContext:proc	Lgnu/mapping/Procedure;
    //   648: aload 4
    //   650: iconst_2
    //   651: putfield 843	gnu/mapping/CallContext:pc	I
    //   654: iconst_0
    //   655: ireturn
    //   656: aload 4
    //   658: aload_2
    //   659: ldc 127
    //   661: invokestatic 59	gnu/mapping/Promise:force	(Ljava/lang/Object;Ljava/lang/Class;)Ljava/lang/Object;
    //   664: dup
    //   665: instanceof 127
    //   668: ifne +7 -> 675
    //   671: ldc_w 832
    //   674: ireturn
    //   675: putfield 836	gnu/mapping/CallContext:value1	Ljava/lang/Object;
    //   678: aload 4
    //   680: aload_3
    //   681: invokestatic 66	gnu/mapping/Promise:force	(Ljava/lang/Object;)Ljava/lang/Object;
    //   684: putfield 850	gnu/mapping/CallContext:value2	Ljava/lang/Object;
    //   687: aload 4
    //   689: aload_1
    //   690: putfield 840	gnu/mapping/CallContext:proc	Lgnu/mapping/Procedure;
    //   693: aload 4
    //   695: iconst_2
    //   696: putfield 843	gnu/mapping/CallContext:pc	I
    //   699: iconst_0
    //   700: ireturn
    //   701: aload 4
    //   703: aload_2
    //   704: invokestatic 66	gnu/mapping/Promise:force	(Ljava/lang/Object;)Ljava/lang/Object;
    //   707: putfield 836	gnu/mapping/CallContext:value1	Ljava/lang/Object;
    //   710: aload 4
    //   712: aload_3
    //   713: invokestatic 66	gnu/mapping/Promise:force	(Ljava/lang/Object;)Ljava/lang/Object;
    //   716: putfield 850	gnu/mapping/CallContext:value2	Ljava/lang/Object;
    //   719: aload 4
    //   721: aload_1
    //   722: putfield 840	gnu/mapping/CallContext:proc	Lgnu/mapping/Procedure;
    //   725: aload 4
    //   727: iconst_2
    //   728: putfield 843	gnu/mapping/CallContext:pc	I
    //   731: iconst_0
    //   732: ireturn
    //   733: aload 4
    //   735: aload_2
    //   736: ldc 103
    //   738: invokestatic 59	gnu/mapping/Promise:force	(Ljava/lang/Object;Ljava/lang/Class;)Ljava/lang/Object;
    //   741: dup
    //   742: instanceof 103
    //   745: ifne +7 -> 752
    //   748: ldc_w 832
    //   751: ireturn
    //   752: putfield 836	gnu/mapping/CallContext:value1	Ljava/lang/Object;
    //   755: aload 4
    //   757: aload_3
    //   758: invokestatic 66	gnu/mapping/Promise:force	(Ljava/lang/Object;)Ljava/lang/Object;
    //   761: putfield 850	gnu/mapping/CallContext:value2	Ljava/lang/Object;
    //   764: aload 4
    //   766: aload_1
    //   767: putfield 840	gnu/mapping/CallContext:proc	Lgnu/mapping/Procedure;
    //   770: aload 4
    //   772: iconst_2
    //   773: putfield 843	gnu/mapping/CallContext:pc	I
    //   776: iconst_0
    //   777: ireturn
    //   778: aload 4
    //   780: aload_2
    //   781: invokestatic 66	gnu/mapping/Promise:force	(Ljava/lang/Object;)Ljava/lang/Object;
    //   784: putfield 836	gnu/mapping/CallContext:value1	Ljava/lang/Object;
    //   787: aload 4
    //   789: aload_3
    //   790: invokestatic 66	gnu/mapping/Promise:force	(Ljava/lang/Object;)Ljava/lang/Object;
    //   793: putfield 850	gnu/mapping/CallContext:value2	Ljava/lang/Object;
    //   796: aload 4
    //   798: aload_1
    //   799: putfield 840	gnu/mapping/CallContext:proc	Lgnu/mapping/Procedure;
    //   802: aload 4
    //   804: iconst_2
    //   805: putfield 843	gnu/mapping/CallContext:pc	I
    //   808: iconst_0
    //   809: ireturn
    //   810: aload 4
    //   812: aload_2
    //   813: ldc 88
    //   815: invokestatic 59	gnu/mapping/Promise:force	(Ljava/lang/Object;Ljava/lang/Class;)Ljava/lang/Object;
    //   818: dup
    //   819: instanceof 88
    //   822: ifne +7 -> 829
    //   825: ldc_w 832
    //   828: ireturn
    //   829: putfield 836	gnu/mapping/CallContext:value1	Ljava/lang/Object;
    //   832: aload 4
    //   834: aload_3
    //   835: invokestatic 66	gnu/mapping/Promise:force	(Ljava/lang/Object;)Ljava/lang/Object;
    //   838: putfield 850	gnu/mapping/CallContext:value2	Ljava/lang/Object;
    //   841: aload 4
    //   843: aload_1
    //   844: putfield 840	gnu/mapping/CallContext:proc	Lgnu/mapping/Procedure;
    //   847: aload 4
    //   849: iconst_2
    //   850: putfield 843	gnu/mapping/CallContext:pc	I
    //   853: iconst_0
    //   854: ireturn
    //   855: aload 4
    //   857: aload_2
    //   858: invokestatic 66	gnu/mapping/Promise:force	(Ljava/lang/Object;)Ljava/lang/Object;
    //   861: putfield 836	gnu/mapping/CallContext:value1	Ljava/lang/Object;
    //   864: aload 4
    //   866: aload_3
    //   867: invokestatic 66	gnu/mapping/Promise:force	(Ljava/lang/Object;)Ljava/lang/Object;
    //   870: putfield 850	gnu/mapping/CallContext:value2	Ljava/lang/Object;
    //   873: aload 4
    //   875: aload_1
    //   876: putfield 840	gnu/mapping/CallContext:proc	Lgnu/mapping/Procedure;
    //   879: aload 4
    //   881: iconst_2
    //   882: putfield 843	gnu/mapping/CallContext:pc	I
    //   885: iconst_0
    //   886: ireturn
    //   887: aload 4
    //   889: aload_2
    //   890: ldc 12
    //   892: invokestatic 59	gnu/mapping/Promise:force	(Ljava/lang/Object;Ljava/lang/Class;)Ljava/lang/Object;
    //   895: dup
    //   896: instanceof 12
    //   899: ifne +7 -> 906
    //   902: ldc_w 832
    //   905: ireturn
    //   906: putfield 836	gnu/mapping/CallContext:value1	Ljava/lang/Object;
    //   909: aload 4
    //   911: aload_3
    //   912: invokestatic 66	gnu/mapping/Promise:force	(Ljava/lang/Object;)Ljava/lang/Object;
    //   915: putfield 850	gnu/mapping/CallContext:value2	Ljava/lang/Object;
    //   918: aload 4
    //   920: aload_1
    //   921: putfield 840	gnu/mapping/CallContext:proc	Lgnu/mapping/Procedure;
    //   924: aload 4
    //   926: iconst_2
    //   927: putfield 843	gnu/mapping/CallContext:pc	I
    //   930: iconst_0
    //   931: ireturn
    //   932: aload 4
    //   934: aload_2
    //   935: invokestatic 66	gnu/mapping/Promise:force	(Ljava/lang/Object;)Ljava/lang/Object;
    //   938: putfield 836	gnu/mapping/CallContext:value1	Ljava/lang/Object;
    //   941: aload 4
    //   943: aload_3
    //   944: invokestatic 66	gnu/mapping/Promise:force	(Ljava/lang/Object;)Ljava/lang/Object;
    //   947: putfield 850	gnu/mapping/CallContext:value2	Ljava/lang/Object;
    //   950: aload 4
    //   952: aload_1
    //   953: putfield 840	gnu/mapping/CallContext:proc	Lgnu/mapping/Procedure;
    //   956: aload 4
    //   958: iconst_2
    //   959: putfield 843	gnu/mapping/CallContext:pc	I
    //   962: iconst_0
    //   963: ireturn
    //   964: aload_0
    //   965: aload_1
    //   966: aload_2
    //   967: aload_3
    //   968: aload 4
    //   970: invokespecial 861	gnu/expr/ModuleBody:match2	(Lgnu/expr/ModuleMethod;Ljava/lang/Object;Ljava/lang/Object;Lgnu/mapping/CallContext;)I
    //   973: ireturn
    // Line number table:
    //   Java source line #247	-> byte code offset #176
    //   Java source line #238	-> byte code offset #222
    //   Java source line #223	-> byte code offset #254
    //   Java source line #214	-> byte code offset #299
    //   Java source line #199	-> byte code offset #331
    //   Java source line #190	-> byte code offset #376
    //   Java source line #175	-> byte code offset #425
    //   Java source line #166	-> byte code offset #470
    //   Java source line #151	-> byte code offset #502
    //   Java source line #142	-> byte code offset #547
    //   Java source line #127	-> byte code offset #579
    //   Java source line #118	-> byte code offset #624
    //   Java source line #103	-> byte code offset #656
    //   Java source line #94	-> byte code offset #701
    //   Java source line #79	-> byte code offset #733
    //   Java source line #70	-> byte code offset #778
    //   Java source line #55	-> byte code offset #810
    //   Java source line #46	-> byte code offset #855
    //   Java source line #19	-> byte code offset #887
    //   Java source line #10	-> byte code offset #932
  }
  
  /* Error */
  public int match3(ModuleMethod arg1, Object arg2, Object arg3, Object arg4, gnu.mapping.CallContext arg5)
  {
    // Byte code:
    //   0: aload_1
    //   1: getfield 831	gnu/expr/ModuleMethod:selector	I
    //   4: lookupswitch	default:+699->703, 7:+644->648, 16:+575->579, 25:+520->524, 34:+451->455, 43:+396->400, 52:+327->331, 61:+272->276, 70:+203->207, 79:+148->152, 88:+92->96
    //   96: aload 5
    //   98: aload_2
    //   99: ldc_w 258
    //   102: invokestatic 59	gnu/mapping/Promise:force	(Ljava/lang/Object;Ljava/lang/Class;)Ljava/lang/Object;
    //   105: dup
    //   106: instanceof 258
    //   109: ifne +7 -> 116
    //   112: ldc_w 832
    //   115: ireturn
    //   116: putfield 836	gnu/mapping/CallContext:value1	Ljava/lang/Object;
    //   119: aload 5
    //   121: aload_3
    //   122: invokestatic 66	gnu/mapping/Promise:force	(Ljava/lang/Object;)Ljava/lang/Object;
    //   125: putfield 850	gnu/mapping/CallContext:value2	Ljava/lang/Object;
    //   128: aload 5
    //   130: aload 4
    //   132: invokestatic 66	gnu/mapping/Promise:force	(Ljava/lang/Object;)Ljava/lang/Object;
    //   135: putfield 864	gnu/mapping/CallContext:value3	Ljava/lang/Object;
    //   138: aload 5
    //   140: aload_1
    //   141: putfield 840	gnu/mapping/CallContext:proc	Lgnu/mapping/Procedure;
    //   144: aload 5
    //   146: iconst_3
    //   147: putfield 843	gnu/mapping/CallContext:pc	I
    //   150: iconst_0
    //   151: ireturn
    //   152: aload 5
    //   154: aload_2
    //   155: ldc -26
    //   157: invokestatic 59	gnu/mapping/Promise:force	(Ljava/lang/Object;Ljava/lang/Class;)Ljava/lang/Object;
    //   160: dup
    //   161: instanceof 230
    //   164: ifne +7 -> 171
    //   167: ldc_w 832
    //   170: ireturn
    //   171: putfield 836	gnu/mapping/CallContext:value1	Ljava/lang/Object;
    //   174: aload 5
    //   176: aload_3
    //   177: invokestatic 66	gnu/mapping/Promise:force	(Ljava/lang/Object;)Ljava/lang/Object;
    //   180: putfield 850	gnu/mapping/CallContext:value2	Ljava/lang/Object;
    //   183: aload 5
    //   185: aload 4
    //   187: invokestatic 66	gnu/mapping/Promise:force	(Ljava/lang/Object;)Ljava/lang/Object;
    //   190: putfield 864	gnu/mapping/CallContext:value3	Ljava/lang/Object;
    //   193: aload 5
    //   195: aload_1
    //   196: putfield 840	gnu/mapping/CallContext:proc	Lgnu/mapping/Procedure;
    //   199: aload 5
    //   201: iconst_3
    //   202: putfield 843	gnu/mapping/CallContext:pc	I
    //   205: iconst_0
    //   206: ireturn
    //   207: aload 5
    //   209: aload_2
    //   210: ldc -47
    //   212: invokestatic 59	gnu/mapping/Promise:force	(Ljava/lang/Object;Ljava/lang/Class;)Ljava/lang/Object;
    //   215: dup
    //   216: instanceof 209
    //   219: ifne +7 -> 226
    //   222: ldc_w 832
    //   225: ireturn
    //   226: putfield 836	gnu/mapping/CallContext:value1	Ljava/lang/Object;
    //   229: aload 5
    //   231: aload_3
    //   232: invokestatic 66	gnu/mapping/Promise:force	(Ljava/lang/Object;)Ljava/lang/Object;
    //   235: putfield 850	gnu/mapping/CallContext:value2	Ljava/lang/Object;
    //   238: aload 5
    //   240: aload 4
    //   242: invokestatic 66	gnu/mapping/Promise:force	(Ljava/lang/Object;)Ljava/lang/Object;
    //   245: dup
    //   246: instanceof 68
    //   249: ifeq +6 -> 255
    //   252: goto +7 -> 259
    //   255: ldc_w 865
    //   258: ireturn
    //   259: putfield 864	gnu/mapping/CallContext:value3	Ljava/lang/Object;
    //   262: aload 5
    //   264: aload_1
    //   265: putfield 840	gnu/mapping/CallContext:proc	Lgnu/mapping/Procedure;
    //   268: aload 5
    //   270: iconst_3
    //   271: putfield 843	gnu/mapping/CallContext:pc	I
    //   274: iconst_0
    //   275: ireturn
    //   276: aload 5
    //   278: aload_2
    //   279: ldc -75
    //   281: invokestatic 59	gnu/mapping/Promise:force	(Ljava/lang/Object;Ljava/lang/Class;)Ljava/lang/Object;
    //   284: dup
    //   285: instanceof 181
    //   288: ifne +7 -> 295
    //   291: ldc_w 832
    //   294: ireturn
    //   295: putfield 836	gnu/mapping/CallContext:value1	Ljava/lang/Object;
    //   298: aload 5
    //   300: aload_3
    //   301: invokestatic 66	gnu/mapping/Promise:force	(Ljava/lang/Object;)Ljava/lang/Object;
    //   304: putfield 850	gnu/mapping/CallContext:value2	Ljava/lang/Object;
    //   307: aload 5
    //   309: aload 4
    //   311: invokestatic 66	gnu/mapping/Promise:force	(Ljava/lang/Object;)Ljava/lang/Object;
    //   314: putfield 864	gnu/mapping/CallContext:value3	Ljava/lang/Object;
    //   317: aload 5
    //   319: aload_1
    //   320: putfield 840	gnu/mapping/CallContext:proc	Lgnu/mapping/Procedure;
    //   323: aload 5
    //   325: iconst_3
    //   326: putfield 843	gnu/mapping/CallContext:pc	I
    //   329: iconst_0
    //   330: ireturn
    //   331: aload 5
    //   333: aload_2
    //   334: ldc -90
    //   336: invokestatic 59	gnu/mapping/Promise:force	(Ljava/lang/Object;Ljava/lang/Class;)Ljava/lang/Object;
    //   339: dup
    //   340: instanceof 166
    //   343: ifne +7 -> 350
    //   346: ldc_w 832
    //   349: ireturn
    //   350: putfield 836	gnu/mapping/CallContext:value1	Ljava/lang/Object;
    //   353: aload 5
    //   355: aload_3
    //   356: invokestatic 66	gnu/mapping/Promise:force	(Ljava/lang/Object;)Ljava/lang/Object;
    //   359: putfield 850	gnu/mapping/CallContext:value2	Ljava/lang/Object;
    //   362: aload 5
    //   364: aload 4
    //   366: invokestatic 66	gnu/mapping/Promise:force	(Ljava/lang/Object;)Ljava/lang/Object;
    //   369: dup
    //   370: instanceof 68
    //   373: ifeq +6 -> 379
    //   376: goto +7 -> 383
    //   379: ldc_w 865
    //   382: ireturn
    //   383: putfield 864	gnu/mapping/CallContext:value3	Ljava/lang/Object;
    //   386: aload 5
    //   388: aload_1
    //   389: putfield 840	gnu/mapping/CallContext:proc	Lgnu/mapping/Procedure;
    //   392: aload 5
    //   394: iconst_3
    //   395: putfield 843	gnu/mapping/CallContext:pc	I
    //   398: iconst_0
    //   399: ireturn
    //   400: aload 5
    //   402: aload_2
    //   403: ldc -114
    //   405: invokestatic 59	gnu/mapping/Promise:force	(Ljava/lang/Object;Ljava/lang/Class;)Ljava/lang/Object;
    //   408: dup
    //   409: instanceof 142
    //   412: ifne +7 -> 419
    //   415: ldc_w 832
    //   418: ireturn
    //   419: putfield 836	gnu/mapping/CallContext:value1	Ljava/lang/Object;
    //   422: aload 5
    //   424: aload_3
    //   425: invokestatic 66	gnu/mapping/Promise:force	(Ljava/lang/Object;)Ljava/lang/Object;
    //   428: putfield 850	gnu/mapping/CallContext:value2	Ljava/lang/Object;
    //   431: aload 5
    //   433: aload 4
    //   435: invokestatic 66	gnu/mapping/Promise:force	(Ljava/lang/Object;)Ljava/lang/Object;
    //   438: putfield 864	gnu/mapping/CallContext:value3	Ljava/lang/Object;
    //   441: aload 5
    //   443: aload_1
    //   444: putfield 840	gnu/mapping/CallContext:proc	Lgnu/mapping/Procedure;
    //   447: aload 5
    //   449: iconst_3
    //   450: putfield 843	gnu/mapping/CallContext:pc	I
    //   453: iconst_0
    //   454: ireturn
    //   455: aload 5
    //   457: aload_2
    //   458: ldc 127
    //   460: invokestatic 59	gnu/mapping/Promise:force	(Ljava/lang/Object;Ljava/lang/Class;)Ljava/lang/Object;
    //   463: dup
    //   464: instanceof 127
    //   467: ifne +7 -> 474
    //   470: ldc_w 832
    //   473: ireturn
    //   474: putfield 836	gnu/mapping/CallContext:value1	Ljava/lang/Object;
    //   477: aload 5
    //   479: aload_3
    //   480: invokestatic 66	gnu/mapping/Promise:force	(Ljava/lang/Object;)Ljava/lang/Object;
    //   483: putfield 850	gnu/mapping/CallContext:value2	Ljava/lang/Object;
    //   486: aload 5
    //   488: aload 4
    //   490: invokestatic 66	gnu/mapping/Promise:force	(Ljava/lang/Object;)Ljava/lang/Object;
    //   493: dup
    //   494: instanceof 68
    //   497: ifeq +6 -> 503
    //   500: goto +7 -> 507
    //   503: ldc_w 865
    //   506: ireturn
    //   507: putfield 864	gnu/mapping/CallContext:value3	Ljava/lang/Object;
    //   510: aload 5
    //   512: aload_1
    //   513: putfield 840	gnu/mapping/CallContext:proc	Lgnu/mapping/Procedure;
    //   516: aload 5
    //   518: iconst_3
    //   519: putfield 843	gnu/mapping/CallContext:pc	I
    //   522: iconst_0
    //   523: ireturn
    //   524: aload 5
    //   526: aload_2
    //   527: ldc 103
    //   529: invokestatic 59	gnu/mapping/Promise:force	(Ljava/lang/Object;Ljava/lang/Class;)Ljava/lang/Object;
    //   532: dup
    //   533: instanceof 103
    //   536: ifne +7 -> 543
    //   539: ldc_w 832
    //   542: ireturn
    //   543: putfield 836	gnu/mapping/CallContext:value1	Ljava/lang/Object;
    //   546: aload 5
    //   548: aload_3
    //   549: invokestatic 66	gnu/mapping/Promise:force	(Ljava/lang/Object;)Ljava/lang/Object;
    //   552: putfield 850	gnu/mapping/CallContext:value2	Ljava/lang/Object;
    //   555: aload 5
    //   557: aload 4
    //   559: invokestatic 66	gnu/mapping/Promise:force	(Ljava/lang/Object;)Ljava/lang/Object;
    //   562: putfield 864	gnu/mapping/CallContext:value3	Ljava/lang/Object;
    //   565: aload 5
    //   567: aload_1
    //   568: putfield 840	gnu/mapping/CallContext:proc	Lgnu/mapping/Procedure;
    //   571: aload 5
    //   573: iconst_3
    //   574: putfield 843	gnu/mapping/CallContext:pc	I
    //   577: iconst_0
    //   578: ireturn
    //   579: aload 5
    //   581: aload_2
    //   582: ldc 88
    //   584: invokestatic 59	gnu/mapping/Promise:force	(Ljava/lang/Object;Ljava/lang/Class;)Ljava/lang/Object;
    //   587: dup
    //   588: instanceof 88
    //   591: ifne +7 -> 598
    //   594: ldc_w 832
    //   597: ireturn
    //   598: putfield 836	gnu/mapping/CallContext:value1	Ljava/lang/Object;
    //   601: aload 5
    //   603: aload_3
    //   604: invokestatic 66	gnu/mapping/Promise:force	(Ljava/lang/Object;)Ljava/lang/Object;
    //   607: putfield 850	gnu/mapping/CallContext:value2	Ljava/lang/Object;
    //   610: aload 5
    //   612: aload 4
    //   614: invokestatic 66	gnu/mapping/Promise:force	(Ljava/lang/Object;)Ljava/lang/Object;
    //   617: dup
    //   618: instanceof 68
    //   621: ifeq +6 -> 627
    //   624: goto +7 -> 631
    //   627: ldc_w 865
    //   630: ireturn
    //   631: putfield 864	gnu/mapping/CallContext:value3	Ljava/lang/Object;
    //   634: aload 5
    //   636: aload_1
    //   637: putfield 840	gnu/mapping/CallContext:proc	Lgnu/mapping/Procedure;
    //   640: aload 5
    //   642: iconst_3
    //   643: putfield 843	gnu/mapping/CallContext:pc	I
    //   646: iconst_0
    //   647: ireturn
    //   648: aload 5
    //   650: aload_2
    //   651: ldc 12
    //   653: invokestatic 59	gnu/mapping/Promise:force	(Ljava/lang/Object;Ljava/lang/Class;)Ljava/lang/Object;
    //   656: dup
    //   657: instanceof 12
    //   660: ifne +7 -> 667
    //   663: ldc_w 832
    //   666: ireturn
    //   667: putfield 836	gnu/mapping/CallContext:value1	Ljava/lang/Object;
    //   670: aload 5
    //   672: aload_3
    //   673: invokestatic 66	gnu/mapping/Promise:force	(Ljava/lang/Object;)Ljava/lang/Object;
    //   676: putfield 850	gnu/mapping/CallContext:value2	Ljava/lang/Object;
    //   679: aload 5
    //   681: aload 4
    //   683: invokestatic 66	gnu/mapping/Promise:force	(Ljava/lang/Object;)Ljava/lang/Object;
    //   686: putfield 864	gnu/mapping/CallContext:value3	Ljava/lang/Object;
    //   689: aload 5
    //   691: aload_1
    //   692: putfield 840	gnu/mapping/CallContext:proc	Lgnu/mapping/Procedure;
    //   695: aload 5
    //   697: iconst_3
    //   698: putfield 843	gnu/mapping/CallContext:pc	I
    //   701: iconst_0
    //   702: ireturn
    //   703: aload_0
    //   704: aload_1
    //   705: aload_2
    //   706: aload_3
    //   707: aload 4
    //   709: aload 5
    //   711: invokespecial 869	gnu/expr/ModuleBody:match3	(Lgnu/expr/ModuleMethod;Ljava/lang/Object;Ljava/lang/Object;Ljava/lang/Object;Lgnu/mapping/CallContext;)I
    //   714: ireturn
    // Line number table:
    //   Java source line #250	-> byte code offset #96
    //   Java source line #226	-> byte code offset #152
    //   Java source line #202	-> byte code offset #207
    //   Java source line #178	-> byte code offset #276
    //   Java source line #154	-> byte code offset #331
    //   Java source line #130	-> byte code offset #400
    //   Java source line #106	-> byte code offset #455
    //   Java source line #82	-> byte code offset #524
    //   Java source line #58	-> byte code offset #579
    //   Java source line #22	-> byte code offset #648
  }
  
  public void apply(gnu.mapping.CallContext paramCallContext)
  {
    ModuleMethod.applyError();
  }
  
  /* Error */
  public Object apply2(ModuleMethod paramModuleMethod, Object paramObject1, Object paramObject2)
  {
    // Byte code:
    //   0: aload_1
    //   1: getfield 831	gnu/expr/ModuleMethod:selector	I
    //   4: lookupswitch	default:+673->677, 2:+172->176, 6:+196->200, 11:+222->226, 15:+246->250, 20:+272->276, 24:+296->300, 29:+322->326, 33:+346->350, 38:+372->376, 42:+396->400, 47:+422->426, 51:+446->450, 56:+472->476, 60:+496->500, 65:+522->526, 69:+546->550, 74:+572->576, 78:+596->600, 83:+622->626, 87:+646->650
    //   176: aload_2
    //   177: invokestatic 66	gnu/mapping/Promise:force	(Ljava/lang/Object;)Ljava/lang/Object;
    //   180: checkcast 68	java/lang/Number
    //   183: invokevirtual 71	java/lang/Number:intValue	()I
    //   186: aload_3
    //   187: invokestatic 66	gnu/mapping/Promise:force	(Ljava/lang/Object;)Ljava/lang/Object;
    //   190: checkcast 68	java/lang/Number
    //   193: invokevirtual 71	java/lang/Number:intValue	()I
    //   196: invokestatic 18	kawa/lib/uniform:makeS8vector	(II)Lgnu/lists/S8Vector;
    //   199: areturn
    //   200: aload_2
    //   201: ldc 12
    //   203: invokestatic 59	gnu/mapping/Promise:force	(Ljava/lang/Object;Ljava/lang/Class;)Ljava/lang/Object;
    //   206: checkcast 12	gnu/lists/S8Vector
    //   209: aload_3
    //   210: invokestatic 66	gnu/mapping/Promise:force	(Ljava/lang/Object;)Ljava/lang/Object;
    //   213: checkcast 68	java/lang/Number
    //   216: invokevirtual 71	java/lang/Number:intValue	()I
    //   219: invokestatic 1126	kawa/lib/uniform:s8vectorRef	(Lgnu/lists/S8Vector;I)B
    //   222: invokestatic 1131	java/lang/Byte:valueOf	(B)Ljava/lang/Byte;
    //   225: areturn
    //   226: aload_2
    //   227: invokestatic 66	gnu/mapping/Promise:force	(Ljava/lang/Object;)Ljava/lang/Object;
    //   230: checkcast 68	java/lang/Number
    //   233: invokevirtual 71	java/lang/Number:intValue	()I
    //   236: aload_3
    //   237: invokestatic 66	gnu/mapping/Promise:force	(Ljava/lang/Object;)Ljava/lang/Object;
    //   240: checkcast 68	java/lang/Number
    //   243: invokevirtual 71	java/lang/Number:intValue	()I
    //   246: invokestatic 92	kawa/lib/uniform:makeU8vector	(II)Lgnu/lists/U8Vector;
    //   249: areturn
    //   250: aload_2
    //   251: ldc 88
    //   253: invokestatic 59	gnu/mapping/Promise:force	(Ljava/lang/Object;Ljava/lang/Class;)Ljava/lang/Object;
    //   256: checkcast 88	gnu/lists/U8Vector
    //   259: aload_3
    //   260: invokestatic 66	gnu/mapping/Promise:force	(Ljava/lang/Object;)Ljava/lang/Object;
    //   263: checkcast 68	java/lang/Number
    //   266: invokevirtual 71	java/lang/Number:intValue	()I
    //   269: invokestatic 1137	kawa/lib/uniform:u8vectorRef	(Lgnu/lists/U8Vector;I)I
    //   272: invokestatic 1142	gnu/math/UByte:valueOf	(B)Lgnu/math/UByte;
    //   275: areturn
    //   276: aload_2
    //   277: invokestatic 66	gnu/mapping/Promise:force	(Ljava/lang/Object;)Ljava/lang/Object;
    //   280: checkcast 68	java/lang/Number
    //   283: invokevirtual 71	java/lang/Number:intValue	()I
    //   286: aload_3
    //   287: invokestatic 66	gnu/mapping/Promise:force	(Ljava/lang/Object;)Ljava/lang/Object;
    //   290: checkcast 68	java/lang/Number
    //   293: invokevirtual 71	java/lang/Number:intValue	()I
    //   296: invokestatic 107	kawa/lib/uniform:makeS16vector	(II)Lgnu/lists/S16Vector;
    //   299: areturn
    //   300: aload_2
    //   301: ldc 103
    //   303: invokestatic 59	gnu/mapping/Promise:force	(Ljava/lang/Object;Ljava/lang/Class;)Ljava/lang/Object;
    //   306: checkcast 103	gnu/lists/S16Vector
    //   309: aload_3
    //   310: invokestatic 66	gnu/mapping/Promise:force	(Ljava/lang/Object;)Ljava/lang/Object;
    //   313: checkcast 68	java/lang/Number
    //   316: invokevirtual 71	java/lang/Number:intValue	()I
    //   319: invokestatic 1148	kawa/lib/uniform:s16vectorRef	(Lgnu/lists/S16Vector;I)S
    //   322: invokestatic 1153	java/lang/Short:valueOf	(S)Ljava/lang/Short;
    //   325: areturn
    //   326: aload_2
    //   327: invokestatic 66	gnu/mapping/Promise:force	(Ljava/lang/Object;)Ljava/lang/Object;
    //   330: checkcast 68	java/lang/Number
    //   333: invokevirtual 71	java/lang/Number:intValue	()I
    //   336: aload_3
    //   337: invokestatic 66	gnu/mapping/Promise:force	(Ljava/lang/Object;)Ljava/lang/Object;
    //   340: checkcast 68	java/lang/Number
    //   343: invokevirtual 71	java/lang/Number:intValue	()I
    //   346: invokestatic 131	kawa/lib/uniform:makeU16vector	(II)Lgnu/lists/U16Vector;
    //   349: areturn
    //   350: aload_2
    //   351: ldc 127
    //   353: invokestatic 59	gnu/mapping/Promise:force	(Ljava/lang/Object;Ljava/lang/Class;)Ljava/lang/Object;
    //   356: checkcast 127	gnu/lists/U16Vector
    //   359: aload_3
    //   360: invokestatic 66	gnu/mapping/Promise:force	(Ljava/lang/Object;)Ljava/lang/Object;
    //   363: checkcast 68	java/lang/Number
    //   366: invokevirtual 71	java/lang/Number:intValue	()I
    //   369: invokestatic 1159	kawa/lib/uniform:u16vectorRef	(Lgnu/lists/U16Vector;I)I
    //   372: invokestatic 1164	gnu/math/UShort:valueOf	(S)Lgnu/math/UShort;
    //   375: areturn
    //   376: aload_2
    //   377: invokestatic 66	gnu/mapping/Promise:force	(Ljava/lang/Object;)Ljava/lang/Object;
    //   380: checkcast 68	java/lang/Number
    //   383: invokevirtual 71	java/lang/Number:intValue	()I
    //   386: aload_3
    //   387: invokestatic 66	gnu/mapping/Promise:force	(Ljava/lang/Object;)Ljava/lang/Object;
    //   390: checkcast 68	java/lang/Number
    //   393: invokevirtual 71	java/lang/Number:intValue	()I
    //   396: invokestatic 146	kawa/lib/uniform:makeS32vector	(II)Lgnu/lists/S32Vector;
    //   399: areturn
    //   400: aload_2
    //   401: ldc -114
    //   403: invokestatic 59	gnu/mapping/Promise:force	(Ljava/lang/Object;Ljava/lang/Class;)Ljava/lang/Object;
    //   406: checkcast 142	gnu/lists/S32Vector
    //   409: aload_3
    //   410: invokestatic 66	gnu/mapping/Promise:force	(Ljava/lang/Object;)Ljava/lang/Object;
    //   413: checkcast 68	java/lang/Number
    //   416: invokevirtual 71	java/lang/Number:intValue	()I
    //   419: invokestatic 1170	kawa/lib/uniform:s32vectorRef	(Lgnu/lists/S32Vector;I)I
    //   422: invokestatic 910	java/lang/Integer:valueOf	(I)Ljava/lang/Integer;
    //   425: areturn
    //   426: aload_2
    //   427: invokestatic 66	gnu/mapping/Promise:force	(Ljava/lang/Object;)Ljava/lang/Object;
    //   430: checkcast 68	java/lang/Number
    //   433: invokevirtual 71	java/lang/Number:intValue	()I
    //   436: aload_3
    //   437: invokestatic 66	gnu/mapping/Promise:force	(Ljava/lang/Object;)Ljava/lang/Object;
    //   440: checkcast 68	java/lang/Number
    //   443: invokevirtual 204	java/lang/Number:longValue	()J
    //   446: invokestatic 170	kawa/lib/uniform:makeU32vector	(IJ)Lgnu/lists/U32Vector;
    //   449: areturn
    //   450: aload_2
    //   451: ldc -90
    //   453: invokestatic 59	gnu/mapping/Promise:force	(Ljava/lang/Object;Ljava/lang/Class;)Ljava/lang/Object;
    //   456: checkcast 166	gnu/lists/U32Vector
    //   459: aload_3
    //   460: invokestatic 66	gnu/mapping/Promise:force	(Ljava/lang/Object;)Ljava/lang/Object;
    //   463: checkcast 68	java/lang/Number
    //   466: invokevirtual 71	java/lang/Number:intValue	()I
    //   469: invokestatic 1176	kawa/lib/uniform:u32vectorRef	(Lgnu/lists/U32Vector;I)I
    //   472: invokestatic 1181	gnu/math/UInt:valueOf	(I)Lgnu/math/UInt;
    //   475: areturn
    //   476: aload_2
    //   477: invokestatic 66	gnu/mapping/Promise:force	(Ljava/lang/Object;)Ljava/lang/Object;
    //   480: checkcast 68	java/lang/Number
    //   483: invokevirtual 71	java/lang/Number:intValue	()I
    //   486: aload_3
    //   487: invokestatic 66	gnu/mapping/Promise:force	(Ljava/lang/Object;)Ljava/lang/Object;
    //   490: checkcast 68	java/lang/Number
    //   493: invokevirtual 204	java/lang/Number:longValue	()J
    //   496: invokestatic 185	kawa/lib/uniform:makeS64vector	(IJ)Lgnu/lists/S64Vector;
    //   499: areturn
    //   500: aload_2
    //   501: ldc -75
    //   503: invokestatic 59	gnu/mapping/Promise:force	(Ljava/lang/Object;Ljava/lang/Class;)Ljava/lang/Object;
    //   506: checkcast 181	gnu/lists/S64Vector
    //   509: aload_3
    //   510: invokestatic 66	gnu/mapping/Promise:force	(Ljava/lang/Object;)Ljava/lang/Object;
    //   513: checkcast 68	java/lang/Number
    //   516: invokevirtual 71	java/lang/Number:intValue	()I
    //   519: invokestatic 1187	kawa/lib/uniform:s64vectorRef	(Lgnu/lists/S64Vector;I)J
    //   522: invokestatic 1192	java/lang/Long:valueOf	(J)Ljava/lang/Long;
    //   525: areturn
    //   526: aload_2
    //   527: invokestatic 66	gnu/mapping/Promise:force	(Ljava/lang/Object;)Ljava/lang/Object;
    //   530: checkcast 68	java/lang/Number
    //   533: invokevirtual 71	java/lang/Number:intValue	()I
    //   536: aload_3
    //   537: ldc_w 852
    //   540: invokestatic 59	gnu/mapping/Promise:force	(Ljava/lang/Object;Ljava/lang/Class;)Ljava/lang/Object;
    //   543: invokestatic 1197	gnu/kawa/lispexpr/LangObjType:coerceIntNum	(Ljava/lang/Object;)Lgnu/math/IntNum;
    //   546: invokestatic 217	kawa/lib/uniform:makeU64vector	(ILgnu/math/IntNum;)Lgnu/lists/U64Vector;
    //   549: areturn
    //   550: aload_2
    //   551: ldc -47
    //   553: invokestatic 59	gnu/mapping/Promise:force	(Ljava/lang/Object;Ljava/lang/Class;)Ljava/lang/Object;
    //   556: checkcast 209	gnu/lists/U64Vector
    //   559: aload_3
    //   560: invokestatic 66	gnu/mapping/Promise:force	(Ljava/lang/Object;)Ljava/lang/Object;
    //   563: checkcast 68	java/lang/Number
    //   566: invokevirtual 71	java/lang/Number:intValue	()I
    //   569: invokestatic 1203	kawa/lib/uniform:u64vectorRef	(Lgnu/lists/U64Vector;I)J
    //   572: invokestatic 1208	gnu/math/ULong:valueOf	(J)Lgnu/math/ULong;
    //   575: areturn
    //   576: aload_2
    //   577: invokestatic 66	gnu/mapping/Promise:force	(Ljava/lang/Object;)Ljava/lang/Object;
    //   580: checkcast 68	java/lang/Number
    //   583: invokevirtual 71	java/lang/Number:intValue	()I
    //   586: aload_3
    //   587: invokestatic 66	gnu/mapping/Promise:force	(Ljava/lang/Object;)Ljava/lang/Object;
    //   590: checkcast 68	java/lang/Number
    //   593: invokevirtual 253	java/lang/Number:floatValue	()F
    //   596: invokestatic 234	kawa/lib/uniform:makeF32vector	(IF)Lgnu/lists/F32Vector;
    //   599: areturn
    //   600: aload_2
    //   601: ldc -26
    //   603: invokestatic 59	gnu/mapping/Promise:force	(Ljava/lang/Object;Ljava/lang/Class;)Ljava/lang/Object;
    //   606: checkcast 230	gnu/lists/F32Vector
    //   609: aload_3
    //   610: invokestatic 66	gnu/mapping/Promise:force	(Ljava/lang/Object;)Ljava/lang/Object;
    //   613: checkcast 68	java/lang/Number
    //   616: invokevirtual 71	java/lang/Number:intValue	()I
    //   619: invokestatic 1214	kawa/lib/uniform:f32vectorRef	(Lgnu/lists/F32Vector;I)F
    //   622: invokestatic 1219	java/lang/Float:valueOf	(F)Ljava/lang/Float;
    //   625: areturn
    //   626: aload_2
    //   627: invokestatic 66	gnu/mapping/Promise:force	(Ljava/lang/Object;)Ljava/lang/Object;
    //   630: checkcast 68	java/lang/Number
    //   633: invokevirtual 71	java/lang/Number:intValue	()I
    //   636: aload_3
    //   637: invokestatic 66	gnu/mapping/Promise:force	(Ljava/lang/Object;)Ljava/lang/Object;
    //   640: checkcast 68	java/lang/Number
    //   643: invokevirtual 281	java/lang/Number:doubleValue	()D
    //   646: invokestatic 262	kawa/lib/uniform:makeF64vector	(ID)Lgnu/lists/F64Vector;
    //   649: areturn
    //   650: aload_2
    //   651: ldc_w 258
    //   654: invokestatic 59	gnu/mapping/Promise:force	(Ljava/lang/Object;Ljava/lang/Class;)Ljava/lang/Object;
    //   657: checkcast 258	gnu/lists/F64Vector
    //   660: aload_3
    //   661: invokestatic 66	gnu/mapping/Promise:force	(Ljava/lang/Object;)Ljava/lang/Object;
    //   664: checkcast 68	java/lang/Number
    //   667: invokevirtual 71	java/lang/Number:intValue	()I
    //   670: invokestatic 1225	kawa/lib/uniform:f64vectorRef	(Lgnu/lists/F64Vector;I)D
    //   673: invokestatic 1230	java/lang/Double:valueOf	(D)Ljava/lang/Double;
    //   676: areturn
    //   677: aload_0
    //   678: aload_1
    //   679: aload_2
    //   680: aload_3
    //   681: invokespecial 1234	gnu/expr/ModuleBody:apply2	(Lgnu/expr/ModuleMethod;Ljava/lang/Object;Ljava/lang/Object;)Ljava/lang/Object;
    //   684: areturn
    //   685: new 75	gnu/mapping/WrongType
    //   688: dup_x1
    //   689: swap
    //   690: ldc_w 895
    //   693: iconst_1
    //   694: aload_2
    //   695: invokespecial 80	gnu/mapping/WrongType:<init>	(Ljava/lang/ClassCastException;Ljava/lang/String;ILjava/lang/Object;)V
    //   698: athrow
    //   699: new 75	gnu/mapping/WrongType
    //   702: dup_x1
    //   703: swap
    //   704: ldc_w 895
    //   707: iconst_2
    //   708: aload_3
    //   709: invokespecial 80	gnu/mapping/WrongType:<init>	(Ljava/lang/ClassCastException;Ljava/lang/String;ILjava/lang/Object;)V
    //   712: athrow
    //   713: new 75	gnu/mapping/WrongType
    //   716: dup_x1
    //   717: swap
    //   718: ldc_w 1122
    //   721: iconst_1
    //   722: aload_2
    //   723: invokespecial 80	gnu/mapping/WrongType:<init>	(Ljava/lang/ClassCastException;Ljava/lang/String;ILjava/lang/Object;)V
    //   726: athrow
    //   727: new 75	gnu/mapping/WrongType
    //   730: dup_x1
    //   731: swap
    //   732: ldc_w 1122
    //   735: iconst_2
    //   736: aload_3
    //   737: invokespecial 80	gnu/mapping/WrongType:<init>	(Ljava/lang/ClassCastException;Ljava/lang/String;ILjava/lang/Object;)V
    //   740: athrow
    //   741: new 75	gnu/mapping/WrongType
    //   744: dup_x1
    //   745: swap
    //   746: ldc_w 923
    //   749: iconst_1
    //   750: aload_2
    //   751: invokespecial 80	gnu/mapping/WrongType:<init>	(Ljava/lang/ClassCastException;Ljava/lang/String;ILjava/lang/Object;)V
    //   754: athrow
    //   755: new 75	gnu/mapping/WrongType
    //   758: dup_x1
    //   759: swap
    //   760: ldc_w 923
    //   763: iconst_2
    //   764: aload_3
    //   765: invokespecial 80	gnu/mapping/WrongType:<init>	(Ljava/lang/ClassCastException;Ljava/lang/String;ILjava/lang/Object;)V
    //   768: athrow
    //   769: new 75	gnu/mapping/WrongType
    //   772: dup_x1
    //   773: swap
    //   774: ldc_w 1133
    //   777: iconst_1
    //   778: aload_2
    //   779: invokespecial 80	gnu/mapping/WrongType:<init>	(Ljava/lang/ClassCastException;Ljava/lang/String;ILjava/lang/Object;)V
    //   782: athrow
    //   783: new 75	gnu/mapping/WrongType
    //   786: dup_x1
    //   787: swap
    //   788: ldc_w 1133
    //   791: iconst_2
    //   792: aload_3
    //   793: invokespecial 80	gnu/mapping/WrongType:<init>	(Ljava/lang/ClassCastException;Ljava/lang/String;ILjava/lang/Object;)V
    //   796: athrow
    //   797: new 75	gnu/mapping/WrongType
    //   800: dup_x1
    //   801: swap
    //   802: ldc_w 945
    //   805: iconst_1
    //   806: aload_2
    //   807: invokespecial 80	gnu/mapping/WrongType:<init>	(Ljava/lang/ClassCastException;Ljava/lang/String;ILjava/lang/Object;)V
    //   810: athrow
    //   811: new 75	gnu/mapping/WrongType
    //   814: dup_x1
    //   815: swap
    //   816: ldc_w 945
    //   819: iconst_2
    //   820: aload_3
    //   821: invokespecial 80	gnu/mapping/WrongType:<init>	(Ljava/lang/ClassCastException;Ljava/lang/String;ILjava/lang/Object;)V
    //   824: athrow
    //   825: new 75	gnu/mapping/WrongType
    //   828: dup_x1
    //   829: swap
    //   830: ldc_w 1144
    //   833: iconst_1
    //   834: aload_2
    //   835: invokespecial 80	gnu/mapping/WrongType:<init>	(Ljava/lang/ClassCastException;Ljava/lang/String;ILjava/lang/Object;)V
    //   838: athrow
    //   839: new 75	gnu/mapping/WrongType
    //   842: dup_x1
    //   843: swap
    //   844: ldc_w 1144
    //   847: iconst_2
    //   848: aload_3
    //   849: invokespecial 80	gnu/mapping/WrongType:<init>	(Ljava/lang/ClassCastException;Ljava/lang/String;ILjava/lang/Object;)V
    //   852: athrow
    //   853: new 75	gnu/mapping/WrongType
    //   856: dup_x1
    //   857: swap
    //   858: ldc_w 967
    //   861: iconst_1
    //   862: aload_2
    //   863: invokespecial 80	gnu/mapping/WrongType:<init>	(Ljava/lang/ClassCastException;Ljava/lang/String;ILjava/lang/Object;)V
    //   866: athrow
    //   867: new 75	gnu/mapping/WrongType
    //   870: dup_x1
    //   871: swap
    //   872: ldc_w 967
    //   875: iconst_2
    //   876: aload_3
    //   877: invokespecial 80	gnu/mapping/WrongType:<init>	(Ljava/lang/ClassCastException;Ljava/lang/String;ILjava/lang/Object;)V
    //   880: athrow
    //   881: new 75	gnu/mapping/WrongType
    //   884: dup_x1
    //   885: swap
    //   886: ldc_w 1155
    //   889: iconst_1
    //   890: aload_2
    //   891: invokespecial 80	gnu/mapping/WrongType:<init>	(Ljava/lang/ClassCastException;Ljava/lang/String;ILjava/lang/Object;)V
    //   894: athrow
    //   895: new 75	gnu/mapping/WrongType
    //   898: dup_x1
    //   899: swap
    //   900: ldc_w 1155
    //   903: iconst_2
    //   904: aload_3
    //   905: invokespecial 80	gnu/mapping/WrongType:<init>	(Ljava/lang/ClassCastException;Ljava/lang/String;ILjava/lang/Object;)V
    //   908: athrow
    //   909: new 75	gnu/mapping/WrongType
    //   912: dup_x1
    //   913: swap
    //   914: ldc_w 989
    //   917: iconst_1
    //   918: aload_2
    //   919: invokespecial 80	gnu/mapping/WrongType:<init>	(Ljava/lang/ClassCastException;Ljava/lang/String;ILjava/lang/Object;)V
    //   922: athrow
    //   923: new 75	gnu/mapping/WrongType
    //   926: dup_x1
    //   927: swap
    //   928: ldc_w 989
    //   931: iconst_2
    //   932: aload_3
    //   933: invokespecial 80	gnu/mapping/WrongType:<init>	(Ljava/lang/ClassCastException;Ljava/lang/String;ILjava/lang/Object;)V
    //   936: athrow
    //   937: new 75	gnu/mapping/WrongType
    //   940: dup_x1
    //   941: swap
    //   942: ldc_w 1166
    //   945: iconst_1
    //   946: aload_2
    //   947: invokespecial 80	gnu/mapping/WrongType:<init>	(Ljava/lang/ClassCastException;Ljava/lang/String;ILjava/lang/Object;)V
    //   950: athrow
    //   951: new 75	gnu/mapping/WrongType
    //   954: dup_x1
    //   955: swap
    //   956: ldc_w 1166
    //   959: iconst_2
    //   960: aload_3
    //   961: invokespecial 80	gnu/mapping/WrongType:<init>	(Ljava/lang/ClassCastException;Ljava/lang/String;ILjava/lang/Object;)V
    //   964: athrow
    //   965: new 75	gnu/mapping/WrongType
    //   968: dup_x1
    //   969: swap
    //   970: ldc_w 1011
    //   973: iconst_1
    //   974: aload_2
    //   975: invokespecial 80	gnu/mapping/WrongType:<init>	(Ljava/lang/ClassCastException;Ljava/lang/String;ILjava/lang/Object;)V
    //   978: athrow
    //   979: new 75	gnu/mapping/WrongType
    //   982: dup_x1
    //   983: swap
    //   984: ldc_w 1011
    //   987: iconst_2
    //   988: aload_3
    //   989: invokespecial 80	gnu/mapping/WrongType:<init>	(Ljava/lang/ClassCastException;Ljava/lang/String;ILjava/lang/Object;)V
    //   992: athrow
    //   993: new 75	gnu/mapping/WrongType
    //   996: dup_x1
    //   997: swap
    //   998: ldc_w 1172
    //   1001: iconst_1
    //   1002: aload_2
    //   1003: invokespecial 80	gnu/mapping/WrongType:<init>	(Ljava/lang/ClassCastException;Ljava/lang/String;ILjava/lang/Object;)V
    //   1006: athrow
    //   1007: new 75	gnu/mapping/WrongType
    //   1010: dup_x1
    //   1011: swap
    //   1012: ldc_w 1172
    //   1015: iconst_2
    //   1016: aload_3
    //   1017: invokespecial 80	gnu/mapping/WrongType:<init>	(Ljava/lang/ClassCastException;Ljava/lang/String;ILjava/lang/Object;)V
    //   1020: athrow
    //   1021: new 75	gnu/mapping/WrongType
    //   1024: dup_x1
    //   1025: swap
    //   1026: ldc_w 1033
    //   1029: iconst_1
    //   1030: aload_2
    //   1031: invokespecial 80	gnu/mapping/WrongType:<init>	(Ljava/lang/ClassCastException;Ljava/lang/String;ILjava/lang/Object;)V
    //   1034: athrow
    //   1035: new 75	gnu/mapping/WrongType
    //   1038: dup_x1
    //   1039: swap
    //   1040: ldc_w 1033
    //   1043: iconst_2
    //   1044: aload_3
    //   1045: invokespecial 80	gnu/mapping/WrongType:<init>	(Ljava/lang/ClassCastException;Ljava/lang/String;ILjava/lang/Object;)V
    //   1048: athrow
    //   1049: new 75	gnu/mapping/WrongType
    //   1052: dup_x1
    //   1053: swap
    //   1054: ldc_w 1183
    //   1057: iconst_1
    //   1058: aload_2
    //   1059: invokespecial 80	gnu/mapping/WrongType:<init>	(Ljava/lang/ClassCastException;Ljava/lang/String;ILjava/lang/Object;)V
    //   1062: athrow
    //   1063: new 75	gnu/mapping/WrongType
    //   1066: dup_x1
    //   1067: swap
    //   1068: ldc_w 1183
    //   1071: iconst_2
    //   1072: aload_3
    //   1073: invokespecial 80	gnu/mapping/WrongType:<init>	(Ljava/lang/ClassCastException;Ljava/lang/String;ILjava/lang/Object;)V
    //   1076: athrow
    //   1077: new 75	gnu/mapping/WrongType
    //   1080: dup_x1
    //   1081: swap
    //   1082: ldc_w 1055
    //   1085: iconst_1
    //   1086: aload_2
    //   1087: invokespecial 80	gnu/mapping/WrongType:<init>	(Ljava/lang/ClassCastException;Ljava/lang/String;ILjava/lang/Object;)V
    //   1090: athrow
    //   1091: new 75	gnu/mapping/WrongType
    //   1094: dup_x1
    //   1095: swap
    //   1096: ldc_w 1055
    //   1099: iconst_2
    //   1100: aload_3
    //   1101: invokespecial 80	gnu/mapping/WrongType:<init>	(Ljava/lang/ClassCastException;Ljava/lang/String;ILjava/lang/Object;)V
    //   1104: athrow
    //   1105: new 75	gnu/mapping/WrongType
    //   1108: dup_x1
    //   1109: swap
    //   1110: ldc_w 1199
    //   1113: iconst_1
    //   1114: aload_2
    //   1115: invokespecial 80	gnu/mapping/WrongType:<init>	(Ljava/lang/ClassCastException;Ljava/lang/String;ILjava/lang/Object;)V
    //   1118: athrow
    //   1119: new 75	gnu/mapping/WrongType
    //   1122: dup_x1
    //   1123: swap
    //   1124: ldc_w 1199
    //   1127: iconst_2
    //   1128: aload_3
    //   1129: invokespecial 80	gnu/mapping/WrongType:<init>	(Ljava/lang/ClassCastException;Ljava/lang/String;ILjava/lang/Object;)V
    //   1132: athrow
    //   1133: new 75	gnu/mapping/WrongType
    //   1136: dup_x1
    //   1137: swap
    //   1138: ldc_w 1077
    //   1141: iconst_1
    //   1142: aload_2
    //   1143: invokespecial 80	gnu/mapping/WrongType:<init>	(Ljava/lang/ClassCastException;Ljava/lang/String;ILjava/lang/Object;)V
    //   1146: athrow
    //   1147: new 75	gnu/mapping/WrongType
    //   1150: dup_x1
    //   1151: swap
    //   1152: ldc_w 1077
    //   1155: iconst_2
    //   1156: aload_3
    //   1157: invokespecial 80	gnu/mapping/WrongType:<init>	(Ljava/lang/ClassCastException;Ljava/lang/String;ILjava/lang/Object;)V
    //   1160: athrow
    //   1161: new 75	gnu/mapping/WrongType
    //   1164: dup_x1
    //   1165: swap
    //   1166: ldc_w 1210
    //   1169: iconst_1
    //   1170: aload_2
    //   1171: invokespecial 80	gnu/mapping/WrongType:<init>	(Ljava/lang/ClassCastException;Ljava/lang/String;ILjava/lang/Object;)V
    //   1174: athrow
    //   1175: new 75	gnu/mapping/WrongType
    //   1178: dup_x1
    //   1179: swap
    //   1180: ldc_w 1210
    //   1183: iconst_2
    //   1184: aload_3
    //   1185: invokespecial 80	gnu/mapping/WrongType:<init>	(Ljava/lang/ClassCastException;Ljava/lang/String;ILjava/lang/Object;)V
    //   1188: athrow
    //   1189: new 75	gnu/mapping/WrongType
    //   1192: dup_x1
    //   1193: swap
    //   1194: ldc_w 1099
    //   1197: iconst_1
    //   1198: aload_2
    //   1199: invokespecial 80	gnu/mapping/WrongType:<init>	(Ljava/lang/ClassCastException;Ljava/lang/String;ILjava/lang/Object;)V
    //   1202: athrow
    //   1203: new 75	gnu/mapping/WrongType
    //   1206: dup_x1
    //   1207: swap
    //   1208: ldc_w 1099
    //   1211: iconst_2
    //   1212: aload_3
    //   1213: invokespecial 80	gnu/mapping/WrongType:<init>	(Ljava/lang/ClassCastException;Ljava/lang/String;ILjava/lang/Object;)V
    //   1216: athrow
    //   1217: new 75	gnu/mapping/WrongType
    //   1220: dup_x1
    //   1221: swap
    //   1222: ldc_w 1221
    //   1225: iconst_1
    //   1226: aload_2
    //   1227: invokespecial 80	gnu/mapping/WrongType:<init>	(Ljava/lang/ClassCastException;Ljava/lang/String;ILjava/lang/Object;)V
    //   1230: athrow
    //   1231: new 75	gnu/mapping/WrongType
    //   1234: dup_x1
    //   1235: swap
    //   1236: ldc_w 1221
    //   1239: iconst_2
    //   1240: aload_3
    //   1241: invokespecial 80	gnu/mapping/WrongType:<init>	(Ljava/lang/ClassCastException;Ljava/lang/String;ILjava/lang/Object;)V
    //   1244: athrow
    // Line number table:
    //   Java source line #10	-> byte code offset #176
    //   Java source line #19	-> byte code offset #200
    //   Java source line #46	-> byte code offset #226
    //   Java source line #55	-> byte code offset #250
    //   Java source line #70	-> byte code offset #276
    //   Java source line #79	-> byte code offset #300
    //   Java source line #94	-> byte code offset #326
    //   Java source line #103	-> byte code offset #350
    //   Java source line #118	-> byte code offset #376
    //   Java source line #127	-> byte code offset #400
    //   Java source line #142	-> byte code offset #426
    //   Java source line #151	-> byte code offset #450
    //   Java source line #166	-> byte code offset #476
    //   Java source line #175	-> byte code offset #500
    //   Java source line #190	-> byte code offset #526
    //   Java source line #199	-> byte code offset #550
    //   Java source line #214	-> byte code offset #576
    //   Java source line #223	-> byte code offset #600
    //   Java source line #238	-> byte code offset #626
    //   Java source line #247	-> byte code offset #650
    //   Java source line #10	-> byte code offset #685
    //   Java source line #19	-> byte code offset #713
    //   Java source line #46	-> byte code offset #741
    //   Java source line #55	-> byte code offset #769
    //   Java source line #70	-> byte code offset #797
    //   Java source line #79	-> byte code offset #825
    //   Java source line #94	-> byte code offset #853
    //   Java source line #103	-> byte code offset #881
    //   Java source line #118	-> byte code offset #909
    //   Java source line #127	-> byte code offset #937
    //   Java source line #142	-> byte code offset #965
    //   Java source line #151	-> byte code offset #993
    //   Java source line #166	-> byte code offset #1021
    //   Java source line #175	-> byte code offset #1049
    //   Java source line #190	-> byte code offset #1077
    //   Java source line #199	-> byte code offset #1105
    //   Java source line #214	-> byte code offset #1133
    //   Java source line #223	-> byte code offset #1161
    //   Java source line #238	-> byte code offset #1189
    //   Java source line #247	-> byte code offset #1217
    // Local variable table:
    //   start	length	slot	name	signature
    //   0	1245	0	this	uniform
    //   0	1245	1	paramModuleMethod	ModuleMethod
    //   0	1245	2	paramObject1	Object
    //   0	1245	3	paramObject2	Object
    //   685	1	4	localClassCastException1	ClassCastException
    //   699	1	5	localClassCastException2	ClassCastException
    //   713	1	6	localClassCastException3	ClassCastException
    //   727	1	7	localClassCastException4	ClassCastException
    //   741	1	8	localClassCastException5	ClassCastException
    //   755	1	9	localClassCastException6	ClassCastException
    //   769	1	10	localClassCastException7	ClassCastException
    //   783	1	11	localClassCastException8	ClassCastException
    //   797	1	12	localClassCastException9	ClassCastException
    //   811	1	13	localClassCastException10	ClassCastException
    //   825	1	14	localClassCastException11	ClassCastException
    //   839	1	15	localClassCastException12	ClassCastException
    //   853	1	16	localClassCastException13	ClassCastException
    //   867	1	17	localClassCastException14	ClassCastException
    //   881	1	18	localClassCastException15	ClassCastException
    //   895	1	19	localClassCastException16	ClassCastException
    //   909	1	20	localClassCastException17	ClassCastException
    //   923	1	21	localClassCastException18	ClassCastException
    //   937	1	22	localClassCastException19	ClassCastException
    //   951	1	23	localClassCastException20	ClassCastException
    //   965	1	24	localClassCastException21	ClassCastException
    //   979	1	25	localClassCastException22	ClassCastException
    //   993	1	26	localClassCastException23	ClassCastException
    //   1007	1	27	localClassCastException24	ClassCastException
    //   1021	1	28	localClassCastException25	ClassCastException
    //   1035	1	29	localClassCastException26	ClassCastException
    //   1049	1	30	localClassCastException27	ClassCastException
    //   1063	1	31	localClassCastException28	ClassCastException
    //   1077	1	32	localClassCastException29	ClassCastException
    //   1091	1	33	localClassCastException30	ClassCastException
    //   1105	1	34	localClassCastException31	ClassCastException
    //   1119	1	35	localClassCastException32	ClassCastException
    //   1133	1	36	localClassCastException33	ClassCastException
    //   1147	1	37	localClassCastException34	ClassCastException
    //   1161	1	38	localClassCastException35	ClassCastException
    //   1175	1	39	localClassCastException36	ClassCastException
    //   1189	1	40	localClassCastException37	ClassCastException
    //   1203	1	41	localClassCastException38	ClassCastException
    //   1217	1	42	localClassCastException39	ClassCastException
    //   1231	1	43	localClassCastException40	ClassCastException
    // Exception table:
    //   from	to	target	type
    //   180	186	685	java/lang/ClassCastException
    //   190	196	699	java/lang/ClassCastException
    //   206	209	713	java/lang/ClassCastException
    //   213	219	727	java/lang/ClassCastException
    //   230	236	741	java/lang/ClassCastException
    //   240	246	755	java/lang/ClassCastException
    //   256	259	769	java/lang/ClassCastException
    //   263	269	783	java/lang/ClassCastException
    //   280	286	797	java/lang/ClassCastException
    //   290	296	811	java/lang/ClassCastException
    //   306	309	825	java/lang/ClassCastException
    //   313	319	839	java/lang/ClassCastException
    //   330	336	853	java/lang/ClassCastException
    //   340	346	867	java/lang/ClassCastException
    //   356	359	881	java/lang/ClassCastException
    //   363	369	895	java/lang/ClassCastException
    //   380	386	909	java/lang/ClassCastException
    //   390	396	923	java/lang/ClassCastException
    //   406	409	937	java/lang/ClassCastException
    //   413	419	951	java/lang/ClassCastException
    //   430	436	965	java/lang/ClassCastException
    //   440	446	979	java/lang/ClassCastException
    //   456	459	993	java/lang/ClassCastException
    //   463	469	1007	java/lang/ClassCastException
    //   480	486	1021	java/lang/ClassCastException
    //   490	496	1035	java/lang/ClassCastException
    //   506	509	1049	java/lang/ClassCastException
    //   513	519	1063	java/lang/ClassCastException
    //   530	536	1077	java/lang/ClassCastException
    //   543	546	1091	java/lang/ClassCastException
    //   556	559	1105	java/lang/ClassCastException
    //   563	569	1119	java/lang/ClassCastException
    //   580	586	1133	java/lang/ClassCastException
    //   590	596	1147	java/lang/ClassCastException
    //   606	609	1161	java/lang/ClassCastException
    //   613	619	1175	java/lang/ClassCastException
    //   630	636	1189	java/lang/ClassCastException
    //   640	646	1203	java/lang/ClassCastException
    //   657	660	1217	java/lang/ClassCastException
    //   664	670	1231	java/lang/ClassCastException
  }
  
  /* Error */
  public Object apply3(ModuleMethod paramModuleMethod, Object paramObject1, Object paramObject2, Object paramObject3)
  {
    // Byte code:
    //   0: aload_1
    //   1: getfield 831	gnu/expr/ModuleMethod:selector	I
    //   4: lookupswitch	default:+463->467, 7:+92->96, 16:+129->133, 25:+166->170, 34:+203->207, 43:+240->244, 52:+277->281, 61:+314->318, 70:+351->355, 79:+388->392, 88:+425->429
    //   96: aload_2
    //   97: ldc 12
    //   99: invokestatic 59	gnu/mapping/Promise:force	(Ljava/lang/Object;Ljava/lang/Class;)Ljava/lang/Object;
    //   102: checkcast 12	gnu/lists/S8Vector
    //   105: aload_3
    //   106: invokestatic 66	gnu/mapping/Promise:force	(Ljava/lang/Object;)Ljava/lang/Object;
    //   109: checkcast 68	java/lang/Number
    //   112: invokevirtual 71	java/lang/Number:intValue	()I
    //   115: aload 4
    //   117: invokestatic 66	gnu/mapping/Promise:force	(Ljava/lang/Object;)Ljava/lang/Object;
    //   120: checkcast 68	java/lang/Number
    //   123: invokevirtual 71	java/lang/Number:intValue	()I
    //   126: invokestatic 1240	kawa/lib/uniform:s8vectorSet$Ex	(Lgnu/lists/S8Vector;IB)V
    //   129: getstatic 1246	gnu/mapping/Values:empty	Lgnu/mapping/Values;
    //   132: areturn
    //   133: aload_2
    //   134: ldc 88
    //   136: invokestatic 59	gnu/mapping/Promise:force	(Ljava/lang/Object;Ljava/lang/Class;)Ljava/lang/Object;
    //   139: checkcast 88	gnu/lists/U8Vector
    //   142: aload_3
    //   143: invokestatic 66	gnu/mapping/Promise:force	(Ljava/lang/Object;)Ljava/lang/Object;
    //   146: checkcast 68	java/lang/Number
    //   149: invokevirtual 71	java/lang/Number:intValue	()I
    //   152: aload 4
    //   154: invokestatic 66	gnu/mapping/Promise:force	(Ljava/lang/Object;)Ljava/lang/Object;
    //   157: checkcast 68	java/lang/Number
    //   160: invokevirtual 71	java/lang/Number:intValue	()I
    //   163: invokestatic 1252	kawa/lib/uniform:u8vectorSet$Ex	(Lgnu/lists/U8Vector;II)V
    //   166: getstatic 1246	gnu/mapping/Values:empty	Lgnu/mapping/Values;
    //   169: areturn
    //   170: aload_2
    //   171: ldc 103
    //   173: invokestatic 59	gnu/mapping/Promise:force	(Ljava/lang/Object;Ljava/lang/Class;)Ljava/lang/Object;
    //   176: checkcast 103	gnu/lists/S16Vector
    //   179: aload_3
    //   180: invokestatic 66	gnu/mapping/Promise:force	(Ljava/lang/Object;)Ljava/lang/Object;
    //   183: checkcast 68	java/lang/Number
    //   186: invokevirtual 71	java/lang/Number:intValue	()I
    //   189: aload 4
    //   191: invokestatic 66	gnu/mapping/Promise:force	(Ljava/lang/Object;)Ljava/lang/Object;
    //   194: checkcast 68	java/lang/Number
    //   197: invokevirtual 71	java/lang/Number:intValue	()I
    //   200: invokestatic 1258	kawa/lib/uniform:s16vectorSet$Ex	(Lgnu/lists/S16Vector;IS)V
    //   203: getstatic 1246	gnu/mapping/Values:empty	Lgnu/mapping/Values;
    //   206: areturn
    //   207: aload_2
    //   208: ldc 127
    //   210: invokestatic 59	gnu/mapping/Promise:force	(Ljava/lang/Object;Ljava/lang/Class;)Ljava/lang/Object;
    //   213: checkcast 127	gnu/lists/U16Vector
    //   216: aload_3
    //   217: invokestatic 66	gnu/mapping/Promise:force	(Ljava/lang/Object;)Ljava/lang/Object;
    //   220: checkcast 68	java/lang/Number
    //   223: invokevirtual 71	java/lang/Number:intValue	()I
    //   226: aload 4
    //   228: invokestatic 66	gnu/mapping/Promise:force	(Ljava/lang/Object;)Ljava/lang/Object;
    //   231: checkcast 68	java/lang/Number
    //   234: invokevirtual 71	java/lang/Number:intValue	()I
    //   237: invokestatic 1264	kawa/lib/uniform:u16vectorSet$Ex	(Lgnu/lists/U16Vector;II)V
    //   240: getstatic 1246	gnu/mapping/Values:empty	Lgnu/mapping/Values;
    //   243: areturn
    //   244: aload_2
    //   245: ldc -114
    //   247: invokestatic 59	gnu/mapping/Promise:force	(Ljava/lang/Object;Ljava/lang/Class;)Ljava/lang/Object;
    //   250: checkcast 142	gnu/lists/S32Vector
    //   253: aload_3
    //   254: invokestatic 66	gnu/mapping/Promise:force	(Ljava/lang/Object;)Ljava/lang/Object;
    //   257: checkcast 68	java/lang/Number
    //   260: invokevirtual 71	java/lang/Number:intValue	()I
    //   263: aload 4
    //   265: invokestatic 66	gnu/mapping/Promise:force	(Ljava/lang/Object;)Ljava/lang/Object;
    //   268: checkcast 68	java/lang/Number
    //   271: invokevirtual 71	java/lang/Number:intValue	()I
    //   274: invokestatic 1270	kawa/lib/uniform:s32vectorSet$Ex	(Lgnu/lists/S32Vector;II)V
    //   277: getstatic 1246	gnu/mapping/Values:empty	Lgnu/mapping/Values;
    //   280: areturn
    //   281: aload_2
    //   282: ldc -90
    //   284: invokestatic 59	gnu/mapping/Promise:force	(Ljava/lang/Object;Ljava/lang/Class;)Ljava/lang/Object;
    //   287: checkcast 166	gnu/lists/U32Vector
    //   290: aload_3
    //   291: invokestatic 66	gnu/mapping/Promise:force	(Ljava/lang/Object;)Ljava/lang/Object;
    //   294: checkcast 68	java/lang/Number
    //   297: invokevirtual 71	java/lang/Number:intValue	()I
    //   300: aload 4
    //   302: invokestatic 66	gnu/mapping/Promise:force	(Ljava/lang/Object;)Ljava/lang/Object;
    //   305: checkcast 68	java/lang/Number
    //   308: invokevirtual 71	java/lang/Number:intValue	()I
    //   311: invokestatic 1276	kawa/lib/uniform:u32vectorSet$Ex	(Lgnu/lists/U32Vector;II)V
    //   314: getstatic 1246	gnu/mapping/Values:empty	Lgnu/mapping/Values;
    //   317: areturn
    //   318: aload_2
    //   319: ldc -75
    //   321: invokestatic 59	gnu/mapping/Promise:force	(Ljava/lang/Object;Ljava/lang/Class;)Ljava/lang/Object;
    //   324: checkcast 181	gnu/lists/S64Vector
    //   327: aload_3
    //   328: invokestatic 66	gnu/mapping/Promise:force	(Ljava/lang/Object;)Ljava/lang/Object;
    //   331: checkcast 68	java/lang/Number
    //   334: invokevirtual 71	java/lang/Number:intValue	()I
    //   337: aload 4
    //   339: invokestatic 66	gnu/mapping/Promise:force	(Ljava/lang/Object;)Ljava/lang/Object;
    //   342: checkcast 68	java/lang/Number
    //   345: invokevirtual 204	java/lang/Number:longValue	()J
    //   348: invokestatic 1282	kawa/lib/uniform:s64vectorSet$Ex	(Lgnu/lists/S64Vector;IJ)V
    //   351: getstatic 1246	gnu/mapping/Values:empty	Lgnu/mapping/Values;
    //   354: areturn
    //   355: aload_2
    //   356: ldc -47
    //   358: invokestatic 59	gnu/mapping/Promise:force	(Ljava/lang/Object;Ljava/lang/Class;)Ljava/lang/Object;
    //   361: checkcast 209	gnu/lists/U64Vector
    //   364: aload_3
    //   365: invokestatic 66	gnu/mapping/Promise:force	(Ljava/lang/Object;)Ljava/lang/Object;
    //   368: checkcast 68	java/lang/Number
    //   371: invokevirtual 71	java/lang/Number:intValue	()I
    //   374: aload 4
    //   376: invokestatic 66	gnu/mapping/Promise:force	(Ljava/lang/Object;)Ljava/lang/Object;
    //   379: checkcast 68	java/lang/Number
    //   382: invokevirtual 204	java/lang/Number:longValue	()J
    //   385: invokestatic 1288	kawa/lib/uniform:u64vectorSet$Ex	(Lgnu/lists/U64Vector;IJ)V
    //   388: getstatic 1246	gnu/mapping/Values:empty	Lgnu/mapping/Values;
    //   391: areturn
    //   392: aload_2
    //   393: ldc -26
    //   395: invokestatic 59	gnu/mapping/Promise:force	(Ljava/lang/Object;Ljava/lang/Class;)Ljava/lang/Object;
    //   398: checkcast 230	gnu/lists/F32Vector
    //   401: aload_3
    //   402: invokestatic 66	gnu/mapping/Promise:force	(Ljava/lang/Object;)Ljava/lang/Object;
    //   405: checkcast 68	java/lang/Number
    //   408: invokevirtual 71	java/lang/Number:intValue	()I
    //   411: aload 4
    //   413: invokestatic 66	gnu/mapping/Promise:force	(Ljava/lang/Object;)Ljava/lang/Object;
    //   416: checkcast 68	java/lang/Number
    //   419: invokevirtual 253	java/lang/Number:floatValue	()F
    //   422: invokestatic 1294	kawa/lib/uniform:f32vectorSet$Ex	(Lgnu/lists/F32Vector;IF)V
    //   425: getstatic 1246	gnu/mapping/Values:empty	Lgnu/mapping/Values;
    //   428: areturn
    //   429: aload_2
    //   430: ldc_w 258
    //   433: invokestatic 59	gnu/mapping/Promise:force	(Ljava/lang/Object;Ljava/lang/Class;)Ljava/lang/Object;
    //   436: checkcast 258	gnu/lists/F64Vector
    //   439: aload_3
    //   440: invokestatic 66	gnu/mapping/Promise:force	(Ljava/lang/Object;)Ljava/lang/Object;
    //   443: checkcast 68	java/lang/Number
    //   446: invokevirtual 71	java/lang/Number:intValue	()I
    //   449: aload 4
    //   451: invokestatic 66	gnu/mapping/Promise:force	(Ljava/lang/Object;)Ljava/lang/Object;
    //   454: checkcast 68	java/lang/Number
    //   457: invokevirtual 281	java/lang/Number:doubleValue	()D
    //   460: invokestatic 1300	kawa/lib/uniform:f64vectorSet$Ex	(Lgnu/lists/F64Vector;ID)V
    //   463: getstatic 1246	gnu/mapping/Values:empty	Lgnu/mapping/Values;
    //   466: areturn
    //   467: aload_0
    //   468: aload_1
    //   469: aload_2
    //   470: aload_3
    //   471: aload 4
    //   473: invokespecial 1304	gnu/expr/ModuleBody:apply3	(Lgnu/expr/ModuleMethod;Ljava/lang/Object;Ljava/lang/Object;Ljava/lang/Object;)Ljava/lang/Object;
    //   476: areturn
    //   477: new 75	gnu/mapping/WrongType
    //   480: dup_x1
    //   481: swap
    //   482: ldc_w 1236
    //   485: iconst_1
    //   486: aload_2
    //   487: invokespecial 80	gnu/mapping/WrongType:<init>	(Ljava/lang/ClassCastException;Ljava/lang/String;ILjava/lang/Object;)V
    //   490: athrow
    //   491: new 75	gnu/mapping/WrongType
    //   494: dup_x1
    //   495: swap
    //   496: ldc_w 1236
    //   499: iconst_2
    //   500: aload_3
    //   501: invokespecial 80	gnu/mapping/WrongType:<init>	(Ljava/lang/ClassCastException;Ljava/lang/String;ILjava/lang/Object;)V
    //   504: athrow
    //   505: new 75	gnu/mapping/WrongType
    //   508: dup_x1
    //   509: swap
    //   510: ldc_w 1236
    //   513: iconst_3
    //   514: aload 4
    //   516: invokespecial 80	gnu/mapping/WrongType:<init>	(Ljava/lang/ClassCastException;Ljava/lang/String;ILjava/lang/Object;)V
    //   519: athrow
    //   520: new 75	gnu/mapping/WrongType
    //   523: dup_x1
    //   524: swap
    //   525: ldc_w 1248
    //   528: iconst_1
    //   529: aload_2
    //   530: invokespecial 80	gnu/mapping/WrongType:<init>	(Ljava/lang/ClassCastException;Ljava/lang/String;ILjava/lang/Object;)V
    //   533: athrow
    //   534: new 75	gnu/mapping/WrongType
    //   537: dup_x1
    //   538: swap
    //   539: ldc_w 1248
    //   542: iconst_2
    //   543: aload_3
    //   544: invokespecial 80	gnu/mapping/WrongType:<init>	(Ljava/lang/ClassCastException;Ljava/lang/String;ILjava/lang/Object;)V
    //   547: athrow
    //   548: new 75	gnu/mapping/WrongType
    //   551: dup_x1
    //   552: swap
    //   553: ldc_w 1248
    //   556: iconst_3
    //   557: aload 4
    //   559: invokespecial 80	gnu/mapping/WrongType:<init>	(Ljava/lang/ClassCastException;Ljava/lang/String;ILjava/lang/Object;)V
    //   562: athrow
    //   563: new 75	gnu/mapping/WrongType
    //   566: dup_x1
    //   567: swap
    //   568: ldc_w 1254
    //   571: iconst_1
    //   572: aload_2
    //   573: invokespecial 80	gnu/mapping/WrongType:<init>	(Ljava/lang/ClassCastException;Ljava/lang/String;ILjava/lang/Object;)V
    //   576: athrow
    //   577: new 75	gnu/mapping/WrongType
    //   580: dup_x1
    //   581: swap
    //   582: ldc_w 1254
    //   585: iconst_2
    //   586: aload_3
    //   587: invokespecial 80	gnu/mapping/WrongType:<init>	(Ljava/lang/ClassCastException;Ljava/lang/String;ILjava/lang/Object;)V
    //   590: athrow
    //   591: new 75	gnu/mapping/WrongType
    //   594: dup_x1
    //   595: swap
    //   596: ldc_w 1254
    //   599: iconst_3
    //   600: aload 4
    //   602: invokespecial 80	gnu/mapping/WrongType:<init>	(Ljava/lang/ClassCastException;Ljava/lang/String;ILjava/lang/Object;)V
    //   605: athrow
    //   606: new 75	gnu/mapping/WrongType
    //   609: dup_x1
    //   610: swap
    //   611: ldc_w 1260
    //   614: iconst_1
    //   615: aload_2
    //   616: invokespecial 80	gnu/mapping/WrongType:<init>	(Ljava/lang/ClassCastException;Ljava/lang/String;ILjava/lang/Object;)V
    //   619: athrow
    //   620: new 75	gnu/mapping/WrongType
    //   623: dup_x1
    //   624: swap
    //   625: ldc_w 1260
    //   628: iconst_2
    //   629: aload_3
    //   630: invokespecial 80	gnu/mapping/WrongType:<init>	(Ljava/lang/ClassCastException;Ljava/lang/String;ILjava/lang/Object;)V
    //   633: athrow
    //   634: new 75	gnu/mapping/WrongType
    //   637: dup_x1
    //   638: swap
    //   639: ldc_w 1260
    //   642: iconst_3
    //   643: aload 4
    //   645: invokespecial 80	gnu/mapping/WrongType:<init>	(Ljava/lang/ClassCastException;Ljava/lang/String;ILjava/lang/Object;)V
    //   648: athrow
    //   649: new 75	gnu/mapping/WrongType
    //   652: dup_x1
    //   653: swap
    //   654: ldc_w 1266
    //   657: iconst_1
    //   658: aload_2
    //   659: invokespecial 80	gnu/mapping/WrongType:<init>	(Ljava/lang/ClassCastException;Ljava/lang/String;ILjava/lang/Object;)V
    //   662: athrow
    //   663: new 75	gnu/mapping/WrongType
    //   666: dup_x1
    //   667: swap
    //   668: ldc_w 1266
    //   671: iconst_2
    //   672: aload_3
    //   673: invokespecial 80	gnu/mapping/WrongType:<init>	(Ljava/lang/ClassCastException;Ljava/lang/String;ILjava/lang/Object;)V
    //   676: athrow
    //   677: new 75	gnu/mapping/WrongType
    //   680: dup_x1
    //   681: swap
    //   682: ldc_w 1266
    //   685: iconst_3
    //   686: aload 4
    //   688: invokespecial 80	gnu/mapping/WrongType:<init>	(Ljava/lang/ClassCastException;Ljava/lang/String;ILjava/lang/Object;)V
    //   691: athrow
    //   692: new 75	gnu/mapping/WrongType
    //   695: dup_x1
    //   696: swap
    //   697: ldc_w 1272
    //   700: iconst_1
    //   701: aload_2
    //   702: invokespecial 80	gnu/mapping/WrongType:<init>	(Ljava/lang/ClassCastException;Ljava/lang/String;ILjava/lang/Object;)V
    //   705: athrow
    //   706: new 75	gnu/mapping/WrongType
    //   709: dup_x1
    //   710: swap
    //   711: ldc_w 1272
    //   714: iconst_2
    //   715: aload_3
    //   716: invokespecial 80	gnu/mapping/WrongType:<init>	(Ljava/lang/ClassCastException;Ljava/lang/String;ILjava/lang/Object;)V
    //   719: athrow
    //   720: new 75	gnu/mapping/WrongType
    //   723: dup_x1
    //   724: swap
    //   725: ldc_w 1272
    //   728: iconst_3
    //   729: aload 4
    //   731: invokespecial 80	gnu/mapping/WrongType:<init>	(Ljava/lang/ClassCastException;Ljava/lang/String;ILjava/lang/Object;)V
    //   734: athrow
    //   735: new 75	gnu/mapping/WrongType
    //   738: dup_x1
    //   739: swap
    //   740: ldc_w 1278
    //   743: iconst_1
    //   744: aload_2
    //   745: invokespecial 80	gnu/mapping/WrongType:<init>	(Ljava/lang/ClassCastException;Ljava/lang/String;ILjava/lang/Object;)V
    //   748: athrow
    //   749: new 75	gnu/mapping/WrongType
    //   752: dup_x1
    //   753: swap
    //   754: ldc_w 1278
    //   757: iconst_2
    //   758: aload_3
    //   759: invokespecial 80	gnu/mapping/WrongType:<init>	(Ljava/lang/ClassCastException;Ljava/lang/String;ILjava/lang/Object;)V
    //   762: athrow
    //   763: new 75	gnu/mapping/WrongType
    //   766: dup_x1
    //   767: swap
    //   768: ldc_w 1278
    //   771: iconst_3
    //   772: aload 4
    //   774: invokespecial 80	gnu/mapping/WrongType:<init>	(Ljava/lang/ClassCastException;Ljava/lang/String;ILjava/lang/Object;)V
    //   777: athrow
    //   778: new 75	gnu/mapping/WrongType
    //   781: dup_x1
    //   782: swap
    //   783: ldc_w 1284
    //   786: iconst_1
    //   787: aload_2
    //   788: invokespecial 80	gnu/mapping/WrongType:<init>	(Ljava/lang/ClassCastException;Ljava/lang/String;ILjava/lang/Object;)V
    //   791: athrow
    //   792: new 75	gnu/mapping/WrongType
    //   795: dup_x1
    //   796: swap
    //   797: ldc_w 1284
    //   800: iconst_2
    //   801: aload_3
    //   802: invokespecial 80	gnu/mapping/WrongType:<init>	(Ljava/lang/ClassCastException;Ljava/lang/String;ILjava/lang/Object;)V
    //   805: athrow
    //   806: new 75	gnu/mapping/WrongType
    //   809: dup_x1
    //   810: swap
    //   811: ldc_w 1284
    //   814: iconst_3
    //   815: aload 4
    //   817: invokespecial 80	gnu/mapping/WrongType:<init>	(Ljava/lang/ClassCastException;Ljava/lang/String;ILjava/lang/Object;)V
    //   820: athrow
    //   821: new 75	gnu/mapping/WrongType
    //   824: dup_x1
    //   825: swap
    //   826: ldc_w 1290
    //   829: iconst_1
    //   830: aload_2
    //   831: invokespecial 80	gnu/mapping/WrongType:<init>	(Ljava/lang/ClassCastException;Ljava/lang/String;ILjava/lang/Object;)V
    //   834: athrow
    //   835: new 75	gnu/mapping/WrongType
    //   838: dup_x1
    //   839: swap
    //   840: ldc_w 1290
    //   843: iconst_2
    //   844: aload_3
    //   845: invokespecial 80	gnu/mapping/WrongType:<init>	(Ljava/lang/ClassCastException;Ljava/lang/String;ILjava/lang/Object;)V
    //   848: athrow
    //   849: new 75	gnu/mapping/WrongType
    //   852: dup_x1
    //   853: swap
    //   854: ldc_w 1290
    //   857: iconst_3
    //   858: aload 4
    //   860: invokespecial 80	gnu/mapping/WrongType:<init>	(Ljava/lang/ClassCastException;Ljava/lang/String;ILjava/lang/Object;)V
    //   863: athrow
    //   864: new 75	gnu/mapping/WrongType
    //   867: dup_x1
    //   868: swap
    //   869: ldc_w 1296
    //   872: iconst_1
    //   873: aload_2
    //   874: invokespecial 80	gnu/mapping/WrongType:<init>	(Ljava/lang/ClassCastException;Ljava/lang/String;ILjava/lang/Object;)V
    //   877: athrow
    //   878: new 75	gnu/mapping/WrongType
    //   881: dup_x1
    //   882: swap
    //   883: ldc_w 1296
    //   886: iconst_2
    //   887: aload_3
    //   888: invokespecial 80	gnu/mapping/WrongType:<init>	(Ljava/lang/ClassCastException;Ljava/lang/String;ILjava/lang/Object;)V
    //   891: athrow
    //   892: new 75	gnu/mapping/WrongType
    //   895: dup_x1
    //   896: swap
    //   897: ldc_w 1296
    //   900: iconst_3
    //   901: aload 4
    //   903: invokespecial 80	gnu/mapping/WrongType:<init>	(Ljava/lang/ClassCastException;Ljava/lang/String;ILjava/lang/Object;)V
    //   906: athrow
    // Line number table:
    //   Java source line #22	-> byte code offset #96
    //   Java source line #58	-> byte code offset #133
    //   Java source line #82	-> byte code offset #170
    //   Java source line #106	-> byte code offset #207
    //   Java source line #130	-> byte code offset #244
    //   Java source line #154	-> byte code offset #281
    //   Java source line #178	-> byte code offset #318
    //   Java source line #202	-> byte code offset #355
    //   Java source line #226	-> byte code offset #392
    //   Java source line #250	-> byte code offset #429
    //   Java source line #22	-> byte code offset #477
    //   Java source line #58	-> byte code offset #520
    //   Java source line #82	-> byte code offset #563
    //   Java source line #106	-> byte code offset #606
    //   Java source line #130	-> byte code offset #649
    //   Java source line #154	-> byte code offset #692
    //   Java source line #178	-> byte code offset #735
    //   Java source line #202	-> byte code offset #778
    //   Java source line #226	-> byte code offset #821
    //   Java source line #250	-> byte code offset #864
    // Local variable table:
    //   start	length	slot	name	signature
    //   0	907	0	this	uniform
    //   0	907	1	paramModuleMethod	ModuleMethod
    //   0	907	2	paramObject1	Object
    //   0	907	3	paramObject2	Object
    //   0	907	4	paramObject3	Object
    //   477	1	5	localClassCastException1	ClassCastException
    //   491	1	6	localClassCastException2	ClassCastException
    //   505	1	7	localClassCastException3	ClassCastException
    //   520	1	8	localClassCastException4	ClassCastException
    //   534	1	9	localClassCastException5	ClassCastException
    //   548	1	10	localClassCastException6	ClassCastException
    //   563	1	11	localClassCastException7	ClassCastException
    //   577	1	12	localClassCastException8	ClassCastException
    //   591	1	13	localClassCastException9	ClassCastException
    //   606	1	14	localClassCastException10	ClassCastException
    //   620	1	15	localClassCastException11	ClassCastException
    //   634	1	16	localClassCastException12	ClassCastException
    //   649	1	17	localClassCastException13	ClassCastException
    //   663	1	18	localClassCastException14	ClassCastException
    //   677	1	19	localClassCastException15	ClassCastException
    //   692	1	20	localClassCastException16	ClassCastException
    //   706	1	21	localClassCastException17	ClassCastException
    //   720	1	22	localClassCastException18	ClassCastException
    //   735	1	23	localClassCastException19	ClassCastException
    //   749	1	24	localClassCastException20	ClassCastException
    //   763	1	25	localClassCastException21	ClassCastException
    //   778	1	26	localClassCastException22	ClassCastException
    //   792	1	27	localClassCastException23	ClassCastException
    //   806	1	28	localClassCastException24	ClassCastException
    //   821	1	29	localClassCastException25	ClassCastException
    //   835	1	30	localClassCastException26	ClassCastException
    //   849	1	31	localClassCastException27	ClassCastException
    //   864	1	32	localClassCastException28	ClassCastException
    //   878	1	33	localClassCastException29	ClassCastException
    //   892	1	34	localClassCastException30	ClassCastException
    // Exception table:
    //   from	to	target	type
    //   102	105	477	java/lang/ClassCastException
    //   109	115	491	java/lang/ClassCastException
    //   120	126	505	java/lang/ClassCastException
    //   139	142	520	java/lang/ClassCastException
    //   146	152	534	java/lang/ClassCastException
    //   157	163	548	java/lang/ClassCastException
    //   176	179	563	java/lang/ClassCastException
    //   183	189	577	java/lang/ClassCastException
    //   194	200	591	java/lang/ClassCastException
    //   213	216	606	java/lang/ClassCastException
    //   220	226	620	java/lang/ClassCastException
    //   231	237	634	java/lang/ClassCastException
    //   250	253	649	java/lang/ClassCastException
    //   257	263	663	java/lang/ClassCastException
    //   268	274	677	java/lang/ClassCastException
    //   287	290	692	java/lang/ClassCastException
    //   294	300	706	java/lang/ClassCastException
    //   305	311	720	java/lang/ClassCastException
    //   324	327	735	java/lang/ClassCastException
    //   331	337	749	java/lang/ClassCastException
    //   342	348	763	java/lang/ClassCastException
    //   361	364	778	java/lang/ClassCastException
    //   368	374	792	java/lang/ClassCastException
    //   379	385	806	java/lang/ClassCastException
    //   398	401	821	java/lang/ClassCastException
    //   405	411	835	java/lang/ClassCastException
    //   416	422	849	java/lang/ClassCastException
    //   436	439	864	java/lang/ClassCastException
    //   443	449	878	java/lang/ClassCastException
    //   454	460	892	java/lang/ClassCastException
  }
}
