package gnu.kawa.slib;
import gnu.lists.PairWithPosition;

public class enums extends gnu.expr.ModuleBody { public static final kawa.lang.Macro define$Mnenum; public static final kawa.lang.Macro $Prvt$$Pcdefine$Mnenum; static final PairWithPosition Lit0; static final PairWithPosition Lit1; static final PairWithPosition Lit2; static final PairWithPosition Lit3; static final PairWithPosition Lit4; public static enums $instance; static final gnu.mapping.SimpleSymbol Lit5; static final kawa.lang.SyntaxPattern Lit6; static final kawa.lang.SyntaxTemplate Lit7; static final kawa.lang.SyntaxTemplate Lit8; static final kawa.lang.SyntaxPattern Lit9; static final kawa.lang.SyntaxTemplate Lit10; static final kawa.lang.SyntaxPattern Lit11; static final kawa.lang.SyntaxPattern Lit12; static final kawa.lang.SyntaxPattern Lit13; static final kawa.lang.SyntaxTemplate Lit14; static final gnu.mapping.SimpleSymbol Lit15; static final kawa.lang.SyntaxPattern Lit16; static final kawa.lang.SyntaxTemplate Lit17; static final kawa.lang.SyntaxTemplate Lit18; static final kawa.lang.SyntaxTemplate Lit19; static final kawa.lang.SyntaxTemplate Lit20; static final kawa.lang.SyntaxTemplate Lit21; static final kawa.lang.SyntaxTemplate Lit22; private static void $runBody$() { ; gnu.lists.Consumer $result = getInstanceconsumer; }
  static final kawa.lang.SyntaxTemplate Lit23; static final kawa.lang.SyntaxTemplate Lit24; static final kawa.lang.SyntaxTemplate Lit25; static final kawa.lang.SyntaxTemplate Lit26; static final kawa.lang.SyntaxTemplate Lit27; static final kawa.lang.SyntaxTemplate Lit28; static final Object[] Lit29; static final gnu.mapping.SimpleSymbol Lit30; static final gnu.mapping.SimpleSymbol Lit31; static final gnu.mapping.SimpleSymbol Lit32; static final gnu.mapping.SimpleSymbol Lit33; static final gnu.mapping.SimpleSymbol Lit34; static final Object[] Lit35; static { Lit44 = PairWithPosition.make(Lit34, PairWithPosition.make(gnu.mapping.Symbol.valueOf("static"), gnu.lists.LList.Empty, "/mnt/hgfs/trunk/kawaForAndroid/kawa-2.4/gnu/kawa/slib/enums.scm", 274451), "/mnt/hgfs/trunk/kawaForAndroid/kawa-2.4/gnu/kawa/slib/enums.scm", 274451);Lit43 = gnu.mapping.Symbol.valueOf("num");Lit42 = gnu.mapping.Symbol.valueOf("str");Lit41 = gnu.mapping.Symbol.valueOf("*init*");Lit40 = gnu.expr.Keyword.make("access");Lit39 = PairWithPosition.make(enums.Lit32 = gnu.mapping.Symbol.valueOf("::"), PairWithPosition.make(gnu.mapping.Symbol.valueOf("String"), gnu.lists.LList.Empty, "/mnt/hgfs/trunk/kawaForAndroid/kawa-2.4/gnu/kawa/slib/enums.scm", 270354), "/mnt/hgfs/trunk/kawaForAndroid/kawa-2.4/gnu/kawa/slib/enums.scm", 270352);Lit38 = PairWithPosition.make(Lit44, gnu.lists.LList.Empty, "/mnt/hgfs/trunk/kawaForAndroid/kawa-2.4/gnu/kawa/slib/enums.scm", 274450);Lit37 = gnu.expr.Keyword.make("allocation");(enums.Lit36 = new Object[1])[0] = "findkeywords"; Object[] tmp224_221 = (enums.Lit35 = new Object[2]); gnu.mapping.SimpleSymbol tmp232_229 = gnu.mapping.Symbol.valueOf("define-enum");Lit5 = tmp232_229;tmp224_221[0] = tmp232_229;tmp224_221[1] = "findkeywords";Lit33 = gnu.mapping.Symbol.valueOf("java.lang.Enum");Lit31 = gnu.mapping.Symbol.valueOf("s");Lit30 = gnu.mapping.Symbol.valueOf("valueOf");Lit29 = new Object[0];Lit28 = new kawa.lang.SyntaxTemplate("\001\001\003\003", "\020", Lit29, 0);Lit27 = new kawa.lang.SyntaxTemplate("\001\001\003\003", "\020", Lit29, 0);Lit26 = new kawa.lang.SyntaxTemplate("\001\001\003\003", "\030\004", new Object[] { gnu.lists.Pair.make(Lit31, gnu.lists.LList.Empty) }, 0);Lit25 = new kawa.lang.SyntaxTemplate("\001\001\003\003", "\030\004", new Object[] { gnu.lists.Pair.make(PairWithPosition.make(gnu.mapping.Symbol.valueOf("$lookup$"), gnu.lists.Pair.make(Lit33, gnu.lists.Pair.make(gnu.lists.Pair.make(gnu.mapping.Symbol.valueOf("quasiquote"), gnu.lists.Pair.make(Lit30, gnu.lists.LList.Empty)), gnu.lists.LList.Empty)), "/mnt/hgfs/trunk/kawaForAndroid/kawa-2.4/gnu/kawa/slib/enums.scm", 278535), gnu.lists.LList.Empty) }, 0);Lit24 = new kawa.lang.SyntaxTemplate("\001\001\003\003", "\030\004", new Object[] { gnu.lists.Pair.make(Lit37, Lit38) }, 0); Object[] tmp471_468 = new Object[1]; PairWithPosition tmp515_512 = PairWithPosition.make(Lit32, gnu.lists.LList.Empty, "/mnt/hgfs/trunk/kawaForAndroid/kawa-2.4/gnu/kawa/slib/enums.scm", 270361);Lit0 = tmp515_512;tmp471_468[0] = gnu.lists.Pair.make(PairWithPosition.make(Lit30, PairWithPosition.make(Lit31, Lit39, "/mnt/hgfs/trunk/kawaForAndroid/kawa-2.4/gnu/kawa/slib/enums.scm", 270351), "/mnt/hgfs/trunk/kawaForAndroid/kawa-2.4/gnu/kawa/slib/enums.scm", 270342), tmp515_512);Lit23 = new kawa.lang.SyntaxTemplate("\001\001\003\003", "\030\004", tmp471_468, 0);Lit22 = new kawa.lang.SyntaxTemplate("\001\001\003\003", "\030\004", new Object[] { gnu.lists.Pair.make(PairWithPosition.make(Lit33, gnu.lists.LList.Empty, "/mnt/hgfs/trunk/kawaForAndroid/kawa-2.4/gnu/kawa/slib/enums.scm", 253964), PairWithPosition.make(Lit40, PairWithPosition.make(Lit45, gnu.lists.LList.Empty, "/mnt/hgfs/trunk/kawaForAndroid/kawa-2.4/gnu/kawa/slib/enums.scm", 253989), "/mnt/hgfs/trunk/kawaForAndroid/kawa-2.4/gnu/kawa/slib/enums.scm", 253981)) }, 0);Lit21 = new kawa.lang.SyntaxTemplate("\001\001\003\003", "\030\004", new Object[] { gnu.lists.Pair.make(gnu.mapping.Symbol.valueOf("define-simple-class"), gnu.lists.LList.Empty) }, 0);Lit20 = new kawa.lang.SyntaxTemplate("\001\001\003\003", "\b\035\033", Lit29, 1);Lit19 = new kawa.lang.SyntaxTemplate("\001\001\003\003", "\013", Lit29, 0);Lit18 = new kawa.lang.SyntaxTemplate("\001\001\003\003", "\b\025\023", Lit29, 1);Lit17 = new kawa.lang.SyntaxTemplate("\001\001\003\003", "\003", Lit29, 0);Lit16 = new kawa.lang.SyntaxPattern("\f\030\f\007\f\017,\r\027\020\b\b\r\037\030\b\b", Lit29, 4, "enums.scm:50");Lit15 = gnu.mapping.Symbol.valueOf("%define-enum");Lit14 = new kawa.lang.SyntaxTemplate("\001\003", "\021\030\004\t\f\t\003\t\020\b\r\013", Lit35, 1);Lit13 = new kawa.lang.SyntaxPattern("\f\030\f\007\r\017\b\b\b", Lit29, 2, "enums.scm:40");Lit12 = new kawa.lang.SyntaxPattern("\f\030\f\007\b", Lit29, 1, "enums.scm:39");Lit11 = new kawa.lang.SyntaxPattern("\f\030\b", Lit29, 0, "enums.scm:38");Lit10 = new kawa.lang.SyntaxTemplate("\001\003\003", "\021\030\004\t\003\031\b\r\013\b\025\023", new Object[] { Lit15 }, 1);Lit9 = new kawa.lang.SyntaxPattern("\f\030\f\002\f\007,\r\017\b\b\b\r\027\020\b\b", Lit36, 3, "enums.scm:36");Lit8 = new kawa.lang.SyntaxTemplate("\001\003\001\001\003", "\021\030\004\t\f\t\0039\t\023\t\033\b\r\013\b%#", Lit35, 1);Lit7 = new kawa.lang.SyntaxTemplate("\001\003\001\001\003", "\023", Lit29, 0);Lit6 = new kawa.lang.SyntaxPattern("\f\030\f\002\f\007,\r\017\b\b\b\f\027\f\037\r' \b\b", Lit36, 5, "enums.scm:34");Lit4 = PairWithPosition.make(Lit37, Lit38, "/mnt/hgfs/trunk/kawaForAndroid/kawa-2.4/gnu/kawa/slib/enums.scm", 110616);Lit3 = PairWithPosition.make(PairWithPosition.make(gnu.mapping.Symbol.valueOf("values"), gnu.lists.LList.Empty, "/mnt/hgfs/trunk/kawaForAndroid/kawa-2.4/gnu/kawa/slib/enums.scm", 110597), Lit0, "/mnt/hgfs/trunk/kawaForAndroid/kawa-2.4/gnu/kawa/slib/enums.scm", 110596);Lit2 = PairWithPosition.make(PairWithPosition.make(Lit41, PairWithPosition.make(PairWithPosition.make(Lit42, Lit39, "/mnt/hgfs/trunk/kawaForAndroid/kawa-2.4/gnu/kawa/slib/enums.scm", 73741), PairWithPosition.make(PairWithPosition.make(Lit43, PairWithPosition.make(Lit32, PairWithPosition.make(gnu.mapping.Symbol.valueOf("int"), gnu.lists.LList.Empty, "/mnt/hgfs/trunk/kawaForAndroid/kawa-2.4/gnu/kawa/slib/enums.scm", 73765), "/mnt/hgfs/trunk/kawaForAndroid/kawa-2.4/gnu/kawa/slib/enums.scm", 73762), "/mnt/hgfs/trunk/kawaForAndroid/kawa-2.4/gnu/kawa/slib/enums.scm", 73757), gnu.lists.LList.Empty, "/mnt/hgfs/trunk/kawaForAndroid/kawa-2.4/gnu/kawa/slib/enums.scm", 73757), "/mnt/hgfs/trunk/kawaForAndroid/kawa-2.4/gnu/kawa/slib/enums.scm", 73741), "/mnt/hgfs/trunk/kawaForAndroid/kawa-2.4/gnu/kawa/slib/enums.scm", 73733), PairWithPosition.make(Lit40, PairWithPosition.make(PairWithPosition.make(Lit34, PairWithPosition.make(gnu.mapping.Symbol.valueOf("private"), gnu.lists.LList.Empty, "/mnt/hgfs/trunk/kawaForAndroid/kawa-2.4/gnu/kawa/slib/enums.scm", 77838), "/mnt/hgfs/trunk/kawaForAndroid/kawa-2.4/gnu/kawa/slib/enums.scm", 77838), PairWithPosition.make(PairWithPosition.make(gnu.mapping.Symbol.valueOf("invoke-special"), PairWithPosition.make(Lit33, PairWithPosition.make(PairWithPosition.make(gnu.mapping.Symbol.valueOf("this"), gnu.lists.LList.Empty, "/mnt/hgfs/trunk/kawaForAndroid/kawa-2.4/gnu/kawa/slib/enums.scm", 81956), PairWithPosition.make(PairWithPosition.make(Lit34, PairWithPosition.make(Lit41, gnu.lists.LList.Empty, "/mnt/hgfs/trunk/kawaForAndroid/kawa-2.4/gnu/kawa/slib/enums.scm", 81964), "/mnt/hgfs/trunk/kawaForAndroid/kawa-2.4/gnu/kawa/slib/enums.scm", 81964), PairWithPosition.make(Lit42, PairWithPosition.make(Lit43, gnu.lists.LList.Empty, "/mnt/hgfs/trunk/kawaForAndroid/kawa-2.4/gnu/kawa/slib/enums.scm", 81975), "/mnt/hgfs/trunk/kawaForAndroid/kawa-2.4/gnu/kawa/slib/enums.scm", 81971), "/mnt/hgfs/trunk/kawaForAndroid/kawa-2.4/gnu/kawa/slib/enums.scm", 81963), "/mnt/hgfs/trunk/kawaForAndroid/kawa-2.4/gnu/kawa/slib/enums.scm", 81956), "/mnt/hgfs/trunk/kawaForAndroid/kawa-2.4/gnu/kawa/slib/enums.scm", 81941), "/mnt/hgfs/trunk/kawaForAndroid/kawa-2.4/gnu/kawa/slib/enums.scm", 81925), gnu.lists.LList.Empty, "/mnt/hgfs/trunk/kawaForAndroid/kawa-2.4/gnu/kawa/slib/enums.scm", 81925), "/mnt/hgfs/trunk/kawaForAndroid/kawa-2.4/gnu/kawa/slib/enums.scm", 77837), "/mnt/hgfs/trunk/kawaForAndroid/kawa-2.4/gnu/kawa/slib/enums.scm", 77829), "/mnt/hgfs/trunk/kawaForAndroid/kawa-2.4/gnu/kawa/slib/enums.scm", 73732);Lit1 = PairWithPosition.make(Lit37, PairWithPosition.make(Lit44, PairWithPosition.make(Lit40, PairWithPosition.make(Lit45, PairWithPosition.make(gnu.expr.Keyword.make("init"), gnu.lists.LList.Empty, "/mnt/hgfs/trunk/kawaForAndroid/kawa-2.4/gnu/kawa/slib/enums.scm", 57357), "/mnt/hgfs/trunk/kawaForAndroid/kawa-2.4/gnu/kawa/slib/enums.scm", 53289), "/mnt/hgfs/trunk/kawaForAndroid/kawa-2.4/gnu/kawa/slib/enums.scm", 53281), "/mnt/hgfs/trunk/kawaForAndroid/kawa-2.4/gnu/kawa/slib/enums.scm", 53273), "/mnt/hgfs/trunk/kawaForAndroid/kawa-2.4/gnu/kawa/slib/enums.scm", 53261);$instance = new enums();enums localEnums1 = $instance;define$Mnenum = kawa.lang.Macro.make(Lit5, new gnu.expr.ModuleMethod(localEnums1, 1, null, 4097), "gnu.kawa.slib.enums");enums localEnums2 = $instance;$Prvt$$Pcdefine$Mnenum = kawa.lang.Macro.make(Lit15, new gnu.expr.ModuleMethod(localEnums2, 2, null, 4097), "gnu.kawa.slib.enums");$runBody$(); } static final Object[] Lit36; static final gnu.expr.Keyword Lit37; static final PairWithPosition Lit38; static final PairWithPosition Lit39; static final gnu.expr.Keyword Lit40; static final gnu.mapping.SimpleSymbol Lit41; static final gnu.mapping.SimpleSymbol Lit42; static final gnu.mapping.SimpleSymbol Lit43; static final PairWithPosition Lit44; static final PairWithPosition Lit45 = PairWithPosition.make(enums.Lit34 = gnu.mapping.Symbol.valueOf("quote"), PairWithPosition.make(PairWithPosition.make(gnu.mapping.Symbol.valueOf("enum"), PairWithPosition.make(gnu.mapping.Symbol.valueOf("final"), gnu.lists.LList.Empty, "/mnt/hgfs/trunk/kawaForAndroid/kawa-2.4/gnu/kawa/slib/enums.scm", 253996), "/mnt/hgfs/trunk/kawaForAndroid/kawa-2.4/gnu/kawa/slib/enums.scm", 253990), gnu.lists.LList.Empty, "/mnt/hgfs/trunk/kawaForAndroid/kawa-2.4/gnu/kawa/slib/enums.scm", 253990), "/mnt/hgfs/trunk/kawaForAndroid/kawa-2.4/gnu/kawa/slib/enums.scm", 253990);
  







  static Object makeFieldDesc(gnu.mapping.Symbol t$Mnname, gnu.mapping.Symbol e$Mnname, int e$Mnval) { return kawa.lang.Quote.consX$V(new Object[] { e$Mnname, kawa.lang.Quote.append$V(new Object[] { Lit0, kawa.lang.Quote.consX$V(new Object[] { t$Mnname, kawa.lang.Quote.append$V(new Object[] { Lit1, gnu.lists.Pair.make(kawa.lang.Quote.consX$V(new Object[] { t$Mnname, kawa.lang.Quote.consX$V(new Object[] { kawa.lib.misc.symbol$To$String(e$Mnname), kawa.lang.Quote.consX$V(new Object[] { Integer.valueOf(e$Mnval), gnu.lists.LList.Empty }) }) }), gnu.lists.LList.Empty) }) }) }) }); }
  
  static PairWithPosition makeInit() { return Lit2; }
  







  static Object makeValues(gnu.mapping.Symbol t$Mnarr, gnu.lists.LList e$Mnnames)
  {
    return kawa.lang.Quote.append$V(new Object[] { Lit3, kawa.lang.Quote.consX$V(new Object[] { t$Mnarr, kawa.lang.Quote.append$V(new Object[] { Lit4, gnu.lists.Pair.make(kawa.lang.Quote.consX$V(new Object[] { t$Mnarr, kawa.lang.Quote.append$V(new Object[] { e$Mnnames, gnu.lists.LList.Empty }) }), gnu.lists.LList.Empty) }) }) });
  }
  

  static Object lambda1(Object form)
  {
    Object localObject = form;Object[] arrayOfObject = kawa.lang.SyntaxPattern.allocVars(5, null); if (Lit6.match(form, arrayOfObject, 0)) {
      localTemplateScope = kawa.lang.TemplateScope.make();
      localTemplateScope = kawa.lang.TemplateScope.make();
    }
    kawa.lang.TemplateScope localTemplateScope = kawa.lang.TemplateScope.make();
    


    localTemplateScope = kawa.lang.TemplateScope.make();return Lit13.match(form, arrayOfObject, 0) ? Lit14.execute(arrayOfObject, localTemplateScope) : Lit12.match(form, arrayOfObject, 0) ? kawa.lib.prim_syntax.reportSyntaxError(form, new Object[] { "no enum constants given" }) : Lit11.match(form, arrayOfObject, 0) ? kawa.lib.prim_syntax.reportSyntaxError(form, new Object[] { "no enum type name given" }) : Lit9.match(form, arrayOfObject, 0) ? Lit10.execute(arrayOfObject, localTemplateScope) : kawa.lib.std_syntax.isIdentifier(Lit7.execute(arrayOfObject, localTemplateScope)) ? Lit8.execute(arrayOfObject, localTemplateScope) : kawa.standard.syntax_case.error("syntax-case", form);
  }
  
  /* Error */
  static gnu.lists.LList mapNames(gnu.mapping.Symbol t$Mnname, gnu.lists.LList e$Mnnames, int i)
  {
    // Byte code:
    //   0: aload_1
    //   1: invokestatic 69	kawa/lib/lists:isNull	(Ljava/lang/Object;)Z
    //   4: ifeq +9 -> 13
    //   7: getstatic 39	gnu/lists/LList:Empty	Lgnu/lists/EmptyList;
    //   10: goto +56 -> 66
    //   13: aload_0
    //   14: aload_1
    //   15: dup
    //   16: astore_3
    //   17: checkcast 47	gnu/lists/Pair
    //   20: invokestatic 82	kawa/lib/lists:car	(Lgnu/lists/Pair;)Ljava/lang/Object;
    //   23: ldc 84
    //   25: invokestatic 90	gnu/mapping/Promise:force	(Ljava/lang/Object;Ljava/lang/Class;)Ljava/lang/Object;
    //   28: dup
    //   29: astore_3
    //   30: checkcast 84	gnu/mapping/Symbol
    //   33: iload_2
    //   34: invokestatic 96	gnu/kawa/slib/enums:makeFieldDesc	(Lgnu/mapping/Symbol;Lgnu/mapping/Symbol;I)Ljava/lang/Object;
    //   37: aload_0
    //   38: aload_1
    //   39: dup
    //   40: astore_3
    //   41: checkcast 47	gnu/lists/Pair
    //   44: invokestatic 100	kawa/lib/lists:cdr	(Lgnu/lists/Pair;)Ljava/lang/Object;
    //   47: ldc 35
    //   49: invokestatic 90	gnu/mapping/Promise:force	(Ljava/lang/Object;Ljava/lang/Class;)Ljava/lang/Object;
    //   52: dup
    //   53: astore_3
    //   54: checkcast 35	gnu/lists/LList
    //   57: iload_2
    //   58: iconst_1
    //   59: iadd
    //   60: invokestatic 106	gnu/kawa/slib/enums:mapNames	(Lgnu/mapping/Symbol;Lgnu/lists/LList;I)Lgnu/lists/LList;
    //   63: invokestatic 109	kawa/lib/lists:cons	(Ljava/lang/Object;Ljava/lang/Object;)Lgnu/lists/Pair;
    //   66: areturn
    //   67: new 73	gnu/mapping/WrongType
    //   70: dup_x1
    //   71: swap
    //   72: ldc 75
    //   74: iconst_1
    //   75: aload_3
    //   76: invokespecial 79	gnu/mapping/WrongType:<init>	(Ljava/lang/ClassCastException;Ljava/lang/String;ILjava/lang/Object;)V
    //   79: athrow
    //   80: new 73	gnu/mapping/WrongType
    //   83: dup_x1
    //   84: swap
    //   85: ldc 92
    //   87: iconst_1
    //   88: aload_3
    //   89: invokespecial 79	gnu/mapping/WrongType:<init>	(Ljava/lang/ClassCastException;Ljava/lang/String;ILjava/lang/Object;)V
    //   92: athrow
    //   93: new 73	gnu/mapping/WrongType
    //   96: dup_x1
    //   97: swap
    //   98: ldc 98
    //   100: iconst_1
    //   101: aload_3
    //   102: invokespecial 79	gnu/mapping/WrongType:<init>	(Ljava/lang/ClassCastException;Ljava/lang/String;ILjava/lang/Object;)V
    //   105: athrow
    //   106: new 73	gnu/mapping/WrongType
    //   109: dup_x1
    //   110: swap
    //   111: ldc 102
    //   113: iconst_1
    //   114: aload_3
    //   115: invokespecial 79	gnu/mapping/WrongType:<init>	(Ljava/lang/ClassCastException;Ljava/lang/String;ILjava/lang/Object;)V
    //   118: athrow
    // Line number table:
    //   Java source line #43	-> byte code offset #0
    //   Java source line #44	-> byte code offset #0
    //   Java source line #45	-> byte code offset #13
    //   Java source line #46	-> byte code offset #37
    //   Java source line #45	-> byte code offset #67
    //   Java source line #46	-> byte code offset #93
    // Local variable table:
    //   start	length	slot	name	signature
    //   0	66	0	t$Mnname	gnu.mapping.Symbol
    //   0	66	1	e$Mnnames	gnu.lists.LList
    //   0	66	2	i	int
    //   16	99	3	localObject	Object
    //   67	1	4	localClassCastException1	ClassCastException
    //   80	1	5	localClassCastException2	ClassCastException
    //   93	1	6	localClassCastException3	ClassCastException
    //   106	1	7	localClassCastException4	ClassCastException
    // Exception table:
    //   from	to	target	type
    //   17	20	67	java/lang/ClassCastException
    //   30	33	80	java/lang/ClassCastException
    //   41	44	93	java/lang/ClassCastException
    //   54	57	106	java/lang/ClassCastException
  }
  
  public enums()
  {
    gnu.expr.ModuleInfo.register(this);
  }
  
  /* Error */
  static Object lambda2(Object form)
  {
    // Byte code:
    //   0: aload_0
    //   1: astore_1
    //   2: iconst_4
    //   3: aconst_null
    //   4: invokestatic 135	kawa/lang/SyntaxPattern:allocVars	(I[Ljava/lang/Object;)[Ljava/lang/Object;
    //   7: astore_2
    //   8: getstatic 226	gnu/kawa/slib/enums:Lit16	Lkawa/lang/SyntaxPattern;
    //   11: aload_0
    //   12: aload_2
    //   13: iconst_0
    //   14: invokevirtual 145	kawa/lang/Pattern:match	(Ljava/lang/Object;[Ljava/lang/Object;I)Z
    //   17: ifeq +474 -> 491
    //   20: invokestatic 150	kawa/lang/TemplateScope:make	()Lkawa/lang/TemplateScope;
    //   23: astore 4
    //   25: getstatic 229	gnu/kawa/slib/enums:Lit17	Lkawa/lang/SyntaxTemplate;
    //   28: aload_2
    //   29: aload 4
    //   31: invokevirtual 160	kawa/lang/SyntaxTemplate:execute	([Ljava/lang/Object;Lkawa/lang/TemplateScope;)Ljava/lang/Object;
    //   34: ldc 84
    //   36: invokestatic 90	gnu/mapping/Promise:force	(Ljava/lang/Object;Ljava/lang/Class;)Ljava/lang/Object;
    //   39: dup
    //   40: astore 5
    //   42: checkcast 84	gnu/mapping/Symbol
    //   45: astore_3
    //   46: iconst_2
    //   47: anewarray 12	java/lang/Object
    //   50: dup
    //   51: iconst_0
    //   52: aload_3
    //   53: invokestatic 27	kawa/lib/misc:symbol$To$String	(Lgnu/mapping/Symbol;)Ljava/lang/String;
    //   56: aastore
    //   57: dup
    //   58: iconst_1
    //   59: ldc -23
    //   61: aastore
    //   62: invokestatic 239	kawa/lib/strings:stringAppend	([Ljava/lang/Object;)Lgnu/lists/FString;
    //   65: invokestatic 243	kawa/lib/misc:string$To$Symbol	(Ljava/lang/CharSequence;)Lgnu/mapping/SimpleSymbol;
    //   68: astore 4
    //   70: invokestatic 150	kawa/lang/TemplateScope:make	()Lkawa/lang/TemplateScope;
    //   73: astore 6
    //   75: getstatic 246	gnu/kawa/slib/enums:Lit18	Lkawa/lang/SyntaxTemplate;
    //   78: aload_2
    //   79: aload 6
    //   81: invokevirtual 160	kawa/lang/SyntaxTemplate:execute	([Ljava/lang/Object;Lkawa/lang/TemplateScope;)Ljava/lang/Object;
    //   84: ldc 35
    //   86: invokestatic 90	gnu/mapping/Promise:force	(Ljava/lang/Object;Ljava/lang/Class;)Ljava/lang/Object;
    //   89: dup
    //   90: astore 7
    //   92: checkcast 35	gnu/lists/LList
    //   95: astore 5
    //   97: aload 5
    //   99: invokevirtual 252	gnu/lists/LList:size	()I
    //   102: pop
    //   103: aload_3
    //   104: aload 5
    //   106: iconst_0
    //   107: invokestatic 106	gnu/kawa/slib/enums:mapNames	(Lgnu/mapping/Symbol;Lgnu/lists/LList;I)Lgnu/lists/LList;
    //   110: astore 6
    //   112: invokestatic 256	gnu/kawa/slib/enums:makeInit	()Lgnu/lists/PairWithPosition;
    //   115: astore 7
    //   117: aload 4
    //   119: aload 5
    //   121: invokestatic 260	gnu/kawa/slib/enums:makeValues	(Lgnu/mapping/Symbol;Lgnu/lists/LList;)Ljava/lang/Object;
    //   124: ldc 35
    //   126: invokestatic 90	gnu/mapping/Promise:force	(Ljava/lang/Object;Ljava/lang/Class;)Ljava/lang/Object;
    //   129: dup
    //   130: astore 9
    //   132: checkcast 35	gnu/lists/LList
    //   135: astore 8
    //   137: invokestatic 150	kawa/lang/TemplateScope:make	()Lkawa/lang/TemplateScope;
    //   140: astore 10
    //   142: getstatic 265	gnu/kawa/slib/enums:Lit19	Lkawa/lang/SyntaxTemplate;
    //   145: aload_2
    //   146: aload 10
    //   148: invokevirtual 160	kawa/lang/SyntaxTemplate:execute	([Ljava/lang/Object;Lkawa/lang/TemplateScope;)Ljava/lang/Object;
    //   151: ldc 35
    //   153: invokestatic 90	gnu/mapping/Promise:force	(Ljava/lang/Object;Ljava/lang/Class;)Ljava/lang/Object;
    //   156: dup
    //   157: astore 11
    //   159: checkcast 35	gnu/lists/LList
    //   162: astore 9
    //   164: invokestatic 150	kawa/lang/TemplateScope:make	()Lkawa/lang/TemplateScope;
    //   167: astore 11
    //   169: getstatic 270	gnu/kawa/slib/enums:Lit20	Lkawa/lang/SyntaxTemplate;
    //   172: aload_2
    //   173: aload 11
    //   175: invokevirtual 160	kawa/lang/SyntaxTemplate:execute	([Ljava/lang/Object;Lkawa/lang/TemplateScope;)Ljava/lang/Object;
    //   178: ldc 35
    //   180: invokestatic 90	gnu/mapping/Promise:force	(Ljava/lang/Object;Ljava/lang/Class;)Ljava/lang/Object;
    //   183: dup
    //   184: astore 12
    //   186: checkcast 35	gnu/lists/LList
    //   189: astore 10
    //   191: invokestatic 150	kawa/lang/TemplateScope:make	()Lkawa/lang/TemplateScope;
    //   194: astore 11
    //   196: iconst_2
    //   197: anewarray 12	java/lang/Object
    //   200: dup
    //   201: iconst_0
    //   202: getstatic 275	gnu/kawa/slib/enums:Lit21	Lkawa/lang/SyntaxTemplate;
    //   205: aload_2
    //   206: aload 11
    //   208: invokevirtual 160	kawa/lang/SyntaxTemplate:execute	([Ljava/lang/Object;Lkawa/lang/TemplateScope;)Ljava/lang/Object;
    //   211: aastore
    //   212: dup
    //   213: iconst_1
    //   214: iconst_2
    //   215: anewarray 12	java/lang/Object
    //   218: dup
    //   219: iconst_0
    //   220: aload_0
    //   221: aload_3
    //   222: invokestatic 279	kawa/lib/std_syntax:datum$To$SyntaxObject	(Ljava/lang/Object;Ljava/lang/Object;)Ljava/lang/Object;
    //   225: aastore
    //   226: dup
    //   227: iconst_1
    //   228: iconst_2
    //   229: anewarray 12	java/lang/Object
    //   232: dup
    //   233: iconst_0
    //   234: getstatic 282	gnu/kawa/slib/enums:Lit22	Lkawa/lang/SyntaxTemplate;
    //   237: aload_2
    //   238: aload 11
    //   240: invokevirtual 160	kawa/lang/SyntaxTemplate:execute	([Ljava/lang/Object;Lkawa/lang/TemplateScope;)Ljava/lang/Object;
    //   243: aastore
    //   244: dup
    //   245: iconst_1
    //   246: iconst_2
    //   247: anewarray 12	java/lang/Object
    //   250: dup
    //   251: iconst_0
    //   252: aload_0
    //   253: aload 9
    //   255: invokestatic 279	kawa/lib/std_syntax:datum$To$SyntaxObject	(Ljava/lang/Object;Ljava/lang/Object;)Ljava/lang/Object;
    //   258: aastore
    //   259: dup
    //   260: iconst_1
    //   261: iconst_2
    //   262: anewarray 12	java/lang/Object
    //   265: dup
    //   266: iconst_0
    //   267: aload_0
    //   268: aload 7
    //   270: invokestatic 279	kawa/lib/std_syntax:datum$To$SyntaxObject	(Ljava/lang/Object;Ljava/lang/Object;)Ljava/lang/Object;
    //   273: aastore
    //   274: dup
    //   275: iconst_1
    //   276: iconst_2
    //   277: anewarray 12	java/lang/Object
    //   280: dup
    //   281: iconst_0
    //   282: aload_0
    //   283: aload 8
    //   285: invokestatic 279	kawa/lib/std_syntax:datum$To$SyntaxObject	(Ljava/lang/Object;Ljava/lang/Object;)Ljava/lang/Object;
    //   288: aastore
    //   289: dup
    //   290: iconst_1
    //   291: iconst_2
    //   292: anewarray 12	java/lang/Object
    //   295: dup
    //   296: iconst_0
    //   297: getstatic 285	gnu/kawa/slib/enums:Lit23	Lkawa/lang/SyntaxTemplate;
    //   300: aload_2
    //   301: aload 11
    //   303: invokevirtual 160	kawa/lang/SyntaxTemplate:execute	([Ljava/lang/Object;Lkawa/lang/TemplateScope;)Ljava/lang/Object;
    //   306: aastore
    //   307: dup
    //   308: iconst_1
    //   309: iconst_2
    //   310: anewarray 12	java/lang/Object
    //   313: dup
    //   314: iconst_0
    //   315: aload_0
    //   316: aload_3
    //   317: invokestatic 279	kawa/lib/std_syntax:datum$To$SyntaxObject	(Ljava/lang/Object;Ljava/lang/Object;)Ljava/lang/Object;
    //   320: aastore
    //   321: dup
    //   322: iconst_1
    //   323: iconst_2
    //   324: anewarray 12	java/lang/Object
    //   327: dup
    //   328: iconst_0
    //   329: getstatic 288	gnu/kawa/slib/enums:Lit24	Lkawa/lang/SyntaxTemplate;
    //   332: aload_2
    //   333: aload 11
    //   335: invokevirtual 160	kawa/lang/SyntaxTemplate:execute	([Ljava/lang/Object;Lkawa/lang/TemplateScope;)Ljava/lang/Object;
    //   338: aastore
    //   339: dup
    //   340: iconst_1
    //   341: iconst_2
    //   342: anewarray 12	java/lang/Object
    //   345: dup
    //   346: iconst_0
    //   347: getstatic 291	gnu/kawa/slib/enums:Lit25	Lkawa/lang/SyntaxTemplate;
    //   350: aload_2
    //   351: aload 11
    //   353: invokevirtual 160	kawa/lang/SyntaxTemplate:execute	([Ljava/lang/Object;Lkawa/lang/TemplateScope;)Ljava/lang/Object;
    //   356: aastore
    //   357: dup
    //   358: iconst_1
    //   359: iconst_2
    //   360: anewarray 12	java/lang/Object
    //   363: dup
    //   364: iconst_0
    //   365: aload_0
    //   366: aload_3
    //   367: invokestatic 279	kawa/lib/std_syntax:datum$To$SyntaxObject	(Ljava/lang/Object;Ljava/lang/Object;)Ljava/lang/Object;
    //   370: aastore
    //   371: dup
    //   372: iconst_1
    //   373: getstatic 294	gnu/kawa/slib/enums:Lit26	Lkawa/lang/SyntaxTemplate;
    //   376: aload_2
    //   377: aload 11
    //   379: invokevirtual 160	kawa/lang/SyntaxTemplate:execute	([Ljava/lang/Object;Lkawa/lang/TemplateScope;)Ljava/lang/Object;
    //   382: aastore
    //   383: invokestatic 45	kawa/lang/Quote:consX$V	([Ljava/lang/Object;)Ljava/lang/Object;
    //   386: aastore
    //   387: invokestatic 54	kawa/lang/Quote:append$V	([Ljava/lang/Object;)Ljava/lang/Object;
    //   390: getstatic 297	gnu/kawa/slib/enums:Lit27	Lkawa/lang/SyntaxTemplate;
    //   393: aload_2
    //   394: aload 11
    //   396: invokevirtual 160	kawa/lang/SyntaxTemplate:execute	([Ljava/lang/Object;Lkawa/lang/TemplateScope;)Ljava/lang/Object;
    //   399: invokestatic 51	gnu/lists/Pair:make	(Ljava/lang/Object;Ljava/lang/Object;)Lgnu/lists/Pair;
    //   402: aastore
    //   403: invokestatic 54	kawa/lang/Quote:append$V	([Ljava/lang/Object;)Ljava/lang/Object;
    //   406: aastore
    //   407: invokestatic 45	kawa/lang/Quote:consX$V	([Ljava/lang/Object;)Ljava/lang/Object;
    //   410: aastore
    //   411: invokestatic 54	kawa/lang/Quote:append$V	([Ljava/lang/Object;)Ljava/lang/Object;
    //   414: iconst_2
    //   415: anewarray 12	java/lang/Object
    //   418: dup
    //   419: iconst_0
    //   420: aload_0
    //   421: aload 6
    //   423: invokestatic 279	kawa/lib/std_syntax:datum$To$SyntaxObject	(Ljava/lang/Object;Ljava/lang/Object;)Ljava/lang/Object;
    //   426: aastore
    //   427: dup
    //   428: iconst_1
    //   429: iconst_2
    //   430: anewarray 12	java/lang/Object
    //   433: dup
    //   434: iconst_0
    //   435: aload_0
    //   436: aload 10
    //   438: invokestatic 279	kawa/lib/std_syntax:datum$To$SyntaxObject	(Ljava/lang/Object;Ljava/lang/Object;)Ljava/lang/Object;
    //   441: aastore
    //   442: dup
    //   443: iconst_1
    //   444: getstatic 300	gnu/kawa/slib/enums:Lit28	Lkawa/lang/SyntaxTemplate;
    //   447: aload_2
    //   448: aload 11
    //   450: invokevirtual 160	kawa/lang/SyntaxTemplate:execute	([Ljava/lang/Object;Lkawa/lang/TemplateScope;)Ljava/lang/Object;
    //   453: aastore
    //   454: invokestatic 54	kawa/lang/Quote:append$V	([Ljava/lang/Object;)Ljava/lang/Object;
    //   457: aastore
    //   458: invokestatic 54	kawa/lang/Quote:append$V	([Ljava/lang/Object;)Ljava/lang/Object;
    //   461: invokestatic 51	gnu/lists/Pair:make	(Ljava/lang/Object;Ljava/lang/Object;)Lgnu/lists/Pair;
    //   464: aastore
    //   465: invokestatic 45	kawa/lang/Quote:consX$V	([Ljava/lang/Object;)Ljava/lang/Object;
    //   468: aastore
    //   469: invokestatic 45	kawa/lang/Quote:consX$V	([Ljava/lang/Object;)Ljava/lang/Object;
    //   472: aastore
    //   473: invokestatic 54	kawa/lang/Quote:append$V	([Ljava/lang/Object;)Ljava/lang/Object;
    //   476: aastore
    //   477: invokestatic 54	kawa/lang/Quote:append$V	([Ljava/lang/Object;)Ljava/lang/Object;
    //   480: aastore
    //   481: invokestatic 45	kawa/lang/Quote:consX$V	([Ljava/lang/Object;)Ljava/lang/Object;
    //   484: aastore
    //   485: invokestatic 54	kawa/lang/Quote:append$V	([Ljava/lang/Object;)Ljava/lang/Object;
    //   488: goto +9 -> 497
    //   491: ldc -58
    //   493: aload_0
    //   494: invokestatic 204	kawa/standard/syntax_case:error	(Ljava/lang/String;Ljava/lang/Object;)Ljava/lang/Object;
    //   497: areturn
    //   498: new 73	gnu/mapping/WrongType
    //   501: dup_x1
    //   502: swap
    //   503: ldc -25
    //   505: bipush -2
    //   507: aload 5
    //   509: invokespecial 79	gnu/mapping/WrongType:<init>	(Ljava/lang/ClassCastException;Ljava/lang/String;ILjava/lang/Object;)V
    //   512: athrow
    //   513: new 73	gnu/mapping/WrongType
    //   516: dup_x1
    //   517: swap
    //   518: ldc -8
    //   520: bipush -2
    //   522: aload 7
    //   524: invokespecial 79	gnu/mapping/WrongType:<init>	(Ljava/lang/ClassCastException;Ljava/lang/String;ILjava/lang/Object;)V
    //   527: athrow
    //   528: new 73	gnu/mapping/WrongType
    //   531: dup_x1
    //   532: swap
    //   533: ldc_w 262
    //   536: bipush -2
    //   538: aload 9
    //   540: invokespecial 79	gnu/mapping/WrongType:<init>	(Ljava/lang/ClassCastException;Ljava/lang/String;ILjava/lang/Object;)V
    //   543: athrow
    //   544: new 73	gnu/mapping/WrongType
    //   547: dup_x1
    //   548: swap
    //   549: ldc_w 267
    //   552: bipush -2
    //   554: aload 11
    //   556: invokespecial 79	gnu/mapping/WrongType:<init>	(Ljava/lang/ClassCastException;Ljava/lang/String;ILjava/lang/Object;)V
    //   559: athrow
    //   560: new 73	gnu/mapping/WrongType
    //   563: dup_x1
    //   564: swap
    //   565: ldc_w 272
    //   568: bipush -2
    //   570: aload 12
    //   572: invokespecial 79	gnu/mapping/WrongType:<init>	(Ljava/lang/ClassCastException;Ljava/lang/String;ILjava/lang/Object;)V
    //   575: athrow
    // Line number table:
    //   Java source line #49	-> byte code offset #0
    //   Java source line #51	-> byte code offset #20
    //   Java source line #52	-> byte code offset #46
    //   Java source line #53	-> byte code offset #52
    //   Java source line #51	-> byte code offset #70
    //   Java source line #54	-> byte code offset #70
    //   Java source line #51	-> byte code offset #97
    //   Java source line #55	-> byte code offset #97
    //   Java source line #51	-> byte code offset #103
    //   Java source line #56	-> byte code offset #103
    //   Java source line #51	-> byte code offset #112
    //   Java source line #57	-> byte code offset #112
    //   Java source line #51	-> byte code offset #117
    //   Java source line #58	-> byte code offset #117
    //   Java source line #51	-> byte code offset #137
    //   Java source line #59	-> byte code offset #137
    //   Java source line #51	-> byte code offset #164
    //   Java source line #60	-> byte code offset #164
    //   Java source line #61	-> byte code offset #191
    //   Java source line #63	-> byte code offset #252
    //   Java source line #64	-> byte code offset #267
    //   Java source line #65	-> byte code offset #282
    //   Java source line #66	-> byte code offset #315
    //   Java source line #68	-> byte code offset #365
    //   Java source line #69	-> byte code offset #420
    //   Java source line #70	-> byte code offset #435
    //   Java source line #51	-> byte code offset #498
    //   Java source line #54	-> byte code offset #513
    //   Java source line #58	-> byte code offset #528
    //   Java source line #59	-> byte code offset #544
    //   Java source line #60	-> byte code offset #560
    // Local variable table:
    //   start	length	slot	name	signature
    //   0	497	0	form	Object
    //   1	1	1	localObject1	Object
    //   7	441	2	arrayOfObject	Object[]
    //   45	322	3	t$Mnname	gnu.mapping.Symbol
    //   23	7	4	localTemplateScope1	kawa.lang.TemplateScope
    //   68	50	4	t$Mnarr	Object
    //   40	1	5	localObject2	Object
    //   95	413	5	e$Mnnames	gnu.lists.LList
    //   73	7	6	localTemplateScope2	kawa.lang.TemplateScope
    //   110	312	6	field$Mndescs	gnu.lists.LList
    //   90	1	7	localObject3	Object
    //   115	408	7	init	Object
    //   135	149	8	values$Mnmethod	gnu.lists.LList
    //   130	1	9	localObject4	Object
    //   162	377	9	opts	gnu.lists.LList
    //   140	7	10	localTemplateScope3	kawa.lang.TemplateScope
    //   189	248	10	other$Mndefs	gnu.lists.LList
    //   157	398	11	localObject5	Object
    //   184	387	12	localObject6	Object
    //   498	1	19	localClassCastException1	ClassCastException
    //   513	1	20	localClassCastException2	ClassCastException
    //   528	1	21	localClassCastException3	ClassCastException
    //   544	1	22	localClassCastException4	ClassCastException
    //   560	1	23	localClassCastException5	ClassCastException
    // Exception table:
    //   from	to	target	type
    //   42	45	498	java/lang/ClassCastException
    //   92	95	513	java/lang/ClassCastException
    //   132	135	528	java/lang/ClassCastException
    //   159	162	544	java/lang/ClassCastException
    //   186	189	560	java/lang/ClassCastException
  }
  
  public int match1(gnu.expr.ModuleMethod paramModuleMethod, Object paramObject, gnu.mapping.CallContext paramCallContext)
  {
    switch (selector)
    {
    case 2: 
      value1 = paramObject;
      proc = paramModuleMethod;
      pc = 1;
      return 0;
    case 1: 
      value1 = paramObject;
      proc = paramModuleMethod;
      pc = 1;
      return 0;
    }
    return super.match1(paramModuleMethod, paramObject, paramCallContext);
  }
  
  public void apply(gnu.mapping.CallContext paramCallContext)
  {
    gnu.expr.ModuleMethod.applyError();
  }
  
  public Object apply1(gnu.expr.ModuleMethod paramModuleMethod, Object paramObject)
  {
    switch (selector)
    {
    case 1: 
      return lambda1(paramObject);
    case 2: 
      return lambda2(paramObject);
    }
    return super.apply1(paramModuleMethod, paramObject);
  }
}
